[{"content": "| Model | Subject Consist. | BG. Consis. | Temp. Flick. | Motion Smooth. | Aesthe. Quality | Imag. Quality | Dyna. Degree | Quality Score | Total Score | Max. Raw Frames |\n|---|---|---|---|---|---|---|---|---|---|---| \n| Runway Gen-3 [47] | 97.10% | 96.62% | 98.61% | 99.23% | 60.14% | **63.34%** | **66.82%** | **84.11%** | **82.32%** | 256 |\n| Kling [24] | **98.33%** | 97.60% | 99.30% | **99.40%** | 46.94% | 61.21% | 65.62% | 83.39% | 81.85% | 313 |\n| OpenSora V1.2 [75] | 96.75% | **97.61%** | **99.53%** | 98.50% | 42.39% | 56.85% | 63.34% | 81.35% | 79.76% | 408 |\n| LinGen | 98.30% | 97.60% | 99.26% | 98.58% | **63.67%** | 60.55% | 63.36% | 83.77% | 81.76% | **1088** |", "caption": "Table 1: Automatic evaluation of LinGen on VBench-Long. Quality Score measures the quality of generated videos and Semantic Score measures text-video alignment. Total Score is their weighted sum. Higher values indicate better performance for all these metrics. LinGen is comparable to state-of-the-art commercial models (i.e., Gen-3 and Kling) and outperforms the typical open-source model (i.e., OpenSora) significantly. LinGen not only achieves a much higher maximum number of raw frames but also does so on a single GPU.", "description": "VBench-Long \ubca4\uce58\ub9c8\ud06c\uc5d0\uc11c LinGen, Runway Gen-3, Kling, OpenSora V1.2 \ubaa8\ub378\uc758 \ube44\ub514\uc624 \uc0dd\uc131 \ud488\uc9c8(Quality Score), \ud14d\uc2a4\ud2b8-\ube44\ub514\uc624 \uc815\ud569\uc131(Semantic Score), \uc885\ud569 \uc810\uc218(Total Score), \uadf8\ub9ac\uace0 \ucd5c\ub300 \uc0dd\uc131 \uac00\ub2a5\ud55c \uc6d0\uc2dc \ud504\ub808\uc784 \uc218\ub97c \ube44\uad50\ud55c \ud45c\uc785\ub2c8\ub2e4. LinGen\uc740 \uc0c1\uc6a9 SOTA \ubaa8\ub378\uacfc \ube44\uc2b7\ud55c \ud488\uc9c8\uc744 \ubcf4\uc5ec\uc8fc\uba74\uc11c, \uc624\ud508\uc18c\uc2a4 \ubaa8\ub378\ubcf4\ub2e4 \ud6e8\uc52c \ub6f0\uc5b4\ub09c \uc131\ub2a5\uc744 \ub2ec\uc131\ud588\uace0, \ud2b9\ud788 \ub2e8\uc77c GPU\uc5d0\uc11c \ub354 \ub9ce\uc740 \uc6d0\uc2dc \ud504\ub808\uc784\uc744 \uc0dd\uc131\ud560 \uc218 \uc788\ub2e4\ub294 \uc810\uc5d0\uc11c \ud6a8\uc728\uc131\uc774 \ub3cb\ubcf4\uc785\ub2c8\ub2e4.", "section": "4. Experiments"}, {"content": "| Model | Object\nClass | Multiple\nObjects | Human\nAction | Color | Spatial\nRelatio. | Scene | Appear. | Temp. | Overall | Semantic\nScore |\n|---|---|---|---|---|---|---|---|---|---|---| \n| Runway Gen-3 [47] | 87.81% | 53.64% | 96.40% | 80.90% | 65.09% | **54.57%** | **24.31%** | **24.71%** | 26.69% | 75.17% |\n| Kling [24] | 87.24% | **68.05%** | 93.40% | 89.90% | **73.03%** | 50.86% | 19.62% | 24.17% | 26.42% | **75.68%** |\n| OpenSora V1.2 [75] | 82.22% | 51.83% | 91.20% | **90.08%** | 68.56% | 42.44% | 23.95% | 24.54% | **26.85%** | 73.39% |\n| LinGen | **90.98%** | 55.15% | **97.50%** | 83.95% | 58.15% | 53.51% | 21.08% | 24.29% | 26.32% | 73.73% |", "caption": "Table 2: Latency of the LinGen default setting and variant settings when generating 512p 17s videos.", "description": "LinGen\uc758 \uae30\ubcf8 \uc124\uc815\uacfc \ub2e4\uc591\ud55c \ubcc0\ud615 \uc124\uc815\uc5d0\uc11c 512p \ud574\uc0c1\ub3c4, 17\ucd08 \uae38\uc774\uc758 \ube44\ub514\uc624\ub97c \uc0dd\uc131\ud560 \ub54c\uc758 \uc9c0\uc5f0 \uc2dc\uac04\uc744 \ube44\uad50\ud55c \ud45c\uc785\ub2c8\ub2e4. TESA \ube14\ub85d, RMS, Zigzag \uc2a4\uce94, Mamba, MA-branch, \ub9ac\ubdf0 \ud1a0\ud070\uc758 \uc720\ubb34\uc5d0 \ub530\ub978 LinGen\uc758 \uc9c0\uc5f0 \uc2dc\uac04 \ubcc0\ud654\ub97c \ubcf4\uc5ec\uc90d\ub2c8\ub2e4. \uac01 \uc124\uc815 \ubcc0\ud654\uc5d0 \ub530\ub978 \uc9c0\uc5f0 \uc2dc\uac04\uc758 \ucc28\uc774(\ucd08)\ub3c4 \ud568\uaed8 \ud45c\uc2dc\ub418\uc5b4 \uc788\uc2b5\ub2c8\ub2e4.", "section": "4.5. Ablation Experiments"}, {"content": "| Model | Latency/s |\n|---|---| \n| LinGen (default setting) | 102 |\n| LinGen w/o TESA | 94 (-8) |\n| LinGen w/o RMS | 99 (-3) |\n| LinGen w/ Zigzag | 144 (+42) |\n| LinGen w/ Mamba | 127 (+25) |\n| LinGen w/o MA-branch | 65 (-37) |\n| LinGen w/o review tokens | 98 (-4) |", "caption": "Table 3: A more complete VBench-Long leaderboard. Quality Score measures the quality of generated videos and Semantic Score measures text-video alignment. Total Score represents their weighted sum. Higher values indicate better performance for all these metrics. LinGen can be seen to be comparable to state-of-the-art commercial models (i.e., Gen-3 and Kling) and significantly outperform typical open-source models.", "description": "VBench-Long \ub9ac\ub354\ubcf4\ub4dc\ub294 \uc0dd\uc131\ub41c \ube44\ub514\uc624\uc758 \ud488\uc9c8(Quality Score)\uacfc \ud14d\uc2a4\ud2b8-\ube44\ub514\uc624 \uc815\ub82c(Semantic Score)\uc744 \uce21\uc815\ud558\uc5ec \uc885\ud569 \uc810\uc218(Total Score)\ub97c \uacc4\uc0b0\ud569\ub2c8\ub2e4. LinGen\uc740 Gen-3, Kling\uacfc \uac19\uc740 \ucd5c\ucca8\ub2e8 \uc0c1\uc6a9 \ubaa8\ub378\uacfc \ube44\uc2b7\ud55c \uc131\ub2a5\uc744 \ubcf4\uc774\uba70, \uc77c\ubc18\uc801\uc778 \uc624\ud508 \uc18c\uc2a4 \ubaa8\ub378\ubcf4\ub2e4 \ud6e8\uc52c \ub6f0\uc5b4\ub09c \uc131\ub2a5\uc744 \ubcf4\uc785\ub2c8\ub2e4.", "section": "4.3. Comparing Quality to State-of-the-Art Models"}, {"content": "| Model | Subject Consist. | BG. Consis. | Temp. Flick. | Motion Smooth. | Aesthe. Quality | Imag. Quality | Dyna. Degree | Quality Score | Total Score | Max. Raw Frames | \n|---|---|---|---|---|---|---|---|---|---|---| \n| Runway Gen-3 [47] | 97.10% | 96.62% | 98.61% | 99.23% | 60.14% | **63.34%** | **66.82%** | **84.11%** | **82.32%** | 256 | \n| Kling [24] | **98.33%** | 97.60% | 99.30% | **99.40%** | 46.94% | 61.21% | 65.62% | 83.39% | 81.85% | 313 | \n| CogVideoX-5B [71] | 96.23% | 96.52% | 98.66% | 96.92% | **70.97%** | 61.98% | 62.90% | 82.75% | 81.61% | 48 | \n| Mochi-1 [57] | 96.99% | 97.28% | 99.40% | 99.02% | 61.85% | 56.94% | 60.64% | 82.64% | 80.13% | 163 | \n| OpenSora V1.2 [75] | 96.75% | **97.61%** | **99.53%** | 98.50% | 42.39% | 56.85% | 63.34% | 81.35% | 79.76% | 408 | \n| Mira [21] | 96.23% | 96.92% | 98.29% | 97.54% | 60.33% | 42.51% | 60.16% | 78.78% | 71.87% | 60 | \n| LinGen | 98.30% | 97.60% | 99.26% | 98.58% | 63.67% | 60.55% | 63.36% | 83.77% | 81.76% | **1088** |", "caption": "Table 4: Automatic evaluation of LinGen on VBench-standard. Quality Score measures the quality of generated videos and Semantic Score measures text-video alignment. Total Score represents their weighted sum. Higher values indicate better performance for all these metrics.", "description": "VBench-standard \ubca4\uce58\ub9c8\ud06c\uc5d0\uc11c LinGen\uacfc \ub2e4\ub978 \ubaa8\ub378\uc758 \uc131\ub2a5\uc744 \ube44\uad50\ud55c \ud45c\uc785\ub2c8\ub2e4. \ud488\uc9c8 \uc810\uc218, \uc758\ubbf8 \uc810\uc218, \ucd1d\uc810\uc218\ub97c \uc0ac\uc6a9\ud558\uc5ec \uc0dd\uc131\ub41c \ube44\ub514\uc624\uc758 \ud488\uc9c8\uacfc \ud14d\uc2a4\ud2b8-\ube44\ub514\uc624 \uc815\ub82c\uc744 \ud3c9\uac00\ud569\ub2c8\ub2e4. \uc810\uc218\uac00 \ub192\uc744\uc218\ub85d \uc131\ub2a5\uc774 \uc88b\ub2e4\ub294 \uac83\uc744 \uc758\ubbf8\ud558\uba70, LinGen\uc740 \ub300\ubd80\ubd84\uc758 \uc9c0\ud45c\uc5d0\uc11c \ub2e4\ub978 \uc624\ud508 \uc18c\uc2a4 \ubaa8\ub378\ubcf4\ub2e4 \uc6b0\uc218\ud55c \uc131\ub2a5\uc744 \ubcf4\uc785\ub2c8\ub2e4.", "section": "4.3. Comparing Quality to State-of-the-Art Models"}, {"content": "| Model | Object Class | Multiple Objects | Human Action | Color | Spatial Relatio. | Scene | Appear. Style | Temp. Style | Overall Consist. | Semantic Score |\n|---|---|---|---|---|---|---|---|---|---|---| \n| Runway Gen-3 [47] | 87.81% | 53.64% | 96.40% | 80.90% | 65.09% | **54.57%** | 24.31% | **24.71%** | 26.69% | 75.17% |\n| Kling [24] | 87.24% | **68.05%** | 93.40% | 89.90% | **73.03%** | 50.86% | 19.62% | 24.17% | 26.42% | 75.68% |\n| CogVideoX-5B [71] | 85.23% | 62.11% | **99.40%** | 82.81% | 66.35% | 53.20% | **24.91%** | 25.38% | **27.59%** | **77.04%** |\n| Mochi-1 [57] | 86.51% | 50.47% | 94.60% | 79.73% | 69.24% | 36.99% | 20.33% | 23.65% | 25.15% | 70.08% |\n| OpenSora V1.2 [75] | 82.22% | 51.83% | 91.20% | **90.08%** | 68.56% | 42.44% | 23.95% | 24.54% | 26.85% | 73.39% |\n| Mira [21] | 52.06% | 12.52% | 63.80% | 42.24% | 27.83% | 16.34% | 21.89% | 18.77% | 18.72% | 44.21% |\n| LinGen | **90.98%** | 55.15% | 97.50% | 83.95% | 58.15% | 53.51% | 21.08% | 24.29% | 26.32% | 73.73% |", "caption": "Table 5: VBench-Custom results based on customized prompts. Quality Score represents the weighted sum of these supported metrics.", "description": "VBench-Custom \ubca4\uce58\ub9c8\ud06c \uacb0\uacfc\ub294 \ub9de\ucda4\ud615 \ud504\ub86c\ud504\ud2b8\ub97c \uc0ac\uc6a9\ud558\uc5ec \ud14d\uc2a4\ud2b8-\ube44\ub514\uc624 \uc0dd\uc131 \ubaa8\ub378\uc744 \ud3c9\uac00\ud569\ub2c8\ub2e4. \ud45c\uc5d0\uc11c Quality Score\ub294 \uc9c0\uc6d0\ub418\ub294 \uba54\ud2b8\ub9ad\uc758 \uac00\uc911 \ud569\uacc4\ub97c \ub098\ud0c0\ub0c5\ub2c8\ub2e4. \uc774 \ud45c\ub294 4.3\uc808\uc5d0 \ub098\uc640 \uc788\uc2b5\ub2c8\ub2e4.", "section": "4. Experiments"}, {"content": "| Model | Subject Consist. | BG. Consis. | Temp. Flick. | Motion Smooth. | Aesthe. Quality | Imag. Quality | Dyna. Degree | Quality Score | Total Score | Max. Raw Frames |\n|---|---|---|---|---|---|---|---|---|---|---| \n| T2V-Turbo-v2 [29] | 95.50% | 96.71% | 97.35% | 97.07% | **90.00%** | 62.61% | **71.78%** | **85.13%** | **83.52%** | 16 |\n| Runway Gen-3 [47] | 97.10% | 96.62% | 98.61% | 99.23% | 60.14% | 63.34% | 66.82% | 84.11% | 82.32% | 256 |\n| LaVie-2 [64] | 97.90% | **98.45%** | 98.76% | 98.42% | 31.11% | **67.62%** | 70.39% | 83.24% | 81.75% | 61 |\n| Pika-1.0 [26] | 96.94% | 97.36% | **99.74%** | **99.50%** | 47.50% | 62.04% | 61.87% | 82.92% | 80.69% | 72 |\n| VideoCrafter-2.0 [3] | 96.85% | 98.22% | 98.41% | 97.73% | 42.50% | 63.13% | 67.22% | 82.20% | 80.44% | 16 |\n| OpenSora V1.2 [75] | 96.75% | 97.61% | 99.53% | 98.50% | 42.39% | 56.85% | 63.34% | 81.35% | 79.76% | 408 |\n| LinGen | **98.30%** | 97.60% | 99.26% | 98.58% | 63.67% | 60.55% | 63.36% | 83.77% | 81.76% | **1088** |", "caption": "Table 6: VBench-Custom results of LinGen at different resolutions. Higher-resolution videos obtain a much higher win rate in human evaluation but only obtain a slightly higher VBench quality score. This indicates that VBench does not perfectly align with human preference.", "description": "\uc774 \ud45c\ub294 VBench-Custom \ubca4\uce58\ub9c8\ud06c\uc5d0\uc11c LinGen \ubaa8\ub378\uc744 \uc11c\ub85c \ub2e4\ub978 \ud574\uc0c1\ub3c4\ub85c \ud3c9\uac00\ud55c \uacb0\uacfc\ub97c \ubcf4\uc5ec\uc90d\ub2c8\ub2e4. \ub192\uc740 \ud574\uc0c1\ub3c4\uc758 \ube44\ub514\uc624\ub294 \uc0ac\ub78c\uc758 \ud3c9\uac00\uc5d0\uc11c \ub354 \ub192\uc740 \uc120\ud638\ub3c4\ub97c \uc5bb\uc5c8\uc9c0\ub9cc, VBench \uc810\uc218\ub294 \uc57d\uac04 \ub354 \ub192\uc558\uc2b5\ub2c8\ub2e4. \uc774\ub294 VBench \uc810\uc218\uac00 \uc0ac\ub78c\uc758 \uc120\ud638\ub3c4\uc640 \uc644\ubcbd\ud558\uac8c \uc77c\uce58\ud558\uc9c0 \uc54a\uc74c\uc744 \uc2dc\uc0ac\ud569\ub2c8\ub2e4.", "section": "4.5. Ablation Experiments"}, {"content": "| Model | Object Class | Multiple Objects | Human Action | Color | Spatial Relatio. | Scene | Appear. Style | Temp. Style | Overall Consist. | Semantic Score |\n|---|---|---|---|---|---|---|---|---|---|---| \n| T2V-Turbo-v2 [29] | **95.33%** | 61.49% | 96.20% | 92.53% | 43.32% | **56.40%** | 24.17% | **27.06%** | **28.26%** | **77.12%** |\n| Runway Gen-3 [47] | 87.81% | 53.64% | 96.40% | 80.90% | 65.09% | 54.57% | 24.31% | 24.71% | 26.69% | 75.17% |\n| LaVie-2 [64] | 97.52% | **64.88%** | 96.40% | 91.65% | 38.68% | 49.59% | 25.09% | 25.24% | 27.39% | 75.76% |\n| Pika-1.0 [26] | 88.72% | 43.08% | 86.20% | 90.57% | 61.03% | 49.83% | 22.26% | 24.22% | 25.94% | 71.77% |\n| VideoCrafter-2.0 [3] | 92.55% | 40.66% | 95.00% | **92.92%** | 35.86% | 55.29% | **25.13%** | 25.84% | 28.23% | 73.42% |\n| OpenSora V1.2 [75] | 82.22% | 51.83% | 91.20% | 90.08% | **68.56%** | 42.44% | 23.95% | 24.54% | 26.85% | 73.39% |\n| LinGen | 90.98% | 55.15% | **97.50%** | 83.95% | 58.15% | 53.51% | 21.08% | 24.29% | 26.32% | 73.73% |", "caption": "Table 7: The pre-training recipe of LVGen. The model was trained on Nvidia H100 GPUs.", "description": "LinGen \ubaa8\ub378\uc758 \uc0ac\uc804 \ud6c8\ub828 \ub808\uc2dc\ud53c\ub97c \ubcf4\uc5ec\uc8fc\ub294 \ud45c\uc785\ub2c8\ub2e4. \uac01 \ub2e8\uacc4\ubcc4\ub85c \ud574\uc0c1\ub3c4, \ube44\ub514\uc624 \uae38\uc774, \ud6c8\ub828 \ub2e8\uacc4 \uc218, \ubc30\uce58 \ud06c\uae30, \uadf8\ub9ac\uace0 Nvidia H100 GPU\ub97c \uc0ac\uc6a9\ud55c \ud6c8\ub828 \uae30\uac04(\uc77c)\uc744 \ub098\ud0c0\ub0c5\ub2c8\ub2e4. 256p \ud574\uc0c1\ub3c4\uc758 \ud14d\uc2a4\ud2b8-\uc774\ubbf8\uc9c0 \uc0ac\uc804 \ud6c8\ub828\ubd80\ud130 \uc2dc\uc791\ud558\uc5ec 512p \ud574\uc0c1\ub3c4\uc758 \ub2e4\uc591\ud55c \uae38\uc774\uc758 \ud14d\uc2a4\ud2b8-\ube44\ub514\uc624 \uc0ac\uc804 \ud6c8\ub828\uae4c\uc9c0 \uc810\uc9c4\uc801\uc73c\ub85c \uc9c4\ud589\ub429\ub2c8\ub2e4.", "section": "Supplementary Material: D. Model Implementation Details"}]