[{"figure_path": "https://arxiv.org/html/2412.20800/x1.png", "caption": "Figure 1: Comparison of text fidelity and visual aesthetics between SDXL\u00a0[15], DPO\u00a0[27], and our VMix. DPO can generate attributes that SDXL fails to produce, but it fails to align with human visual fine-grained preferences. Our method achieves better text fidelity and visual aesthetics simultaneously.", "description": "\ubcf8 \uadf8\ub9bc\uc740 SDXL, DPO, \uadf8\ub9ac\uace0 \uc81c\uc548\ub41c VMix \uc138 \uac00\uc9c0 \ubc29\ubc95\uc744 \uc0ac\uc6a9\ud558\uc5ec \uc0dd\uc131\ub41c \uc774\ubbf8\uc9c0\ub97c \ube44\uad50 \ubd84\uc11d\ud55c \uacb0\uacfc\ub97c \ubcf4\uc5ec\uc90d\ub2c8\ub2e4. SDXL\uc740 \uae30\ubcf8 \ubaa8\ub378\ub85c, DPO\ub294 \uae30\uc874\uc758 \ubbf8\uc801 \uac1c\uc120 \ubc29\ubc95\uc744 \ub098\ud0c0\ub0c5\ub2c8\ub2e4.  \uadf8\ub9bc\uc5d0\uc11c \ubcfc \uc218 \uc788\ub4ef\uc774, DPO\ub294 SDXL\uc774 \uc0dd\uc131\ud558\uc9c0 \ubabb\ud558\ub294 \uc18d\uc131\ub4e4\uc744 \uc0dd\uc131\ud560 \uc218 \uc788\uc9c0\ub9cc, \uc138\ubc00\ud55c \uc218\uc900\uc758 \ubbf8\uc801 \uae30\uc900\uc5d0\ub294 \ubd80\ud569\ud558\uc9c0 \ubabb\ud569\ub2c8\ub2e4. \ubc18\uba74\uc5d0 VMix\ub294 \ud14d\uc2a4\ud2b8 \ucda9\uc2e4\ub3c4\uc640 \uc2dc\uac01\uc801 \ubbf8\uc801 \ud45c\ud604 \ubaa8\ub450\uc5d0\uc11c \ub354 \ub098\uc740 \uc131\ub2a5\uc744 \ubcf4\uc774\uba70, \ud14d\uc2a4\ud2b8\uc640 \uc774\ubbf8\uc9c0 \uac04\uc758 \uc815\ud569\uc131\uc744 \uc720\uc9c0\ud558\uba74\uc11c \ubbf8\uc801 \ud45c\ud604\uc744 \ud5a5\uc0c1\uc2dc\ud0a8\ub2e4\ub294 \uc810\uc744 \ubcf4\uc5ec\uc90d\ub2c8\ub2e4.  \uac01 \ubaa8\ub378\uc758 \uacb0\uacfc \uc774\ubbf8\uc9c0\ub294 \uba38\ub9ac\uce74\ub77d \uc0c9\uae54, \ub4dc\ub808\uc2a4 \uc0c9\uc0c1, \uaf43 \uc0c9\uae54, \ud53c\ubd80 \ub514\ud14c\uc77c, \uc0c9\uc0c1\uc758 \uc77c\uad00\uc131, \uc870\uba85 \ub4f1 \ub2e4\uc591\ud55c \ubbf8\uc801 \uc694\uc18c\ub4e4\uc744 \uae30\uc900\uc73c\ub85c \ube44\uad50 \ubd84\uc11d\ub429\ub2c8\ub2e4.", "section": "1. Introduction"}, {"figure_path": "https://arxiv.org/html/2412.20800/x5.png", "caption": "Figure 2: Illustration of of VMix. (a)In the initialization stage, pre-defined aesthetic labels are transformed into [CLS] tokens through CLIP, thereby obtaining AesEmb, which only need to be processed once at the beginning of training. (b)In the training stage, a project layer first maps the input aesthetic description ya\u2062e\u2062ssubscript\ud835\udc66\ud835\udc4e\ud835\udc52\ud835\udc60y_{aes}italic_y start_POSTSUBSCRIPT italic_a italic_e italic_s end_POSTSUBSCRIPT into an embedding fasubscript\ud835\udc53\ud835\udc4ef_{a}italic_f start_POSTSUBSCRIPT italic_a end_POSTSUBSCRIPT of the same token dimension as the content text embedding ftsubscript\ud835\udc53\ud835\udc61f_{t}italic_f start_POSTSUBSCRIPT italic_t end_POSTSUBSCRIPT. The text embedding ftsubscript\ud835\udc53\ud835\udc61f_{t}italic_f start_POSTSUBSCRIPT italic_t end_POSTSUBSCRIPT is then integrated into the denoising network through value-mixed cross-attention. (c)In the inference stage, VMix extract all positive aesthetic embedding from AesEmb to form the aesthetic input, along with the content input, is fed into the model for the denoising process.", "description": "\uadf8\ub9bc 2\ub294 \uc81c\uc548\ub41c VMix \ubc29\ubc95\uc758 \uc791\ub3d9 \uacfc\uc815\uc744 \ubcf4\uc5ec\uc90d\ub2c8\ub2e4. (a) \ucd08\uae30\ud654 \ub2e8\uacc4\uc5d0\uc11c\ub294 \ubbf8\ub9ac \uc815\uc758\ub41c \ubbf8\uc801 \ub808\uc774\ube14\uc774 CLIP\uc744 \ud1b5\ud574 [CLS] \ud1a0\ud070\uc73c\ub85c \ubcc0\ud658\ub418\uc5b4 AesEmb\uac00 \uc0dd\uc131\ub429\ub2c8\ub2e4. AesEmb\ub294 \ud6c8\ub828 \uc2dc\uc791 \uc2dc \ud55c \ubc88\ub9cc \ucc98\ub9ac\ub429\ub2c8\ub2e4. (b) \ud6c8\ub828 \ub2e8\uacc4\uc5d0\uc11c\ub294 \ud22c\uc601 \ub808\uc774\uc5b4\uac00 \uc785\ub825 \ubbf8\uc801 \uc124\uba85 (yaes)\uc744 \ucf58\ud150\uce20 \ud14d\uc2a4\ud2b8 \uc784\ubca0\ub529 (ft)\uacfc \ub3d9\uc77c\ud55c \ud1a0\ud070 \ucc28\uc6d0\uc758 \uc784\ubca0\ub529 (fa)\ub85c \ub9e4\ud551\ud569\ub2c8\ub2e4. \uadf8\ub7f0 \ub2e4\uc74c \ud14d\uc2a4\ud2b8 \uc784\ubca0\ub529 (ft)\uc740 \uac12 \ud63c\ud569 \uad50\ucc28 \uc5b4\ud150\uc158\uc744 \ud1b5\ud574 \uc7a1\uc74c \uc81c\uac70 \ub124\ud2b8\uc6cc\ud06c\uc5d0 \ud1b5\ud569\ub429\ub2c8\ub2e4. (c) \ucd94\ub860 \ub2e8\uacc4\uc5d0\uc11c\ub294 VMix\uac00 AesEmb\uc5d0\uc11c \ubaa8\ub4e0 \uae0d\uc815\uc801\uc778 \ubbf8\uc801 \uc784\ubca0\ub529\uc744 \ucd94\ucd9c\ud558\uc5ec \ubbf8\uc801 \uc785\ub825\uc744 \ud615\uc131\ud558\uace0, \ucf58\ud150\uce20 \uc785\ub825\uacfc \ud568\uaed8 \ubaa8\ub378\uc5d0 \uc785\ub825\ud558\uc5ec \uc7a1\uc74c \uc81c\uac70 \ud504\ub85c\uc138\uc2a4\ub97c \uc218\ud589\ud569\ub2c8\ub2e4.", "section": "3. \ubc29\ubc95\ub860"}, {"figure_path": "https://arxiv.org/html/2412.20800/x6.png", "caption": "Figure 3: Qualitative comparison with various state-of-the-art methods. All results are based on Stable Diffusion\u00a0[20]. Our VMix method outperforms others, significantly enhancing the quality of image generation across various fine-grained aesthetic dimensions.", "description": "\uadf8\ub9bc 3\uc740 \ub2e4\uc591\ud55c \ucd5c\ucca8\ub2e8 \ubc29\ubc95\ub4e4\uacfc \ube44\uad50\ud558\uc5ec VMix\uc758 \uc131\ub2a5\uc744 \ubcf4\uc5ec\uc90d\ub2c8\ub2e4. \ubaa8\ub4e0 \uacb0\uacfc\ub294 Stable Diffusion [20]\uc744 \uae30\ubc18\uc73c\ub85c \uc0dd\uc131\ub418\uc5c8\uc2b5\ub2c8\ub2e4. \uc81c\uc2dc\ub41c \uc608\uc2dc\ub294 \ub2e4\uc591\ud55c \ud14d\uc2a4\ud2b8 \ud504\ub86c\ud504\ud2b8\uc5d0 \ub300\ud55c \uc774\ubbf8\uc9c0 \uc0dd\uc131 \uacb0\uacfc\ub97c \ubcf4\uc5ec\uc8fc\uba70, VMix \ubc29\ubc95\uc774 \uc0c9\uc0c1, \uc870\uba85, \uad6c\uc131 \ub4f1 \ubbf8\uc138\ud55c \uc2ec\ubbf8\uc801 \ucc28\uc6d0\uc5d0\uc11c \uc774\ubbf8\uc9c0 \ud488\uc9c8\uc744 \ud06c\uac8c \ud5a5\uc0c1\uc2dc\ud0a8\ub2e4\ub294 \uac83\uc744 \ubcf4\uc5ec\uc90d\ub2c8\ub2e4.  \uac01\uac01\uc758 \ud504\ub86c\ud504\ud2b8\uc5d0 \ub300\ud574 VMix\ub97c \ud3ec\ud568\ud55c \ub2e4\uc591\ud55c \ubc29\ubc95\ub4e4(SD, FreeU, DPO, SFT, SFT & TI)\uc774 \uc801\uc6a9\ub41c \uacb0\uacfc \uc774\ubbf8\uc9c0\ub4e4\uc744 \ube44\uad50\ud558\uc5ec VMix\uc758 \uc6b0\uc218\uc131\uc744 \uc2dc\uac01\uc801\uc73c\ub85c \ud655\uc778\ud560 \uc218 \uc788\uc2b5\ub2c8\ub2e4.", "section": "4. \uc2e4\ud5d8 \uacb0\uacfc"}, {"figure_path": "https://arxiv.org/html/2412.20800/x9.png", "caption": "Figure 4: Qualitative comparison with various state-of-the-art methods. All the results of the methods are based on the SDXL\u00a0[15]. Our VMix method outperforms others, significantly enhancing the quality of image generation.", "description": "\uadf8\ub9bc 4\ub294 \ucd5c\ucca8\ub2e8 \uae30\ubc95\ub4e4\uacfc VMix\uc758 \uc131\ub2a5\uc744 \ube44\uad50\ud55c \uc815\uc131\uc801 \ubd84\uc11d \uacb0\uacfc\ub97c \ubcf4\uc5ec\uc90d\ub2c8\ub2e4. \ubaa8\ub4e0 \uacb0\uacfc\ub294 SDXL [15] \uae30\ubc18\uc73c\ub85c \uc0dd\uc131\ub418\uc5c8\uc2b5\ub2c8\ub2e4. VMix\ub294 \ub2e4\ub978 \ubc29\ubc95\ub4e4\ubcf4\ub2e4 \ub6f0\uc5b4\ub09c \uc131\ub2a5\uc744 \ubcf4\uc774\uba70 \uc774\ubbf8\uc9c0 \uc0dd\uc131 \ud488\uc9c8\uc744 \ud06c\uac8c \ud5a5\uc0c1\uc2dc\ud0b5\ub2c8\ub2e4.  \uac01 \ud589\uc740 \uc11c\ub85c \ub2e4\ub978 \ud504\ub86c\ud504\ud2b8(\ud14d\uc2a4\ud2b8 \uc785\ub825)\uc5d0 \ub300\ud55c \uacb0\uacfc\ub97c \ubcf4\uc5ec\uc8fc\uba70, \uac01 \uc5f4\uc740 \uc11c\ub85c \ub2e4\ub978 \ubc29\ubc95(SDXL, FreeU, DPO, SFT, SFT & TI, \uadf8\ub9ac\uace0 \uc81c\uc548\ub41c VMix)\uc73c\ub85c \uc0dd\uc131\ub41c \uc774\ubbf8\uc9c0\ub4e4\uc744 \ub098\ud0c0\ub0c5\ub2c8\ub2e4.  \uc774 \uadf8\ub9bc\uc744 \ud1b5\ud574 VMix\uac00 \ub2e4\uc591\ud55c \ubbf8\ubb18\ud55c \ubbf8\uc801 \uc694\uc18c\ub4e4(\uc870\uba85, \uc0c9\uc0c1, \uad6c\uc131 \ub4f1)\uc744 \uac1c\uc120\ud558\ub294 \ub370 \ud0c1\uc6d4\ud558\ub2e4\ub294 \uac83\uc744 \uc9c1\uad00\uc801\uc73c\ub85c \ubcf4\uc5ec\uc90d\ub2c8\ub2e4.", "section": "4. \uc2e4\ud5d8"}, {"figure_path": "https://arxiv.org/html/2412.20800/x10.png", "caption": "Figure 5: Qualitative results. We compare images generated by VMix-integrated personalized models with those from standard personalized models. On the left are images produced by the personalized model with VMix integration, while on the right are images from the standard personalized model without modifications.", "description": "\uadf8\ub9bc 5\ub294 VMix\ub97c \ud1b5\ud569\ud55c \uac1c\uc778\ud654\ub41c \ubaa8\ub378\uacfc \uc218\uc815\ub418\uc9c0 \uc54a\uc740 \ud45c\uc900 \uac1c\uc778\ud654 \ubaa8\ub378\uc5d0\uc11c \uc0dd\uc131\ub41c \uc774\ubbf8\uc9c0\ub97c \ube44\uad50\ud55c \uc815\uc131\uc801 \uacb0\uacfc\ub97c \ubcf4\uc5ec\uc90d\ub2c8\ub2e4. \uc67c\ucabd\uc5d0\ub294 VMix\uac00 \ud1b5\ud569\ub41c \uac1c\uc778\ud654 \ubaa8\ub378\ub85c \uc0dd\uc131\ub41c \uc774\ubbf8\uc9c0\uac00, \uc624\ub978\ucabd\uc5d0\ub294 \uc218\uc815\ub418\uc9c0 \uc54a\uc740 \ud45c\uc900 \uac1c\uc778\ud654 \ubaa8\ub378\ub85c \uc0dd\uc131\ub41c \uc774\ubbf8\uc9c0\uac00 \ub098\uc5f4\ub418\uc5b4 \uc788\uc2b5\ub2c8\ub2e4.  \ub2e4\uc591\ud55c \uc2a4\ud0c0\uc77c\uacfc \uac1c\uc778\ud654\ub41c \ubaa8\ub378\uc758 \ube44\uad50\ub97c \ud1b5\ud574 VMix\uac00 \uc774\ubbf8\uc9c0 \ud488\uc9c8 \uac1c\uc120\uc5d0 \ubbf8\uce58\ub294 \uc601\ud5a5\uc744 \uc2dc\uac01\uc801\uc73c\ub85c \ubcf4\uc5ec\uc90d\ub2c8\ub2e4. \uac01 \ubaa8\ub378\uc740 \ub2e4\uc591\ud55c \ud504\ub86c\ud504\ud2b8\ub97c \uc0ac\uc6a9\ud558\uc5ec \uc0dd\uc131\ub41c \uc774\ubbf8\uc9c0\ub97c \ubcf4\uc5ec\uc8fc\uba70, VMix \ud1b5\ud569 \uc5ec\ubd80\uc5d0 \ub530\ub978 \uc2dc\uac01\uc801 \ucc28\uc774\ub97c \uba85\ud655\ud558\uac8c \ube44\uad50\ud560 \uc218 \uc788\uc2b5\ub2c8\ub2e4.", "section": "4. Experiments"}, {"figure_path": "https://arxiv.org/html/2412.20800/x11.png", "caption": "Figure 6: User study. We report the user preference between using VMix and not using VMix.", "description": "\ubcf8 \uadf8\ub9bc\uc740 VMix \uc0ac\uc6a9 \uc5ec\ubd80\uc5d0 \ub530\ub978 \uc0ac\uc6a9\uc790 \uc120\ud638\ub3c4\ub97c \ubcf4\uc5ec\uc8fc\ub294 \uc0ac\uc6a9\uc790 \uc5f0\uad6c \uacb0\uacfc\ub97c \ub098\ud0c0\ub0c5\ub2c8\ub2e4.  \uadf8\ub9bc\uc740 VMix\ub97c \uc0ac\uc6a9\ud55c \uc774\ubbf8\uc9c0\uc640 \uc0ac\uc6a9\ud558\uc9c0 \uc54a\uc740 \uc774\ubbf8\uc9c0 \uac01\uac01\uc5d0 \ub300\ud55c \uc0ac\uc6a9\uc790 \uc120\ud638\ub3c4\ub97c \ube44\uad50 \ubd84\uc11d\ud558\uc5ec VMix\uc758 \ud6a8\uacfc\ub97c \uc2dc\uac01\uc801\uc73c\ub85c \ubcf4\uc5ec\uc90d\ub2c8\ub2e4.  \uad6c\uccb4\uc801\uc73c\ub85c\ub294, \uc5ec\ub7ec \uac1c\uc758 \uc774\ubbf8\uc9c0 \uc30d\uc5d0 \ub300\ud574 \uc0ac\uc6a9\uc790\ub4e4\uc774 \uc5b4\ub5a4 \uc774\ubbf8\uc9c0\ub97c \ub354 \uc120\ud638\ud558\ub294\uc9c0\uc5d0 \ub300\ud55c \ube44\uc728\uc744 \ub9c9\ub300 \uadf8\ub798\ud504\uc640 \uc0b0\uc810\ub3c4\ub85c \ud45c\ud604\ud558\uc5ec, VMix \uc0ac\uc6a9 \uc2dc \uc0ac\uc6a9\uc790 \uc120\ud638\ub3c4\uac00 \uc5bc\ub9c8\ub098 \uc99d\uac00\ud558\ub294\uc9c0 \uc815\ub7c9\uc801\uc73c\ub85c \ub098\ud0c0\ub0c5\ub2c8\ub2e4.", "section": "4. Experiments"}, {"figure_path": "https://arxiv.org/html/2412.20800/x12.png", "caption": "(a)", "description": "\uc774 \uadf8\ub9bc\uc740 \ub17c\ubb38\uc758 3. \ubc29\ubc95\ub860 \uc139\uc158\uc5d0 \uc18d\ud558\uba70, VMix \ubaa8\ub378\uc758 \ucd08\uae30\ud654 \ub2e8\uacc4\ub97c \ubcf4\uc5ec\uc90d\ub2c8\ub2e4. \ubbf8\ub9ac \uc815\uc758\ub41c \uc2ec\ubbf8\uc801 \ub808\uc774\ube14\uc774 CLIP \ud1a0\ud070\uc73c\ub85c \ubcc0\ud658\ub418\ub294 \uacfc\uc815\uacfc, \uc774\ub7ec\ud55c \ud1a0\ud070\uc774 \ucd94\ub860 \ub2e8\uacc4\uc5d0\uc11c \ubaa8\ub378\uc5d0 \uc785\ub825\ub418\ub294 \ubc29\uc2dd\uc744 \uc2dc\uac01\uc801\uc73c\ub85c \uc124\uba85\ud569\ub2c8\ub2e4.  \uc2ec\ubbf8\uc801 \uc785\ub825\uc740 \ub0b4\uc6a9 \uc785\ub825\uacfc \ud568\uaed8 \ubaa8\ub378\uc5d0 \uc81c\uacf5\ub418\uc5b4 \uc774\ubbf8\uc9c0 \uc0dd\uc131 \uacfc\uc815\uc5d0 \uc2ec\ubbf8\uc801 \uc870\uac74\uc744 \ud1b5\ud569\ud558\ub294 \ubc29\uc2dd\uc744 \ubcf4\uc5ec\uc90d\ub2c8\ub2e4.", "section": "3. \ubc29\ubc95\ub860"}, {"figure_path": "https://arxiv.org/html/2412.20800/x13.png", "caption": "(b)", "description": "\uadf8\ub9bc 2(b)\ub294 VMix\uc758 \ud559\uc2b5 \ub2e8\uacc4\ub97c \ubcf4\uc5ec\uc90d\ub2c8\ub2e4.  \ubbf8\uc801 \uc18d\uc131 \uc124\uba85(Yaes)\uc740 \ub3d9\uc77c\ud55c \ud1a0\ud070 \ucc28\uc6d0\uc744 \uac16\ub294 \ucf58\ud150\uce20 \ud14d\uc2a4\ud2b8 \uc784\ubca0\ub529(ft)\uacfc \ub3d9\uc77c\ud55c \ud1a0\ud070 \ucc28\uc6d0\uc758 \uc784\ubca0\ub529(fa)\uc73c\ub85c \ub9e4\ud551\ub429\ub2c8\ub2e4.  \ud14d\uc2a4\ud2b8 \uc784\ubca0\ub529(ft)\uc740 \uac12 \ud63c\ud569 \uad50\ucc28 \uc5b4\ud150\uc158\uc744 \ud1b5\ud574 \uc7a1\uc74c \uc81c\uac70 \ub124\ud2b8\uc6cc\ud06c\uc5d0 \ud1b5\ud569\ub429\ub2c8\ub2e4.  \uc774 \uacfc\uc815\uc740 \ubbf8\uc801 \uc870\uac74\uc744 \uc7a1\uc74c \uc81c\uac70 \uacfc\uc815\uc5d0 \ud1b5\ud569\ud558\uc5ec \uc774\ubbf8\uc9c0\uc758 \ubbf8\uc801 \ud488\uc9c8\uc744 \ud5a5\uc0c1\uc2dc\ud0a4\ub294 \ubc29\ubc95\uc744 \ubcf4\uc5ec\uc90d\ub2c8\ub2e4.  \uc81c\ub85c\ub85c \ucd08\uae30\ud654\ub41c \uc120\ud615 \ub808\uc774\uc5b4\ub97c \ud1b5\ud574 \ub124\ud2b8\uc6cc\ud06c\uac00 \uc5f0\uacb0\ub418\uc5b4 \uc788\uc2b5\ub2c8\ub2e4. ", "section": "3. Methodology"}, {"figure_path": "https://arxiv.org/html/2412.20800/x14.png", "caption": "Figure 7: Ablation Study for \u03bb\ud835\udf06\\lambdaitalic_\u03bb of VMix. (a)Visual performance changes of \u03bb\ud835\udf06\\lambdaitalic_\u03bb. (b)Performance metrics for VMix, evaluated across a range of \u03bb\ud835\udf06\\lambdaitalic_\u03bb values from 1 to 2 from right to left.", "description": "\uadf8\ub9bc 7\uc740 VMix\uc758 \u03bb\uc5d0 \ub300\ud55c \uc808\ucda9 \uc5f0\uad6c \uacb0\uacfc\ub97c \ubcf4\uc5ec\uc90d\ub2c8\ub2e4. (a)\ub294 \u03bb \uac12\uc758 \ubcc0\ud654\uc5d0 \ub530\ub978 \uc2dc\uac01\uc801 \uc131\ub2a5 \ubcc0\ud654\ub97c, (b)\ub294 \u03bb \uac12\uc774 1\uc5d0\uc11c 2\uae4c\uc9c0 \ubcc0\ud654\ud560 \ub54c VMix\uc758 \uc131\ub2a5 \uc9c0\ud45c\ub97c \ud3c9\uac00\ud55c \uacb0\uacfc\ub97c \ub098\ud0c0\ub0c5\ub2c8\ub2e4. \u03bb \uac12\uc774 \uc99d\uac00\ud568\uc5d0 \ub530\ub77c Aes \uc810\uc218\ub294 \uc810\uc9c4\uc801\uc73c\ub85c \uc99d\uac00\ud558\uc9c0\ub9cc CLIP \uc810\uc218\ub294 \uc57d\uac04 \uac10\uc18c\ud558\ub294 \uacbd\ud5a5\uc744 \ubcf4\uc785\ub2c8\ub2e4. \ud558\uc9c0\ub9cc VMix\ub294 \ub2e4\ub978 \ubc29\ubc95\ub4e4\uc5d0 \ube44\ud574 \uc5ec\uc804\ud788 \uc0c1\ub2f9\ud55c \uc774\uc810\uc744 \uc720\uc9c0\ud569\ub2c8\ub2e4.", "section": "4.4 \uc808\ucda9 \uc5f0\uad6c"}, {"figure_path": "https://arxiv.org/html/2412.20800/x15.png", "caption": "Figure 8: Ablation Study for AesEmb of VMix. Left: The effects of using all aesthetic labels versus not using them. Right: The effects of using single-dimensional aesthetic labels.", "description": "\uadf8\ub9bc 8\uc740 VMix\uc758 AesEmb\uc5d0 \ub300\ud55c ablation study \uacb0\uacfc\ub97c \ubcf4\uc5ec\uc90d\ub2c8\ub2e4. \uc67c\ucabd\uc740 \ubaa8\ub4e0 \ubbf8\uc801 \ub808\uc774\ube14\uc744 \uc0ac\uc6a9\ud55c \uacbd\uc6b0\uc640 \uc0ac\uc6a9\ud558\uc9c0 \uc54a\uc740 \uacbd\uc6b0\uc758 \ud6a8\uacfc\ub97c \ube44\uad50\ud558\uace0, \uc624\ub978\ucabd\uc740 \ub2e8\uc77c \ucc28\uc6d0 \ubbf8\uc801 \ub808\uc774\ube14\uc744 \uc0ac\uc6a9\ud55c \uacbd\uc6b0\uc758 \ud6a8\uacfc\ub97c \ubcf4\uc5ec\uc90d\ub2c8\ub2e4.  \uc67c\ucabd \ud328\ub110\uc740 \ubaa8\ub4e0 \ubbf8\uc801 \uc18d\uc131\uc744 \uace0\ub824\ud558\uc5ec \uc774\ubbf8\uc9c0 \uc0dd\uc131\uc744 \ud588\uc744 \ub54c\uc640, \uc544\ubb34\ub7f0 \ubbf8\uc801 \uc18d\uc131\ub3c4 \uace0\ub824\ud558\uc9c0 \uc54a\uc558\uc744 \ub54c\uc758 \uacb0\uacfc\ub97c \ube44\uad50\ud558\uc5ec VMix \ubaa8\ub378\uc774 \ubbf8\uc801 \uc138\ubd80\uc0ac\ud56d\uc744 \ud5a5\uc0c1\uc2dc\ud0a4\ub294 \ub370 \uc5bc\ub9c8\ub098 \ud6a8\uacfc\uc801\uc778\uc9c0 \ubcf4\uc5ec\uc90d\ub2c8\ub2e4. \uc624\ub978\ucabd \ud328\ub110\uc740 \ud2b9\uc815 \ubbf8\uc801 \uc18d\uc131(\uc608: \uc0c9\uc0c1, \uc870\uba85, \uad6c\ub3c4)\ub9cc\uc744 \uace0\ub824\ud558\uc5ec \uc774\ubbf8\uc9c0\ub97c \uc0dd\uc131\ud588\uc744 \ub54c\uc758 \uacb0\uacfc\ub97c \ubcf4\uc5ec\uc8fc\uc5b4, \uac01 \ubbf8\uc801 \uc18d\uc131\uc774 \uc774\ubbf8\uc9c0 \ud488\uc9c8\uc5d0 \ubbf8\uce58\ub294 \uc601\ud5a5\uc744 \uac1c\ubcc4\uc801\uc73c\ub85c \ubd84\uc11d\ud569\ub2c8\ub2e4.", "section": "4.4 Ablation Study"}]