{"importance": "**\ubcf8 \ub17c\ubb38\uc740 \uc9c0\uc18d\uc801\uc778 \uc0c1\ud0dc\ub97c \uac00\uc9c4 \uc5f0\uc18d\uc801\uc778 3D \uc778\uc2dd \ubaa8\ub378\uc744 \uc81c\uc2dc\ud558\uc5ec, \ube44\ub514\uc624 \ub610\ub294 \uc0ac\uc9c4 \uceec\ub809\uc158\uc73c\ub85c\ubd80\ud130 \uc628\ub77c\uc778\uc73c\ub85c \ubc00\uc9d1\ub41c 3D \uc7ac\uad6c\uc131\uc744 \uc218\ud589\ud558\ub294 \ubc29\ubc95\uc744 \ubcf4\uc5ec\uc90d\ub2c8\ub2e4.** \uc774\ub294 3D \uc778\uc2dd \ubd84\uc57c\uc758 \uc8fc\uc694 \uc5f0\uad6c \ub3d9\ud5a5\uc774\uba70, \ub2e4\uc591\ud55c 3D \uc791\uc5c5\uc5d0 \uc801\uc6a9\ub420 \uc218 \uc788\ub294 \uc720\uc5f0\uc131\uc744 \uac00\uc9c0\uace0 \uc788\uc2b5\ub2c8\ub2e4.  **\uc774 \uc5f0\uad6c\ub294 \ud2b9\ud788 \uc2e4\uc2dc\uac04 \uc751\uc6a9 \ubd84\uc57c\ub098, \uc81c\ud55c\ub41c \uc815\ubcf4\ub9cc\uc73c\ub85c\ub3c4 3D \ud658\uacbd\uc744 \ud6a8\uc728\uc801\uc73c\ub85c \ud30c\uc545\ud574\uc57c \ud558\ub294 \ubd84\uc57c\uc5d0 \ud070 \uc601\ud5a5\uc744 \ubbf8\uce60 \uc218 \uc788\uc2b5\ub2c8\ub2e4.**", "summary": "\uc5f0\uc18d\uc801\uc778 \uc0c1\ud0dc\ub97c \uc9c0\ub2cc \ud601\uc2e0\uc801\uc778 3D \uc778\uc2dd \ubaa8\ub378\uc774 \ub4f1\uc7a5\ud558\uc5ec, \uc81c\ud55c\ub41c \uc2dc\uac01 \uc815\ubcf4\ub9cc\uc73c\ub85c\ub3c4 \uc2e4\uc2dc\uac04\uc73c\ub85c \uc815\ubc00\ud55c 3D \ud658\uacbd \uc7ac\uad6c\uc131\uc774 \uac00\ub2a5\ud574\uc84c\uc2b5\ub2c8\ub2e4.", "takeaways": ["\uc9c0\uc18d\uc801\uc778 \uc0c1\ud0dc\ub97c \uac00\uc9c4 \uc5f0\uc18d\uc801\uc778 3D \uc778\uc2dd \ubaa8\ub378\uc744 \ud1b5\ud574 \ube44\ub514\uc624 \ubc0f \uc774\ubbf8\uc9c0\ub85c\ubd80\ud130 \uc2e4\uc2dc\uac04\uc73c\ub85c \uc815\ubc00\ud55c 3D \uc7a5\uba74\uc744 \uc7ac\uad6c\uc131\ud560 \uc218 \uc788\uc2b5\ub2c8\ub2e4.", "\uc81c\uc548\ub41c \ubaa8\ub378\uc740 \uc815\uc801 \ubc0f \ub3d9\uc801 \uc7a5\uba74 \ubaa8\ub450\ub97c \ucc98\ub9ac\ud560 \uc218 \uc788\ub294 \uc720\uc5f0\uc131\uc744 \ubcf4\uc5ec\uc8fc\uba70, \ub2e4\uc591\ud55c 3D \uc791\uc5c5\uc5d0\uc11c \ucd5c\ucca8\ub2e8 \uc131\ub2a5\uc744 \ub2ec\uc131\ud569\ub2c8\ub2e4.", "\uac00\uc0c1 \ubdf0\ub97c \ud1b5\ud574 \ubcf4\uc774\uc9c0 \uc54a\ub294 \uc7a5\uba74 \uc601\uc5ed\uae4c\uc9c0 \ucd94\ub860\ud560 \uc218 \uc788\ub294 \uae30\ub2a5\uc744 \uac16\ucd94\uc5b4, 3D \uc778\uc2dd\uc758 \ud55c\uacc4\ub97c \ub6f0\uc5b4\ub118\ub294 \uc0c8\ub85c\uc6b4 \uac00\ub2a5\uc131\uc744 \uc81c\uc2dc\ud569\ub2c8\ub2e4."], "tldr": "\uae30\uc874\uc758 3D \uc7ac\uad6c\uc131 \ubc29\ubc95\ub4e4\uc740 \uc81c\ud55c\ub41c \uad00\uce21\uce58\ub098 \ubd88\uc548\uc815\ud55c \uc870\uac74\uc5d0\uc11c\ub294 \uc131\ub2a5\uc774 \uc800\ud558\ub418\ub294 \ubb38\uc81c\uac00 \uc788\uc5c8\uc2b5\ub2c8\ub2e4. \ud2b9\ud788 \ub3d9\uc801\uc778 \ubb3c\uccb4\ub098 \ubd80\uc871\ud55c \uc815\ubcf4\ub85c \uc778\ud574 \uc815\ud655\ud55c 3D \ubaa8\ub378 \uc0dd\uc131\uc5d0 \uc5b4\ub824\uc6c0\uc744 \uacaa\uc5c8\uc2b5\ub2c8\ub2e4. \uc774\ub7ec\ud55c \ubb38\uc81c\uc810\ub4e4\uc744 \ud574\uacb0\ud558\uae30 \uc704\ud574, \uc5f0\uad6c\uc790\ub4e4\uc740 **\uc9c0\uc18d\uc801\uc778 \uc0c1\ud0dc\ub97c \uc720\uc9c0\ud558\ub294 \uc21c\ud658 \uc2e0\uacbd\ub9dd \uae30\ubc18\uc758 \ud1b5\ud569 \ud504\ub808\uc784\uc6cc\ud06c**\ub97c \uc81c\uc2dc\ud588\uc2b5\ub2c8\ub2e4.\n\ubcf8 \ub17c\ubb38\uc5d0\uc11c\ub294 **CUT3R\uc774\ub77c\ub294 \uc0c8\ub85c\uc6b4 \ubaa8\ub378**\uc744 \uc81c\uc548\ud558\uc5ec, \uc774\ubbf8\uc9c0 \uc2a4\ud2b8\ub9bc\uc73c\ub85c\ubd80\ud130 \uc5f0\uc18d\uc801\uc774\uace0 \uc815\ubc00\ud55c 3D \uc7ac\uad6c\uc131\uc744 \uc218\ud589\ud569\ub2c8\ub2e4. **CUT3R\uc740 \uac01 \ud504\ub808\uc784\ub9c8\ub2e4 \uce74\uba54\ub77c \ub9e4\uac1c\ubcc0\uc218\uc640 3D \uae30\ud558\ud559\uc801 \uc815\ubcf4\ub97c \ucd94\uc815**\ud558\uace0, \uc774\ub97c \ud1b5\ud574 \ub2e4\uc591\ud55c 3D \uc791\uc5c5\uc744 \ucc98\ub9ac\ud560 \uc218 \uc788\uc2b5\ub2c8\ub2e4. **\uc774 \ubaa8\ub378\uc740 \uc815\uc801 \ubc0f \ub3d9\uc801 \uc7a5\uba74 \ubaa8\ub450\uc5d0 \uc801\uc6a9 \uac00\ub2a5**\ud558\uba70, \ube44\ub514\uc624\uc640 \uc2a4\ud30c\uc2a4 \uc0ac\uc9c4 \uceec\ub809\uc158 \ubaa8\ub450\uc5d0\uc11c \uc785\ub825\uc744 \ucc98\ub9ac\ud558\uc5ec, \ubcf4\uc774\uc9c0 \uc54a\ub294 \uc601\uc5ed\uae4c\uc9c0 \ucd94\ub860\ud558\ub294 \uae30\ub2a5\uc744 \uc81c\uacf5\ud569\ub2c8\ub2e4. \uc2e4\ud5d8 \uacb0\uacfc\ub294 \uc81c\uc548\ub41c \ubaa8\ub378\uc774 \ub2e4\uc591\ud55c 3D \uc791\uc5c5\uc5d0\uc11c \ucd5c\ucca8\ub2e8 \uc131\ub2a5 \ub610\ub294 \uacbd\uc7c1\ub825 \uc788\ub294 \uc131\ub2a5\uc744 \ub2ec\uc131\ud568\uc744 \ubcf4\uc5ec\uc90d\ub2c8\ub2e4.", "affiliation": "Google DeepMind", "categories": {"main_category": "Computer Vision", "sub_category": "3D Vision"}}