[{"content": "| Layers | Attention Heads | Head Dim | FFN Dim | Cross-Attn Dim | Activation Function | Normalization |\n|---|---|---|---|---|---|---|\n| 48 | 48 | 128 | 24,576 | (6,144, 1,024) | GELU-approx | RMSNorm |", "caption": "Table 1: Hyper-parameters used in Step-Video-T2V.", "description": "Step-Video-T2V \ubaa8\ub378\uc758 \ud558\uc774\ud37c\ud30c\ub77c\ubbf8\ud130\ub4e4\uc744 \ubcf4\uc5ec\uc8fc\ub294 \ud45c\uc785\ub2c8\ub2e4.  \ub808\uc774\uc5b4 \uc218, \uc5b4\ud150\uc158 \ud5e4\ub4dc \uc218, \ud5e4\ub4dc \ucc28\uc6d0, \ud53c\ub4dc\ud3ec\uc6cc\ub4dc \ub124\ud2b8\uc6cc\ud06c \ucc28\uc6d0, \ud06c\ub85c\uc2a4 \uc5b4\ud150\uc158 \ucc28\uc6d0, \ud65c\uc131\ud654 \ud568\uc218, \uadf8\ub9ac\uace0 \uc815\uaddc\ud654 \uae30\ubc95 \ub4f1 Step-Video-T2V \ubaa8\ub378\uc758 \uc8fc\uc694 \uad6c\uc131 \uc694\uc18c\ub4e4\uc758 \uc138\ubd80\uc801\uc778 \uc124\uc815\uac12\ub4e4\uc744 \ubcf4\uc5ec\uc90d\ub2c8\ub2e4. \uc774\ub97c \ud1b5\ud574 Step-Video-T2V \ubaa8\ub378\uc758 \uad6c\uc870 \ubc0f \uc131\ub2a5\uc5d0 \ub300\ud55c \uc774\ud574\ub97c \ub192\uc77c \uc218 \uc788\uc2b5\ub2c8\ub2e4.", "section": "4.3 DiT w/ 3D Full Attention"}, {"content": "| TP | CP | PP | VPP | Checkpointing (%) | MFU |\n|---|---|---|---|---|---|---|\n| 4 | 1 | 2 | 24 | 93.75 | 35.90 |\n| 4 | 1 | 4 | 24 | 93.75 | 35.71 |\n| 8 | 1 | 1 | 1 | 83.33 | 35.59 |\n| 8 | 1 | 2 | 24 | 72.91 | 36.06 |\n| 8 | 1 | 4 | 12 | 72.91 | 35.76 |\n| 8 | 2 | 1 | 1 | 62.50 | 31.79 |\n| 8 | 2 | 4 | 12 | 31.25 | 35.11 |\n| 3 | 1 | 1 | 31.25 | 33.41 |  |\n| 3 | 4 | 12 | 11.53 | 36.47 |  |", "caption": "Table 2: Estimated MFU from SEMU of different parallelism strategies under 540P video pre-training stage.", "description": "\ud45c 2\ub294 Step-Video-T2V\uc758 540P \ube44\ub514\uc624 \uc0ac\uc804 \ud559\uc2b5 \ub2e8\uacc4\uc5d0\uc11c \ub2e4\uc591\ud55c \ubcd1\ub82c\ud654 \uc804\ub7b5\uc5d0 \ub530\ub978 \ubaa8\ub378 \uc5f0\uc0b0\ub7c9 \ud65c\uc6a9\ub3c4(MFU)\ub97c Step Emulator(SEMU)\ub97c \uc0ac\uc6a9\ud558\uc5ec \ucd94\uc815\ud55c \uacb0\uacfc\ub97c \ubcf4\uc5ec\uc90d\ub2c8\ub2e4.  \uac01 \ud589\uc740 TP(Tensor Parallelism), CP(Context Parallelism), PP(Pipeline Parallelism), VPP(Virtual Pipeline Parallelism)\uc640 \uccb4\ud06c\ud3ec\uc778\ud305 \ube44\uc728\uc744 \ub098\ud0c0\ub0b4\uba70, \uc774\ub7ec\ud55c \uc804\ub7b5\ub4e4\uc758 \uc870\ud569\uc5d0 \ub530\ub978 MFU \uac12\uc744 \ubcf4\uc5ec\uc90d\ub2c8\ub2e4.  \uc774\ub294 540P \uace0\ud574\uc0c1\ub3c4 \ube44\ub514\uc624 \ud559\uc2b5\uc5d0 \ucd5c\uc801\uc758 \ubcd1\ub82c \uc804\ub7b5\uc744 \uc124\uc815\ud558\uae30 \uc704\ud55c \uc2dc\ubbac\ub808\uc774\uc158 \uacb0\uacfc\uc785\ub2c8\ub2e4.", "section": "6.2 Training Framework Optimizations"}, {"content": "| Resolution (F, H, W) | TFLOPs per sample |\n|---|---| \n| 204 \u00d7 256 \u00d7 256 | 1,717.20 |\n| 204 \u00d7 192 \u00d7 320 | 1,592.61 |\n| 136 \u00d7 256 \u00d7 256 | 1,079.85 |\n| 136 \u00d7 192 \u00d7 320 | 1,004.89 |\n| 68 \u00d7 256 \u00d7 256 | 509.31 |\n| 68 \u00d7 192 \u00d7 320 | 475.87 |\n| 1 \u00d7 256 \u00d7 256 | 44.99 |", "caption": "Table 3: FLOPs per sample of different resolutions.", "description": "\ud45c 3\uc740 \ube44\ub514\uc624\uc758 \ud574\uc0c1\ub3c4\uc5d0 \ub530\ub978 \uc0d8\ud50c\ub2f9 FLOPs(Floating Point Operations) \uc218\ub97c \ubcf4\uc5ec\uc90d\ub2c8\ub2e4.  \uc989,  \ube44\ub514\uc624 \uc0dd\uc131 \ubaa8\ub378\uc774 \ud2b9\uc815 \ud574\uc0c1\ub3c4\uc758 \ube44\ub514\uc624\ub97c \ucc98\ub9ac\ud558\ub294 \ub370 \ud544\uc694\ud55c \uacc4\uc0b0\ub7c9\uc744 \ub098\ud0c0\ub0c5\ub2c8\ub2e4.  \ub2e4\uc591\ud55c \ud574\uc0c1\ub3c4\uc758 \ube44\ub514\uc624\ub97c \ucc98\ub9ac\ud558\ub294 \ub370 \ud544\uc694\ud55c \uacc4\uc0b0\ub7c9\uc774 \uc5bc\ub9c8\ub098 \ucc28\uc774\uac00 \ub098\ub294\uc9c0 \ubcf4\uc5ec\uc8fc\ub294 \ud45c\uc774\uba70,  \uc774\ub7ec\ud55c \uacc4\uc0b0\ub7c9\uc758 \ucc28\uc774\ub294 \ube44\ub514\uc624 \uc0dd\uc131 \ubaa8\ub378\uc758 \ud6a8\uc728\uc131\uacfc \ucc98\ub9ac \uc18d\ub3c4\uc5d0 \uc601\ud5a5\uc744 \ubbf8\uce69\ub2c8\ub2e4.", "section": "6.2.4 DP Load Balance"}, {"content": "| Fault | Category | Count |\n|---|---|---|\n| GPU_DBE_ERROR | GPU | 3 |\n| GPU_LOCKED | GPU | 1 |\n| LINK_DOWN | Network | 1 |\n| NODE_SHUTDOWN | Host | 2 |\n| SOFTWARE_FAULT | Software | 11 |\n| CUDA_OOM | Software | 7 |\n| NON_FATAL | Hardware | 4 |", "caption": "Table 4: Over a month of Step-Video-T2V training, fatal hardware failures occurred only 7 times.", "description": "\ud45c 4\ub294 Step-Video-T2V \ubaa8\ub378\uc758 \ud55c \ub2ec\uac04\uc758 \ud559\uc2b5 \uacfc\uc815\uc5d0\uc11c \ubc1c\uc0dd\ud55c \uce58\uba85\uc801\uc778 \ud558\ub4dc\uc6e8\uc5b4 \uc624\ub958\uc758 \ud69f\uc218\ub97c \ubcf4\uc5ec\uc90d\ub2c8\ub2e4. \ucd1d 7\ubc88\uc758 \uce58\uba85\uc801\uc778 \uc624\ub958\ub9cc \ubc1c\uc0dd\ud588\uc74c\uc744 \ubcf4\uc5ec\uc8fc\ub294 \uc774 \ud45c\ub294 \uc2dc\uc2a4\ud15c\uc758 \uc548\uc815\uc131\uacfc \uacac\uace0\uc131\uc744 \uac15\uc870\ud569\ub2c8\ub2e4. \ud45c\uc5d0\ub294 \uc624\ub958 \uc720\ud615(GPU, \ub124\ud2b8\uc6cc\ud06c, \ud638\uc2a4\ud2b8, \uc18c\ud504\ud2b8\uc6e8\uc5b4 \ub4f1)\uacfc \uac01 \uc720\ud615\ubcc4 \ubc1c\uc0dd \ud69f\uc218\uac00 \uc790\uc138\ud788 \ub098\uc5f4\ub418\uc5b4 \uc788\uc2b5\ub2c8\ub2e4. \uc774\ub97c \ud1b5\ud574 \uc2dc\uc2a4\ud15c \uad00\ub9ac\uc790\ub294 \ubb38\uc81c \ud574\uacb0 \ubc0f \uc2dc\uc2a4\ud15c \uac1c\uc120\uc744 \uc704\ud55c \uc815\ubcf4\ub97c \uc5bb\uc744 \uc218 \uc788\uc2b5\ub2c8\ub2e4.", "section": "6 System"}, {"content": "| Cause of Restart | Step-Video-T2V |  | LLaMA3.1 |  |\n|---|---|---|---|---|\n| Hardware | Hardware | Total Unexpected | Hardware | Total Unexpected |\n| Avg Daily Restarts/1k GPUs | **0.037** | 0.095 | **0.422** | 0.485 |", "caption": "Table 5: Restart count statistics during training for Step-Video-T2V and LLaMA3.1 .", "description": "\ud45c 5\ub294 Step-Video-T2V\uc640 LLaMA 3.1 \ubaa8\ub378\uc758 \ud559\uc2b5 \uc911 \ud558\ub4dc\uc6e8\uc5b4 \uc7ac\uc2dc\uc791 \ud69f\uc218 \ud1b5\uacc4\ub97c \ubcf4\uc5ec\uc90d\ub2c8\ub2e4.  '\ud558\ub4dc\uc6e8\uc5b4 \uc7ac\uc2dc\uc791'\uc774\ub780 \ud558\ub4dc\uc6e8\uc5b4 \uc624\ub958\ub85c \uc778\ud574 \ud559\uc2b5 \uc791\uc5c5\uc774 \uc911\ub2e8\ub418\uace0 \ub2e4\uc2dc \uc2dc\uc791\ub41c \uacbd\uc6b0\ub97c \uc758\ubbf8\ud558\uba70, \ubaa8\ub378 \ud559\uc2b5 \uc548\uc815\uc131 \ubc0f \uc2dc\uc2a4\ud15c \uc548\uc815\uc131 \uc9c0\ud45c\ub85c \uc0ac\uc6a9\ub429\ub2c8\ub2e4. \ud45c\ub294 \ud558\ub8e8 \ub3d9\uc548 1,000\uac1c\uc758 GPU\ub2f9 \ubc1c\uc0dd\ud55c \ud558\ub4dc\uc6e8\uc5b4 \uc7ac\uc2dc\uc791 \ud69f\uc218\uc640 \uc608\uc0c1\uce58 \ubabb\ud55c \uc7ac\uc2dc\uc791 \ud69f\uc218\ub97c Step-Video-T2V\uc640 LLaMA 3.1 \ubaa8\ub378\uc5d0 \ub300\ud574 \uac01\uac01 \ube44\uad50\ud558\uc5ec \ubcf4\uc5ec\uc90d\ub2c8\ub2e4.  \uc774\ub97c \ud1b5\ud574 Step-Video-T2V \ubaa8\ub378\uc758 \uc2dc\uc2a4\ud15c \uc548\uc815\uc131 \ubc0f \ud6a8\uc728\uc131\uc744 \uac1d\uad00\uc801\uc73c\ub85c \ud3c9\uac00\ud560 \uc218 \uc788\uc2b5\ub2c8\ub2e4.", "section": "6 System"}, {"content": "| training stage | dataset | bs/node | learning rate | #iters | #seen samples |\n|---|---|---|---|---|---| \n| Step-1: T2I Pre-training (256px) | O(1)B images | 40 | 1e-4 | 53k | 0.8B |\n|  | O(1)B images | 40 | 1e-4 | 200k | 3B |\n| **Total** |  |  | **253k** | **3.8B** |\n| Step-2: T2VI Pre-training (192px) | O(1)B video clips | 4 | 6e-5 | 171k | 256M |\n|  | O(100)M video clips | 4 | 6e-5 | 101k | 151M |\n|  | O(100)M video clips | 4 | 6e-5 | 158k | 237M |\n| **Total** |  |  | **430k** | **644M** |\n| Step-2: T2VI Pre-training (540px) | O(100)M video clips | 2 | 2e-5 | 23k | 17.3M |\n|  | O(10)M video clips | 2 | 1e-5 | 17k | 8.5M |\n|  | O(1)M video clips | 1 | 1e-5 | 6k | 1.5M |\n| **Total** |  |  | **46k** | **27.3M** |", "caption": "Table 6: Pre-training details of Step-Video-T2V. 256px, 192px, and 540px denote resolutions of 256x256, 192x320, and 544x992, respectively.", "description": "\ud45c 6\uc740 Step-Video-T2V\uc758 \uc0ac\uc804 \ud6c8\ub828 \uc138\ubd80 \uc815\ubcf4\ub97c \ubcf4\uc5ec\uc90d\ub2c8\ub2e4.  256px, 192px, 540px\ub294 \uac01\uac01 256x256, 192x320, 544x992 \ud574\uc0c1\ub3c4\ub97c \ub098\ud0c0\ub0c5\ub2c8\ub2e4.  \ud45c\uc5d0\ub294 \uac01 \uc0ac\uc804 \ud6c8\ub828 \ub2e8\uacc4(T2I, T2VI)\uc5d0\uc11c \uc0ac\uc6a9\ub41c \ub370\uc774\ud130\uc14b\uc758 \uc885\ub958, \ub178\ub4dc\ub2f9 \ubc30\uce58 \ud06c\uae30(bs/node), \ud559\uc2b5\ub960, \ubc18\ubcf5 \ud69f\uc218, \ucc98\ub9ac\ub41c \uc0d8\ud50c \uc218 \ub4f1\uc758 \uc815\ubcf4\uac00 \ud3ec\ud568\ub418\uc5b4 \uc788\uc2b5\ub2c8\ub2e4. \uc774\ub97c \ud1b5\ud574 Step-Video-T2V \ubaa8\ub378\uc758 \ud6c8\ub828 \uacfc\uc815\uc5d0 \ub300\ud55c \uc790\uc138\ud55c \ub0b4\uc6a9\uc744 \uc774\ud574\ud560 \uc218 \uc788\uc2b5\ub2c8\ub2e4.", "section": "8 \ud6c8\ub828 \uc804\ub7b5"}, {"content": "| Step-Video-T2V vs. HunyuanVideo (Win-Tie-Loss) | Annotator-1 | Annotator-2 | Annotator-3 |\n|---|---|---|---|\n| Overall | 59-22-47 | 46-47-35 | 54-41-33 |\n| Sports | 6-3-3 | 5-5-2 | 6-6-0 |\n| Food | 5-2-4 | 5-4-2 | 3-7-1 |\n| Scenery | 5-3-4 | 2-9-1 | 7-1-4 |\n| Animals | 6-0-6 | 3-6-3 | 2-7-3 |\n| Festivals | 4-4-3 | 5-2-4 | 4-5-2 |\n| Combined Concepts | 5-2-5 | 6-3-3 | 8-1-3 |\n| Surreal | 4-2-5 | 5-2-4 | 6-2-3 |\n| People | 6-2-4 | 3-4-5 | 5-2-5 |\n| 3D Animation | 7-1-4 | 4-5-3 | 6-3-3 |\n| Cinematography | 5-1-5 | 2-5-4 | 1-4-6 |\n| Style | 6-2-4 | 6-2-4 | 6-3-3 |", "caption": "Table 7: Comparison with HunyuanVideo using Metric-1.", "description": "\ubcf8 \ud45c\ub294 Step-Video-T2V \ubaa8\ub378\uacfc HunyuanVideo \ubaa8\ub378\uc758 \uc131\ub2a5\uc744 Metric-1\uc744 \uc0ac\uc6a9\ud558\uc5ec \ube44\uad50\ud55c \uacb0\uacfc\ub97c \ubcf4\uc5ec\uc90d\ub2c8\ub2e4. Metric-1\uc740 \ub450 \ubaa8\ub378\uc774 \uc0dd\uc131\ud55c \ube44\ub514\uc624 \uc30d\uc5d0 \ub300\ud574 \uc778\uac04 \ud3c9\uac00\uc790\uac00 Step-Video-T2V\uac00 \ub354 \ub098\uc740\uc9c0, HunyuanVideo\uac00 \ub354 \ub098\uc740\uc9c0, \uc544\ub2c8\uba74 \ube44\uc2b7\ud55c\uc9c0\ub97c \ud310\ub2e8\ud558\ub294 \ubc29\uc2dd\uc785\ub2c8\ub2e4. \ud45c\uc5d0\ub294 \ub2e4\uc591\ud55c \uce74\ud14c\uace0\ub9ac(\uc608: \uc2a4\ud3ec\uce20, \uc74c\uc2dd, \ud48d\uacbd \ub4f1)\uc5d0 \ub300\ud55c \uac01 \ubaa8\ub378\uc758 \uc2b9/\ubb34/\ud328 \ud69f\uc218\uac00 \uc81c\uc2dc\ub418\uc5b4 \uc788\uc2b5\ub2c8\ub2e4.", "section": "9.2 \uc624\ud508\uc18c\uc2a4 \ubaa8\ub378\uacfc\uc758 \ube44\uad50"}, {"content": "| Step-Video-T2V vs. HunyuanVideo | Instruction Following | Motion Smoothness | Physical Plausibility | Aesthetic Appeal |\n|---|---|---|---|---|\n| Overall | 1,273-1,221 | 1,407-1,327 | 1,417-1,238 | 1,312-1,238 |\n| Sports | 130-111 | 120-104 | 113-99 | 110-98 |\n| Food | 85-92 | 110-97 | 107-93 | 111-90 |\n| Scenery | 130-129 | 139-126 | 134-120 | 125-122 |\n| Animals | 104-106 | 123-114 | 110-107 | 99-108 |\n| Festivals | 102-91 | 110-102 | 97-90 | 103-94 |\n| Combined Concepts | 132-115 | 139-136 | 139-135 | 118-115 |\n| Surreal | 99-101 | 138-139 | 135-134 | 125-126 |\n| People | 115-117 | 129-129 | 148-150 | 115-112 |\n| 3D Animation | 113-109 | 137-133 | 149-146 | 139-135 |\n| Cinematography | 121-117 | 121-122 | 132-133 | 116-115 |\n| Style | 142-133 | 141-125 | 153-134 | 151-123 |", "caption": "Table 8: Comparison with HunyuanVideo using Metric-2. We invited three human annotators to evaluate each video. For each category and evaluation dimension, we aggregated the scores given by all annotators across all prompts within the category for that dimension.", "description": "\uc774 \ud45c\ub294 Step-Video-T2V \ubaa8\ub378\uacfc HunyuanVideo \ubaa8\ub378\uc758 \uc131\ub2a5\uc744 \ube44\uad50 \ubd84\uc11d\ud55c \uacb0\uacfc\ub97c \ubcf4\uc5ec\uc90d\ub2c8\ub2e4. Metric-2 \uc9c0\ud45c\ub97c \uc0ac\uc6a9\ud558\uc5ec Instruction Following, Motion Smoothness, Physical Plausibility, Aesthetic Appeal \ub124 \uac00\uc9c0 \ud3c9\uac00 \uae30\uc900\uc73c\ub85c \uac01 \ube44\ub514\uc624\ub97c \ud3c9\uac00\ud588\uc2b5\ub2c8\ub2e4. \uc138 \uba85\uc758 \uc778\uac04 \ud3c9\uac00\uc790\uac00 \uac01 \ube44\ub514\uc624\uc5d0 \uc810\uc218\ub97c \ub9e4\uacbc\uc73c\uba70, \uac01 \ubc94\uc8fc\uc640 \ud3c9\uac00 \uae30\uc900\uc5d0 \ub300\ud574 \ubaa8\ub4e0 \ud3c9\uac00\uc790\uc758 \uc810\uc218\ub97c \uc9d1\uacc4\ud558\uc5ec \ud45c\uc5d0 \ub098\ud0c0\ub0c8\uc2b5\ub2c8\ub2e4.", "section": "9.2 HunyuanVideo\uc640\uc758 \ube44\uad50"}, {"content": "| Step-Video-T2V vs. T2VTopA (Win-Tie-Loss) | Annotator-1 | Annotator-2 | Annotator-3 |\n|---|---|---|---|\n| Overall | 44-13-69 | 41-13-72 | 46-25-55 |\n| Sports | 6-2-4 | 7-0-5 | 7-3-2 |\n| Food | 5-2-4 | 6-1-4 | 4-2-5 |\n| Scenery | 1-0-10 | 4-0-7 | 1-2-8 |\n| Animals | 1-3-8 | 1-3-8 | 3-1-8 |\n| Festivals | 6-2-3 | 7-2-2 | 5-3-3 |\n| Combined Concepts | 2-0-10 | 1-3-8 | 8-0-4 |\n| Surreal | 4-1-6 | 3-2-6 | 4-2-5 |\n| People | 2-1-8 | 2-1-8 | 6-1-4 |\n| 3D Animation | 6-0-6 | 3-0-9 | 5-3-4 |\n| Cinematography | 5-1-5 | 4-1-6 | 1-3-7 |\n| Style | 6-1-5 | 3-0-9 | 2-5-5 |", "caption": "Table 9: Comparison with T2VTopA using Metric-1. A total of 126 prompts were evaluated, rather than 128, as T2VTopA rejected 2 prompts.", "description": "\uc774 \ud45c\ub294 Step-Video-T2V \ubaa8\ub378\uc758 \uc131\ub2a5\uc744 \ud3c9\uac00\ud558\uae30 \uc704\ud574 \uc0ac\uc6a9\ub41c \ubca4\uce58\ub9c8\ud06c\uc778 Step-Video-T2V-Eval \ub370\uc774\ud130\uc14b\uc744 \uae30\ubc18\uc73c\ub85c, Step-Video-T2V\uc640 \uc911\uad6d \ub0b4 \uc8fc\uc694 \ub450 \uac1c\uc758 \uc0c1\uc6a9 \ud14d\uc2a4\ud2b8-\ube44\ub514\uc624 \uc0dd\uc131 \uc5d4\uc9c4\uc778 T2VTopA\uc640 T2VTopB\uc758 \uc131\ub2a5\uc744 Metric-1\uc744 \uc0ac\uc6a9\ud558\uc5ec \ube44\uad50 \ubd84\uc11d\ud55c \uacb0\uacfc\ub97c \ubcf4\uc5ec\uc90d\ub2c8\ub2e4. Metric-1\uc740 \uc778\uac04 \ud3c9\uac00\uc790\ub4e4\uc774 Step-Video-T2V\uc640 \ube44\uad50 \ubaa8\ub378\uc774 \uc0dd\uc131\ud55c \ube44\ub514\uc624 \uc30d\uc5d0 \ub300\ud574 Step-Video-T2V\uac00 \ub354 \uc6b0\uc218\ud55c\uc9c0, \ub3d9\ub4f1\ud55c\uc9c0, \ub610\ub294 \uc5f4\ub4f1\ud55c\uc9c0\ub97c \ud310\ub2e8\ud558\ub294 \ubc29\uc2dd\uc785\ub2c8\ub2e4. \ucd1d 128\uac1c\uc758 \ud504\ub86c\ud504\ud2b8 \uc911 T2VTopA\uac00 2\uac1c\uc758 \ud504\ub86c\ud504\ud2b8\ub97c \ucc98\ub9ac\ud558\uc9c0 \ubabb\ud558\uc5ec \uc2e4\uc81c\ub85c\ub294 126\uac1c\uc758 \ud504\ub86c\ud504\ud2b8\uc5d0 \ub300\ud55c \ud3c9\uac00 \uacb0\uacfc\uac00 \uc81c\uc2dc\ub418\uc5b4 \uc788\uc2b5\ub2c8\ub2e4. \uac01 \ud504\ub86c\ud504\ud2b8\uc5d0 \ub300\ud55c \ube44\ub514\uc624 \ube44\uad50 \uacb0\uacfc\ub97c \ubc14\ud0d5\uc73c\ub85c \uc138 \uba85\uc758 \uc778\uac04 \ud3c9\uac00\uc790\uc758 \uc758\uacac\uc744 \uc885\ud569\ud558\uc5ec Step-Video-T2V\uc758 \uc0c1\ub300\uc801 \uc131\ub2a5\uc744 \uce21\uc815\ud569\ub2c8\ub2e4.", "section": "9.3 \uc0c1\uc6a9 \ubaa8\ub378\uacfc\uc758 \ube44\uad50"}, {"content": "| Step-Video-T2V vs. T2VTopB (Win-Tie-Loss) | Annotator-1 | Annotator-2 | Annotator-3 |\n|---|---|---|---|\n| Overall | 36-35-51 | 67-10-45 | 55-22-45 |\n| Sports | 8-2-2 | 10-1-1 | 8-2-2 |\n| Food | 3-4-3 | 7-1-2 | 7-2-1 |\n| Scenery | 2-6-4 | 5-2-5 | 5-4-3 |\n| Animals | 5-1-5 | 3-1-7 | 2-2-7 |\n| Festivals | 6-1-4 | 6-0-5 | 2-4-5 |\n| Combined Concepts | 1-4-7 | 6-1-5 | 4-2-6 |\n| Surreal | 2-0-6 | 3-0-5 | 2-1-5 |\n| People | 1-3-7 | 4-1-6 | 3-1-7 |\n| 3D Animation | 5-3-4 | 11-0-1 | 11-0-1 |\n| Cinematography | 3-3-5 | 4-2-5 | 3-1-7 |\n| Style | 0-8-4 | 8-1-3 | 8-3-1 |", "caption": "Table 10: Comparison with T2VTopB using Metric-1. A total of 122 prompts were evaluated, rather than 128, as T2VTopB rejected 6 prompts.", "description": "\ud45c 10\uc740 Step-Video-T2V \ubaa8\ub378\uacfc T2VTopB \ubaa8\ub378\uc758 \uc131\ub2a5\uc744 Metric-1\uc744 \uc0ac\uc6a9\ud558\uc5ec \ube44\uad50\ud55c \uacb0\uacfc\ub97c \ubcf4\uc5ec\uc90d\ub2c8\ub2e4.  \ucd1d 128\uac1c\uc758 \ud504\ub86c\ud504\ud2b8 \uc911 T2VTopB\uac00 6\uac1c\uc758 \ud504\ub86c\ud504\ud2b8\ub97c \ucc98\ub9ac\ud558\uc9c0 \ubabb\ud558\uc5ec \uc2e4\uc81c\ub85c\ub294 122\uac1c\uc758 \ud504\ub86c\ud504\ud2b8\uc5d0 \ub300\ud55c \ube44\uad50 \ubd84\uc11d\uc774 \uc218\ud589\ub418\uc5c8\uc74c\uc744 \uc758\ubbf8\ud569\ub2c8\ub2e4.  \uac01 \ud3c9\uac00\uc790\ubcc4 Step-Video-T2V \ubaa8\ub378\uc774 T2VTopB \ubaa8\ub378\ubcf4\ub2e4 \uc6b0\uc218\ud55c(Win), \ub3d9\ub4f1\ud55c(Tie), \uc5f4\ub4f1\ud55c(Loss) \uacb0\uacfc\ub97c \uac1c\uc218\ub85c \ub098\ud0c0\ub0b4\uc5b4 \ubaa8\ub378 \uac04\uc758 \uc131\ub2a5 \ucc28\uc774\ub97c \ubcf4\uc5ec\uc90d\ub2c8\ub2e4.", "section": "9.2 \ube44\uad50 \uc2e4\ud5d8"}, {"content": "| Annotator | Model | Instruction Following | Motion Smoothness | Physical Plausibility | Aesthetic Appeal |\n|---|---|---|---|---|---| \n| Annotator-1 | Step-Video-T2V | 204 | 210 | 203 | 187 |\n|  | T2VTopA | 211 | 200 | 198 | 196 |\n|  | T2VTopB | 185 | 184 | 178 | 175 |\n| Annotator-2 | Step-Video-T2V | 211 | 243 | 256 | 217 |\n|  | T2VTopA | 241 | 243 | 242 | 228 |\n|  | T2VTopB | 234 | 236 | 229 | 204 |\n| Annotator-3 | Step-Video-T2V | 170 | 197 | 172 | 178 |\n|  | T2VTopA | 177 | 177 | 153 | 171 |\n|  | T2VTopB | 164 | 163 | 139 | 148 |\n| Annotator-4 | Step-Video-T2V | 199 | 232 | 230 | 225 |\n|  | T2VTopA | 217 | 221 | 201 | 199 |\n|  | T2VTopB | 194 | 219 | 194 | 194 |\n| Annotator-5 | Step-Video-T2V | 218 | 225 | 213 | 211 |\n|  | T2VTopA | 221 | 220 | 213 | 212 |\n|  | T2VTopB | 209 | 217 | 202 | 196 |\n| Annotator-6 | Step-Video-T2V | 187 | 213 | 251 | 211 |\n|  | T2VTopA | 193 | 201 | 259 | 197 |\n|  | T2VTopB | 201 | 224 | 271 | 227 |", "caption": "Table 11: Comparison with T2VTopA and T2VTopB using Metric-2. We invited six human annotators to evaluate each video. For each evaluation dimension, we aggregated the scores given by each annotator across all prompts for that dimension. Prompts that were rejected by any model were excluded from the analysis for all models.", "description": "\ud45c 11\uc740 Step-Video-T2V \ubaa8\ub378\uacfc \uc911\uad6d \ub0b4 \ub450 \uac1c\uc758 \uc8fc\uc694 \uc0c1\uc6a9 \ud14d\uc2a4\ud2b8-\ube44\ub514\uc624 \uc0dd\uc131 \uc5d4\uc9c4\uc778 T2VTopA\uc640 T2VTopB\uc758 \uc131\ub2a5\uc744 \ube44\uad50\ud55c \uac83\uc785\ub2c8\ub2e4. 6\uba85\uc758 \uc778\uac04 \ud3c9\uac00\uc790\uac00 \uac01 \ube44\ub514\uc624\uc758 \ud488\uc9c8\uc744 \ud3c9\uac00\ud588\uace0, \uac01 \ud3c9\uac00 \ucc28\uc6d0(Instruction Following, Motion Smoothness, Physical Plausibility, Aesthetic Appeal)\uc5d0 \ub300\ud55c \uc810\uc218\ub97c \uc9d1\uacc4\ud558\uc5ec \ubaa8\ub378 \uac04 \uc131\ub2a5\uc744 \ube44\uad50\ud588\uc2b5\ub2c8\ub2e4. \uc5b4\ub5a4 \ubaa8\ub378\uc5d0\uc11c\ub3c4 \uac70\ubd80\ub41c \ud504\ub86c\ud504\ud2b8\ub294 \ubd84\uc11d\uc5d0\uc11c \uc81c\uc678\ud588\uc2b5\ub2c8\ub2e4.", "section": "9.3 \uc0c1\uc6a9 \ubaa8\ub378\uacfc\uc758 \ube44\uad50"}, {"content": "| Category | Step-Video-T2V vs. Movie Gen Video (Win-Tie-Loss) | Step-Video-T2V vs. HunyuanVideo (Win-Tie-Loss) | # of Prompts |\n|---|---|---|---| \n| Overall | 485-315-489 | 615-313-361 | 1,289 |\n| human | 123-58-160 | 181-64-96 | 341 |\n| physics | 61-54-64 | 87-47-45 | 179 |\n| unusual activity & subject | 110-74-108 | 136-75-81 | 292 |\n| animal | 39-37-42 | 47-30-41 | 118 |\n| scene | 84-53-63 | 91-58-51 | 200 |\n| sequential motion | 9-2-2 | 6-2-5 | 13 |\n| camera motion | 59-37-50 | 67-37-42 | 146 |", "caption": "Table 12: Comparison of Movie Gen Video and HunyuanVideo using the Movie Gen Video Bench. The total number of evaluations (1,289) is greater than 1,003 due to some prompts having multiple category tags. This evaluation involved six human annotators.", "description": "\ud45c 12\ub294 Movie Gen Video \ubca4\uce58\ub9c8\ud06c\ub97c \uc0ac\uc6a9\ud558\uc5ec Movie Gen Video\uc640 HunyuanVideo\uc758 \uc131\ub2a5\uc744 \ube44\uad50\ud55c \uacb0\uacfc\ub97c \ubcf4\uc5ec\uc90d\ub2c8\ub2e4.  \uc77c\ubd80 \ud504\ub86c\ud504\ud2b8\uac00 \uc5ec\ub7ec \uce74\ud14c\uace0\ub9ac \ud0dc\uadf8\ub97c \uac00\uc9c0\uace0 \uc788\uae30 \ub54c\ubb38\uc5d0 \ud3c9\uac00 \ud69f\uc218(1,289\ud68c)\uac00 1,003\ud68c\ubcf4\ub2e4 \ub9ce\uc2b5\ub2c8\ub2e4. \uc774 \ud3c9\uac00\uc5d0\ub294 6\uba85\uc758 \uc778\uac04 \ud3c9\uac00\uc790\uac00 \ucc38\uc5ec\ud588\uc2b5\ub2c8\ub2e4.  \ud45c\ub294 \uac01 \uce74\ud14c\uace0\ub9ac\ubcc4\ub85c Movie Gen Video\uc640 HunyuanVideo\uc758 \uc131\ub2a5 \ucc28\uc774\ub97c Win/Tie/Loss \ud615\ud0dc\ub85c \ub098\ud0c0\ub0b4\uace0 \uc788\uc73c\uba70, \uac01 \uce74\ud14c\uace0\ub9ac\ubcc4 \ud3c9\uac00\uc5d0 \uc0ac\uc6a9\ub41c \ud504\ub86c\ud504\ud2b8 \uc218\ub3c4 \ud568\uaed8 \uc81c\uc2dc\ud569\ub2c8\ub2e4.  \uc774\ub97c \ud1b5\ud574, \uac01 \ubaa8\ub378\uc758 \uac15\uc810\uacfc \uc57d\uc810\uc744 \uce74\ud14c\uace0\ub9ac\ubcc4\ub85c \ube44\uad50 \ubd84\uc11d\ud560 \uc218 \uc788\uc2b5\ub2c8\ub2e4.", "section": "9.4 Movie Gen Video Bench\uc5d0\uc11c\uc758 \ud3c9\uac00"}, {"content": "| Model | Downsample Factor | SSIM\u2191 | PSNR\u2191 | rFVD\u2193 |\n|---|---|---|---|---|\n| OpenSora-1.2 (Zheng et al. (2024)) | 4 \u00d7 8 \u00d7 8 | 0.9126 | 31.41 | 20.42 |\n| CogvideoX-1.5 (Yang et al. (2024a)) | 4 \u00d7 8 \u00d7 8 | 0.9373 | 38.10 | 16.33 |\n| HunyuanVideo (Kong et al. (2025)) | 4 \u00d7 8 \u00d7 8 | 0.9710 | 39.56 | 4.17 |\n| Cosmos-VAE (Nvidia (2025)) | 4 \u00d7 8 \u00d7 8 | 0.9315 | 37.66 | 9.10 |\n| Cosmos-VAE (Nvidia (2025)) | 8 \u00d7 16 \u00d7 16 | 0.8862 | 34.82 | 40.33 |\n| Video-VAE (Ours) | 8 \u00d7 16 \u00d7 16 | 0.9776 | 39.37 | 3.61 |", "caption": "Table 13: Comparison of reconstruction metrics.", "description": "\ubcf8 \ud45c\ub294 Step-Video-T2V \ubaa8\ub378\uc5d0\uc11c \uc0ac\uc6a9\ub41c Video-VAE\uc758 \uc601\uc0c1 \uc7ac\uad6c\uc131 \uc131\ub2a5\uc744 \ubcf4\uc5ec\uc90d\ub2c8\ub2e4. \ub2e4\uc591\ud55c \ube44\uc728\ub85c \ub2e4\uc6b4\uc0d8\ud50c\ub9c1\ub41c \uc5ec\ub7ec \uc624\ud508\uc18c\uc2a4 \uae30\ubc18 \ubaa8\ub378\ub4e4\uacfc \ube44\uad50\ud558\uc5ec, Video-VAE\uac00 \uc555\ub3c4\uc801\uc73c\ub85c \ub192\uc740 SSIM, PSNR \uc810\uc218\uc640 \ub0ae\uc740 rFVD \uc810\uc218\ub97c \uae30\ub85d\ud568\uc744 \ubcf4\uc5ec\uc90d\ub2c8\ub2e4. \ud2b9\ud788 8x16x16\uc758 \ub192\uc740 \uc555\ucd95\ub960\uc5d0\uc11c\ub3c4 \uc6b0\uc218\ud55c \uc7ac\uad6c\uc131 \ud488\uc9c8\uc744 \uc720\uc9c0\ud558\ub294 \uac83\uc744 \ud655\uc778\ud560 \uc218 \uc788\uc2b5\ub2c8\ub2e4.", "section": "4.1 Video-VAE"}]