{"importance": "\ubcf8 \ub17c\ubb38\uc740 **\uc778\uac04\uc758 \ud53c\ub4dc\ubc31\uc744 \ud65c\uc6a9\ud558\uc5ec \ube44\ub514\uc624 \uc0dd\uc131 \ubaa8\ub378\uc744 \ud5a5\uc0c1\uc2dc\ud0a4\ub294 \ubc29\ubc95**\uc744 \uc81c\uc2dc\ud558\uc5ec, **\ube44\ub514\uc624 \uc0dd\uc131 \ubd84\uc57c\uc758 \ud575\uc2ec\uc801\uc778 \ubb38\uc81c\uc810 \ud574\uacb0**\uc5d0 \ud06c\uac8c \uae30\uc5ec\ud569\ub2c8\ub2e4.  **\ub300\uaddc\ubaa8 \uc120\ud638\ub3c4 \ub370\uc774\ud130\uc14b \uad6c\ucd95**, **\ub2e4\ucc28\uc6d0\uc801 \ubcf4\uc0c1 \ubaa8\ub378 \uac1c\ubc1c**, **\uc0c8\ub85c\uc6b4 \uc815\ub82c \uc54c\uace0\ub9ac\uc998 \uc81c\uc2dc** \ub4f1\uc758 \uc5f0\uad6c \uacb0\uacfc\ub294 \ud5a5\ud6c4 \ube44\ub514\uc624 \uc0dd\uc131 \uae30\uc220 \ubc1c\uc804\uc5d0 \uc911\uc694\ud55c \uc601\ud5a5\uc744 \ubbf8\uce60 \uac83\uc774\uba70, **\ub2e4\uc591\ud55c \uc5f0\uad6c \ubd84\uc57c\uc5d0\uc11c\uc758 \ud65c\uc6a9 \uac00\ub2a5\uc131**\uc744 \uc2dc\uc0ac\ud569\ub2c8\ub2e4.  \ud2b9\ud788, **\ucd5c\uc2e0 \ube44\ub514\uc624 \uc0dd\uc131 \ubaa8\ub378\uc758 \ud2b9\uc9d5\uc744 \uace0\ub824\ud55c \uc815\ub82c \uc54c\uace0\ub9ac\uc998 \uac1c\ubc1c**\uc740 \uc774 \ubd84\uc57c \uc5f0\uad6c\uc758 \uc0c8\ub85c\uc6b4 \ubc29\ud5a5\uc744 \uc81c\uc2dc\ud560 \uac83\uc73c\ub85c \uae30\ub300\ub429\ub2c8\ub2e4.", "summary": "\uc778\uac04 \ud53c\ub4dc\ubc31\uc73c\ub85c \ube44\ub514\uc624 \uc0dd\uc131 \uac1c\uc120: \ub2e4\ucc28\uc6d0\uc801 \ubcf4\uc0c1 \ubc0f \uc815\ub82c \uc54c\uace0\ub9ac\uc998 \uc81c\uc2dc", "takeaways": ["\ub300\uaddc\ubaa8 \ub2e4\ucc28\uc6d0\uc801 \ube44\ub514\uc624 \uc120\ud638\ub3c4 \ub370\uc774\ud130\uc14b \uad6c\ucd95", "\ub2e4\ucc28\uc6d0\uc801 \ube44\ub514\uc624 \ubcf4\uc0c1 \ubaa8\ub378 \ubc0f \ud3c9\uac00 \ubca4\uce58\ub9c8\ud06c \uc81c\uc2dc", "\ucd5c\uc2e0 \ud750\ub984 \uae30\ubc18 \ubaa8\ub378\uc744 \uc704\ud55c \ud6a8\uc728\uc801\uc778 \uc815\ub82c \uc54c\uace0\ub9ac\uc998(Flow-DPO, Flow-RWR, Flow-NRG) \uac1c\ubc1c"], "tldr": "\ucd5c\uadfc \ube44\ub514\uc624 \uc0dd\uc131 \uae30\uc220\uc740 \ubc1c\uc804\ud588\uc9c0\ub9cc, **\uc6c0\uc9c1\uc784 \ubd88\uc548\uc815, \ud504\ub86c\ud504\ud2b8 \ubd88\uc77c\uce58, \ud654\uc9c8 \uc800\ud558** \ub4f1\uc758 \ubb38\uc81c\uc810\uc774 \uc788\uc2b5\ub2c8\ub2e4. \uae30\uc874 \uc5f0\uad6c\ub294 \uc8fc\ub85c \uc800\ud488\uc9c8 \ub370\uc774\ud130\uc5d0 \uae30\ubc18\ud558\uc5ec \uc774\ub7ec\ud55c \ubb38\uc81c\ub97c \ud574\uacb0\ud558\ub824 \ud588\uc73c\ub098, \ucd5c\uc2e0 \ubaa8\ub378\uc758 \ubc1c\uc804 \uc18d\ub3c4\ub97c \ub530\ub77c\uac00\uc9c0 \ubabb\ud588\uc2b5\ub2c8\ub2e4. \n\ubcf8 \uc5f0\uad6c\ub294 **18\ub9cc 2\ucc9c \uac1c\uc758 \uc778\uac04 \uc120\ud638\ub3c4 \ub370\uc774\ud130**\ub97c \uae30\ubc18\uc73c\ub85c, **\ub2e4\ucc28\uc6d0\uc801 \ube44\ub514\uc624 \ubcf4\uc0c1 \ubaa8\ub378**\uc744 \uc81c\uc2dc\ud558\uace0, \uc774\ub97c \ud1b5\ud574 **\ube44\ub514\uc624 \ud488\uc9c8 \ubc0f \ud504\ub86c\ud504\ud2b8 \uc77c\uce58\ub3c4**\ub97c \uac1c\uc120\ud588\uc2b5\ub2c8\ub2e4. \ub610\ud55c, **\ucd5c\uc2e0 \ud750\ub984 \uae30\ubc18 \ubaa8\ub378**\uc5d0 \uc801\ud569\ud55c \uc138 \uac00\uc9c0 \uc815\ub82c \uc54c\uace0\ub9ac\uc998\uc744 \uac1c\ubc1c\ud558\uc5ec, **\ud6c8\ub828 \uc2dc\uac04 \ubc0f \ucd94\ub860 \uc2dc\uac04** \ubaa8\ub450\uc5d0\uc11c \uc131\ub2a5\uc744 \ud5a5\uc0c1\uc2dc\ucf30\uc2b5\ub2c8\ub2e4. \uc774\ub97c \ud1b5\ud574 \uc0ac\uc6a9\uc790 \ub9de\ucda4\ud615 \ube44\ub514\uc624 \uc0dd\uc131 \uacbd\ud5d8\uc744 \uc81c\uacf5\ud560 \uc218 \uc788\uac8c \ub418\uc5c8\uc2b5\ub2c8\ub2e4.", "affiliation": "Tsinghua University", "categories": {"main_category": "Computer Vision", "sub_category": "Video Understanding"}}