{"importance": "\ubcf8 \ub17c\ubb38\uc740 **\ubd84\uc0b0\ub41c \ub2e4\uc911 \uc5d0\uc774\uc804\ud2b8 \uc2dc\uc2a4\ud15c**\uc5d0\uc11c \ud611\ub825\uc744 \ud5a5\uc0c1\uc2dc\ud0a4\ub294 \uc0c8\ub85c\uc6b4 \ubc29\ubc95\uc744 \uc81c\uc2dc\ud558\uc5ec **\ub2e4\uc591\ud55c \ubd84\uc57c\uc758 \uc5f0\uad6c\uc790\ub4e4\uc5d0\uac8c \uc911\uc694\ud55c \uc758\ubbf8**\ub97c \uc9c0\ub2d9\ub2c8\ub2e4. \ud2b9\ud788, **\ubcf5\uc7a1\ud55c \ubb38\uc81c \ud574\uacb0\uc744 \uc704\ud55c \ub2e4\uc911 \uc5d0\uc774\uc804\ud2b8 \uc2dc\uc2a4\ud15c\uc758 \uc124\uacc4 \ubc0f \uad6c\ud604**\uc5d0 \ub300\ud55c \uc0c8\ub85c\uc6b4 \ud1b5\ucc30\ub825\uc744 \uc81c\uacf5\ud558\uba70, **\uae30\uc874\uc758 \ud55c\uacc4\ub97c \uadf9\ubcf5**\ud558\uace0 \ub354\uc6b1 \ud6a8\uc728\uc801\uc778 \ud611\ub825 \uc2dc\uc2a4\ud15c\uc744 \uad6c\ucd95\ud558\ub294 \ub370 \uae30\uc5ec\ud560 \uc218 \uc788\uc2b5\ub2c8\ub2e4. \ub610\ud55c, \uc81c\uc2dc\ub41c \ubc29\ubc95\uc740 \ub2e4\uc591\ud55c \uc751\uc6a9 \ubd84\uc57c\uc5d0 \uc801\uc6a9\ub420 \uc218 \uc788\ub294 \uc7a0\uc7ac\ub825\uc744 \uac00\uc9c0\uace0 \uc788\uc73c\uba70, **\ud5a5\ud6c4 \uc5f0\uad6c**\uc5d0 \ub300\ud55c \uc0c8\ub85c\uc6b4 \ubc29\ud5a5\uc744 \uc81c\uc2dc\ud569\ub2c8\ub2e4.", "summary": "\uacf5\uc720 \uc21c\ud658 \uba54\ubaa8\ub9ac \ubcc0\ud658\uae30(SRMT)\ub97c \uc774\uc6a9\ud574 \ub2e4\uc911 \uc5d0\uc774\uc804\ud2b8 \uacbd\ub85c \ucc3e\uae30\ub97c \uac1c\uc120\ud558\uc5ec \ud611\ub825\uc744 \ud5a5\uc0c1\uc2dc\ud0a4\ub294 \ud68d\uae30\uc801\uc778 \ubc29\ubc95\uc744 \uc81c\uc2dc\ud569\ub2c8\ub2e4.", "takeaways": ["SRMT\ub294 \uc5d0\uc774\uc804\ud2b8 \uac04\uc758 \uc554\uc2dc\uc801 \uc815\ubcf4 \uad50\ud658\uc744 \uac00\ub2a5\ud558\uac8c \ud558\uc5ec \ud611\ub825\uc744 \uac1c\uc120\ud569\ub2c8\ub2e4.", "SRMT\ub294 \uc81c\ud55c\ub41c \uad00\uce21 \ud658\uacbd\uc5d0\uc11c\ub3c4 \ud6a8\uacfc\uc801\uc73c\ub85c \uc791\ub3d9\ud558\uba70, \uae34 \uacbd\ub85c\uc5d0\ub3c4 \uc77c\ubc18\ud654\ub429\ub2c8\ub2e4.", "SRMT\ub294 \ub2e4\uc591\ud55c \ubca4\uce58\ub9c8\ud06c\uc5d0\uc11c \uae30\uc874\uc758 \ub2e4\uc911 \uc5d0\uc774\uc804\ud2b8 \uac15\ud654 \ud559\uc2b5 \uc54c\uace0\ub9ac\uc998\uacfc \ube44\uad50\ud558\uc5ec \uacbd\uc7c1\ub825 \uc788\ub294 \uc131\ub2a5\uc744 \ubcf4\uc785\ub2c8\ub2e4."], "tldr": "\ub2e4\uc911 \uc5d0\uc774\uc804\ud2b8 \uac15\ud654 \ud559\uc2b5(MARL)\uc740 \ub2e4\uc591\ud55c \ud658\uacbd\uc5d0\uc11c \ud611\ub825 \ubc0f \uacbd\uc7c1 \ubb38\uc81c\ub97c \ud574\uacb0\ud558\ub294 \ub370 \uc0c1\ub2f9\ud55c \ubc1c\uc804\uc744 \uc774\ub8e8\uc5c8\uc9c0\ub9cc, \uc5d0\uc774\uc804\ud2b8 \uac04\uc758 \ud6a8\uacfc\uc801\uc778 \ud611\ub825\uc744 \uc704\ud55c \uba85\uc2dc\uc801\uc778 \uc608\uce21\uc774 \uc5ec\uc804\ud788 \uc5b4\ub824\uc6c0\uc73c\ub85c \ub0a8\uc544 \uc788\uc2b5\ub2c8\ub2e4. \ubcf8 \ub17c\ubb38\uc5d0\uc11c\ub294 \uac1c\ubcc4 \uc791\uc5c5 \uba54\ubaa8\ub9ac\ub97c \ud480\ub9c1\ud558\uace0 \uc804\uc5ed\uc801\uc73c\ub85c \ube0c\ub85c\ub4dc\uce90\uc2a4\ud305\ud558\uc5ec \uc5d0\uc774\uc804\ud2b8 \uac04\uc758 \uc554\uc2dc\uc801\uc778 \uc815\ubcf4 \uad50\ud658\uc744 \uac00\ub2a5\ud558\uac8c \ud558\ub294 \uacf5\uc720 \uc21c\ud658 \uba54\ubaa8\ub9ac \ubcc0\ud658\uae30(SRMT)\ub97c \uc81c\uc2dc\ud569\ub2c8\ub2e4.\nSRMT\ub294 \ubd80\ubd84\uc801\uc73c\ub85c \uad00\uce21 \uac00\ub2a5\ud55c \ub2e4\uc911 \uc5d0\uc774\uc804\ud2b8 \uacbd\ub85c \ucc3e\uae30 \ubb38\uc81c\uc5d0 \ub300\ud574 \ud3c9\uac00\ub418\uc5c8\uc73c\uba70, \ud2b9\ud788 \ud76c\uc18c \ubcf4\uc0c1 \ud558\uc5d0\uc11c \uae30\uc874 \uac15\ud654 \ud559\uc2b5 \uae30\uc900\uc120\ubcf4\ub2e4 \uc6b0\uc218\ud55c \uc131\ub2a5\uc744 \ubcf4\uc600\uc2b5\ub2c8\ub2e4. \ub610\ud55c, SRMT\ub294 \ub2e4\uc591\ud55c \ud658\uacbd\uc5d0\uc11c \ucd5c\uadfc MARL, \ud558\uc774\ube0c\ub9ac\ub4dc \ubc0f \uacc4\ud68d \uae30\ubc18 \uc54c\uace0\ub9ac\uc998\uacfc \uacbd\uc7c1\ub825 \uc788\ub294 \uc131\ub2a5\uc744 \ubcf4\uc600\uc2b5\ub2c8\ub2e4. \uc774\ub7ec\ud55c \uacb0\uacfc\ub294 \ubcc0\ud658\uae30 \uae30\ubc18 \uc544\ud0a4\ud14d\ucc98\uc5d0 \uacf5\uc720 \uc21c\ud658 \uba54\ubaa8\ub9ac\ub97c \ud1b5\ud569\ud558\uba74 \ubd84\uc0b0\ub41c \ub2e4\uc911 \uc5d0\uc774\uc804\ud2b8 \uc2dc\uc2a4\ud15c\uc758 \uc870\uc815\uc744 \ud5a5\uc0c1\uc2dc\ud0ac \uc218 \uc788\uc74c\uc744 \uc2dc\uc0ac\ud569\ub2c8\ub2e4.", "affiliation": "AIRI", "categories": {"main_category": "Machine Learning", "sub_category": "Reinforcement Learning"}}