{"importance": "\ubcf8 \ub17c\ubb38\uc740 **\uace0\ud488\uc9c8 \ud569\uc131 \ub2e4\uc911 \uc5b8\uc5b4 \ub2e4\uc911 \ubaa8\ub2ec \ub370\uc774\ud130\uc14b\uc744 \uc0dd\uc131\ud558\ub294 \uc0c8\ub85c\uc6b4 \ud504\ub808\uc784\uc6cc\ud06c**\ub97c \uc81c\uc2dc\ud558\uc5ec \ub2e4\uc911 \ubaa8\ub2ec \uc784\ubca0\ub529 \ubaa8\ub378\uc758 \uc131\ub2a5\uc744 \ud06c\uac8c \ud5a5\uc0c1\uc2dc\ucf30\ub2e4\ub294 \uc810\uc5d0\uc11c \uc911\uc694\ud569\ub2c8\ub2e4. **\uae30\uc874\uc758 \ub370\uc774\ud130 \ubd80\uc871 \ubb38\uc81c\ub97c \ud574\uacb0\ud558\uace0 \ub2e4\uc591\ud55c \ud558\ub958 \uc791\uc5c5\uc5d0 \uc801\uc6a9 \uac00\ub2a5\ud55c \ubc94\uc6a9\uc801\uc778 \uc784\ubca0\ub529 \ubaa8\ub378 \uac1c\ubc1c**\uc5d0 \uae30\uc5ec\ud558\uba70, \ud5a5\ud6c4 \uc5f0\uad6c\uc758 \uc0c8\ub85c\uc6b4 \ubc29\ud5a5\uc744 \uc81c\uc2dc\ud569\ub2c8\ub2e4. \ud2b9\ud788, \ub2e4\uad6d\uc5b4 \uc9c0\uc6d0 \ubc0f \ub2e4\uc591\ud55c \ubaa8\ub2ec \uc870\ud569\uc744 \uace0\ub824\ud55c \ub370\uc774\ud130\uc14b \uc0dd\uc131\uc740 **\ub2e4\uad6d\uc5b4 \ub2e4\uc911 \ubaa8\ub2ec \uc5f0\uad6c \ubd84\uc57c\uc758 \ubc1c\uc804**\uc5d0 \ud070 \uc601\ud5a5\uc744 \ubbf8\uce60 \uac83\uc73c\ub85c \uc608\uc0c1\ub429\ub2c8\ub2e4.", "summary": "\uace0\ud488\uc9c8 \ud569\uc131 \ub370\uc774\ud130\ub97c \ud65c\uc6a9, \ub2e4\uad6d\uc5b4 \ub2e4\uc911 \ubaa8\ub2ec \uc784\ubca0\ub529 \ubaa8\ub378 mmE5 \uac1c\ubc1c\ub85c SOTA \uc131\ub2a5 \ub2ec\uc131!", "takeaways": ["\uace0\ud488\uc9c8 \ud569\uc131 \ub2e4\uc911 \uc5b8\uc5b4 \ub2e4\uc911 \ubaa8\ub2ec \ub370\uc774\ud130\uc14b \uc0dd\uc131\uc744 \uc704\ud55c \uc0c8\ub85c\uc6b4 \ud504\ub808\uc784\uc6cc\ud06c \uc81c\uc2dc", "\uc81c\uc548\ub41c \ud504\ub808\uc784\uc6cc\ud06c \uae30\ubc18 mmE5 \ubaa8\ub378 \uac1c\ubc1c\uc744 \ud1b5\ud574 \ub2e4\uc591\ud55c \ubca4\uce58\ub9c8\ud06c\uc5d0\uc11c \ucd5c\ucca8\ub2e8 \uc131\ub2a5 \ub2ec\uc131", "\ub2e4\uad6d\uc5b4 \uc9c0\uc6d0 \ubc0f \ub2e4\uc591\ud55c \ubaa8\ub2ec \uc870\ud569\uc744 \uace0\ub824\ud55c \ub370\uc774\ud130\uc14b\uc740 \ub2e4\uad6d\uc5b4 \ub2e4\uc911 \ubaa8\ub2ec \uc5f0\uad6c \ubd84\uc57c\uc758 \ubc1c\uc804\uc5d0 \uae30\uc5ec"], "tldr": "\uae30\uc874\uc758 \ub2e4\uc911 \ubaa8\ub2ec \uc784\ubca0\ub529 \ubaa8\ub378\uc740 **\ub370\uc774\ud130 \ubd80\uc871**\uc73c\ub85c \uc778\ud574 \uc131\ub2a5 \ud5a5\uc0c1\uc5d0 \uc5b4\ub824\uc6c0\uc744 \uacaa\uc5c8\uc2b5\ub2c8\ub2e4. \ud2b9\ud788, **\ub2e4\uad6d\uc5b4 \uc9c0\uc6d0 \ubc0f \ub2e4\uc591\ud55c \ubaa8\ub2ec \uc870\ud569**\uc744 \uace0\ub824\ud55c \ub370\uc774\ud130\uc14b\uc774 \ubd80\uc871\ud558\uc5ec \ubaa8\ub378\uc758 \uc77c\ubc18\ud654 \uc131\ub2a5\uc774 \uc800\ud558\ub418\ub294 \ubb38\uc81c\uac00 \uc788\uc5c8\uc2b5\ub2c8\ub2e4. \ubcf8 \ub17c\ubb38\uc5d0\uc11c\ub294 \uc774\ub7ec\ud55c \ubb38\uc81c\ub97c \ud574\uacb0\ud558\uae30 \uc704\ud574 **\uace0\ud488\uc9c8 \ud569\uc131 \ub2e4\uc911 \uc5b8\uc5b4 \ub2e4\uc911 \ubaa8\ub2ec \ub370\uc774\ud130\uc14b**\uc744 \uc0dd\uc131\ud558\ub294 \uc0c8\ub85c\uc6b4 \ud504\ub808\uc784\uc6cc\ud06c\ub97c \uc81c\uc548\ud569\ub2c8\ub2e4.\n\ubcf8 \ub17c\ubb38\uc5d0\uc11c \uc81c\uc548\ud558\ub294 \ud504\ub808\uc784\uc6cc\ud06c\ub294 **\uc138 \uac00\uc9c0 \ud575\uc2ec \uae30\uc900**(\uad11\ubc94\uc704\ud55c \ubc94\uc704, \uac15\ub825\ud55c \uad50\ucc28 \ubaa8\ub2ec \uc815\ub82c, \ub192\uc740 \ucda9\uc2e4\ub3c4)\uc744 \ubc14\ud0d5\uc73c\ub85c **\ub2e4\uc591\ud55c \uc791\uc5c5, \ubaa8\ub2ec \uc870\ud569 \ubc0f \uc5b8\uc5b4**\ub97c \ud3ec\uad04\ud558\ub294 \uace0\ud488\uc9c8 \ub370\uc774\ud130\uc14b\uc744 \uc0dd\uc131\ud569\ub2c8\ub2e4. **\ub300\uaddc\ubaa8 \uc5b8\uc5b4 \ubaa8\ub378(MLLM)**\uc744 \ud65c\uc6a9\ud558\uc5ec \ud6a8\uc728\uc801\uc73c\ub85c \ub370\uc774\ud130\ub97c \uc0dd\uc131\ud558\uba70, \uc790\uccb4 \ud3c9\uac00 \ubc0f \uac1c\uc120 \uacfc\uc815\uc744 \ud1b5\ud574 \ub370\uc774\ud130\uc758 \ud488\uc9c8\uc744 \ub192\uc600\uc2b5\ub2c8\ub2e4. \uc0dd\uc131\ub41c \ub370\uc774\ud130\uc14b\uc744 \uc0ac\uc6a9\ud558\uc5ec \ud6c8\ub828\ub41c mmE5 \ubaa8\ub378\uc740 \ub2e4\uc591\ud55c \ubca4\uce58\ub9c8\ud06c\uc5d0\uc11c **\ucd5c\ucca8\ub2e8 \uc131\ub2a5**\uc744 \ub2ec\uc131\ud558\uc600\uc73c\uba70, \ud2b9\ud788 \ub2e4\uad6d\uc5b4 \uc131\ub2a5\uc5d0\uc11c \ub6f0\uc5b4\ub09c \uacb0\uacfc\ub97c \ubcf4\uc600\uc2b5\ub2c8\ub2e4.", "affiliation": "Microsoft Research", "categories": {"main_category": "Multimodal Learning", "sub_category": "Vision-Language Models"}}