[{"figure_path": "https://arxiv.org/html/2502.08524/x1.png", "caption": "Figure 1: Overview of CoCoMix. We use an SAE to extract concepts from a pretrained model\u2019s hidden state h\ud835\ude8c\ud835\ude98\ud835\ude97subscript\u210e\ud835\ude8c\ud835\ude98\ud835\ude97h_{\\mathtt{con}}italic_h start_POSTSUBSCRIPT typewriter_con end_POSTSUBSCRIPT and then select important concepts based on the attribution score (i.e., measuring the influence on the output). These selected concepts are used as labels \u2110\u2110\\mathcal{I}caligraphic_I for concept prediction by minimizing the cross-entropy loss CE\u2062(\u22c5,\u22c5)CE\u22c5\u22c5\\mathrm{CE}(\\cdot,\\cdot)roman_CE ( \u22c5 , \u22c5 ).\nThe predicted concepts \ud835\udc33\ud835\udc33{\\mathbf{z}}bold_z are then compressed into a compact vector, forming a continuous concept \ud835\udc1c\ud835\udc1c{\\mathbf{c}}bold_c, which is mixed into the model\u2019s hidden state by interleaving with token hidden representations. We demonstrate that CoCoMix is more sample efficient and outperforms standard next-token prediction and knowledge distillation baselines.", "description": "\uadf8\ub9bc 1\uc740 CoCoMix\uc758 \uac1c\uc694\ub97c \ubcf4\uc5ec\uc90d\ub2c8\ub2e4.  \uba3c\uc800, \uc0ac\uc804 \ud6c8\ub828\ub41c \ubaa8\ub378\uc758 \uc740\ub2c9 \uc0c1\ud0dc(h<sub>con</sub>)\uc5d0\uc11c SAE(Sparse Autoencoder)\ub97c \uc0ac\uc6a9\ud558\uc5ec \uac1c\ub150\uc744 \ucd94\ucd9c\ud569\ub2c8\ub2e4. \uadf8\ub7f0 \ub2e4\uc74c, \ucd9c\ub825\uc5d0 \ub300\ud55c \uc601\ud5a5(attribution score)\uc744 \uce21\uc815\ud558\uc5ec \uc911\uc694\ud55c \uac1c\ub150\uc744 \uc120\ud0dd\ud569\ub2c8\ub2e4. \uc120\ud0dd\ub41c \uac1c\ub150\uc740 \uac1c\ub150 \uc608\uce21\uc744 \uc704\ud55c \ub808\uc774\ube14(\u2110)\ub85c \uc0ac\uc6a9\ub418\uba70, \uad50\ucc28 \uc5d4\ud2b8\ub85c\ud53c \uc190\uc2e4(CE(\u22c5,\u22c5))\uc744 \ucd5c\uc18c\ud654\ud558\uc5ec \uc608\uce21\ud569\ub2c8\ub2e4. \uc608\uce21\ub41c \uac1c\ub150(\ud835\udc33)\uc740 \uc555\ucd95\ub418\uc5b4 \ud558\ub098\uc758 \ucef4\ud329\ud2b8 \ubca1\ud130\ub97c \ud615\uc131\ud558\uace0, \uc774\ub294 \uc5f0\uc18d\uc801\uc778 \uac1c\ub150(\ud835\udc1c)\uc774 \ub429\ub2c8\ub2e4.  \uc774 \uc5f0\uc18d\uc801\uc778 \uac1c\ub150\uc740 \ud1a0\ud070\uc758 \uc740\ub2c9 \ud45c\ud604\uacfc \ubc88\uac08\uc544\uac00\uba70 \ubaa8\ub378\uc758 \uc740\ub2c9 \uc0c1\ud0dc\uc5d0 \ud63c\ud569\ub429\ub2c8\ub2e4.  \uc2e4\ud5d8 \uacb0\uacfc, CoCoMix\ub294 \ud45c\ubcf8 \ud6a8\uc728\uc131\uc774 \ub192\uace0 \ud45c\uc900 \ub2e4\uc74c \ud1a0\ud070 \uc608\uce21 \ubc0f \uc9c0\uc2dd \uc99d\ub958 \uae30\uc900\ubcf4\ub2e4 \uc131\ub2a5\uc774 \uc6b0\uc218\ud568\uc744 \ubcf4\uc5ec\uc90d\ub2c8\ub2e4.", "section": "2 CoCoMix: Continuous Concept Mixing"}, {"figure_path": "https://arxiv.org/html/2502.08524/x2.png", "caption": "(a) Validation perplexity", "description": "\uadf8\ub9bc 2\ub294 CoCoMix\uc640 NTP\uc758 \uc131\ub2a5\uc744 \ub2e4\uc591\ud55c \ud6c8\ub828 \ub2e8\uacc4\uc5d0\uc11c \ube44\uad50\ud55c \uadf8\ub798\ud504\uc785\ub2c8\ub2e4. (a)\ub294 \uac80\uc99d \ud37c\ud50c\ub809\uc11c\ud2f0\ub97c, (b)\ub294 \ud3c9\uade0 \ub2e4\uc6b4\uc2a4\ud2b8\ub9bc \uc791\uc5c5 \ud37c\ud50c\ub809\uc11c\ud2f0\ub97c, (c)\ub294 \ud3c9\uade0 \ub2e4\uc6b4\uc2a4\ud2b8\ub9bc \uc791\uc5c5 \uc815\ud655\ub3c4\ub97c \ubcf4\uc5ec\uc90d\ub2c8\ub2e4. CoCoMix\ub294 \ud6c8\ub828 \ud1a0\ud070 \uc218\uac00 \uc99d\uac00\ud568\uc5d0 \ub530\ub77c \uac80\uc99d \ud37c\ud50c\ub809\uc11c\ud2f0\uc640 \ub2e4\uc6b4\uc2a4\ud2b8\ub9bc \uc791\uc5c5 \ud37c\ud50c\ub809\uc11c\ud2f0\uac00 \uc9c0\uc18d\uc801\uc73c\ub85c \uac10\uc18c\ud558\uace0, \ub2e4\uc6b4\uc2a4\ud2b8\ub9bc \uc791\uc5c5 \uc815\ud655\ub3c4\uac00 \uc9c0\uc18d\uc801\uc73c\ub85c \uc99d\uac00\ud558\ub294 \uac83\uc744 \ubcf4\uc5ec\uc90d\ub2c8\ub2e4. \ud2b9\ud788, CoCoMix\ub294 NTP\ubcf4\ub2e4 21.5% \uc801\uc740 \ud1a0\ud070\uc73c\ub85c \ub3d9\uc77c\ud55c \uc131\ub2a5\uc744 \ub2ec\uc131\ud558\uc5ec \ud45c\ubcf8 \ud6a8\uc728\uc131\uc744 \uc785\uc99d\ud569\ub2c8\ub2e4.", "section": "3 \uc2e4\ud5d8"}, {"figure_path": "https://arxiv.org/html/2502.08524/x3.png", "caption": "(b) Average downstream task perplexity", "description": "\uadf8\ub9bc (b)\ub294 \ub2e4\uc591\ud55c \ub2e4\uc6b4\uc2a4\ud2b8\ub9bc \uc791\uc5c5(\ud558\uc704 \uacfc\uc81c)\uc5d0 \ub300\ud55c \ud3c9\uade0 perplexity\ub97c \ubcf4\uc5ec\uc90d\ub2c8\ub2e4.  perplexity\ub294 \uc5b8\uc5b4 \ubaa8\ub378\uc774 \ud14d\uc2a4\ud2b8\ub97c \uc5bc\ub9c8\ub098 \uc798 \uc0dd\uc131\ud558\ub294\uc9c0 \uce21\uc815\ud558\ub294 \uc9c0\ud45c\ub85c, \uac12\uc774 \ub0ae\uc744\uc218\ub85d \uc131\ub2a5\uc774 \uc88b\uc74c\uc744 \uc758\ubbf8\ud569\ub2c8\ub2e4. \uc774 \uadf8\ub9bc\uc740 CoCoMix \ubaa8\ub378\uacfc \uae30\uc900 \ubaa8\ub378(NTP)\uc758 perplexity\ub97c \ube44\uad50\ud558\uc5ec CoCoMix \ubaa8\ub378\uc774 \ub2e4\uc591\ud55c \ud558\uc704 \uacfc\uc81c\uc5d0\uc11c \ub354 \ub0ae\uc740 perplexity\ub97c \ub2ec\uc131\ud568\uc73c\ub85c\uc368 \ub354 \ub098\uc740 \uc131\ub2a5\uc744 \ubcf4\uc5ec\uc90c\uc744 \uc2dc\uac01\uc801\uc73c\ub85c \ubcf4\uc5ec\uc90d\ub2c8\ub2e4.  \ub2e4\uc6b4\uc2a4\ud2b8\ub9bc \uc791\uc5c5\uc740 \ubaa8\ub378\uc758 \uc77c\ubc18\ud654 \ub2a5\ub825\uc744 \ud3c9\uac00\ud558\ub294 \ub370 \uc0ac\uc6a9\ub418\ub294 \ucd94\uac00\uc801\uc778 \uc5b8\uc5b4 \uc774\ud574 \uacfc\uc81c\ub85c, \ub2e4\uc591\ud55c \uc720\ud615\uc758 \uc5b8\uc5b4 \uc774\ud574 \ub2a5\ub825(\uc608: \ucd94\ub860, \uc9c8\uc758\uc751\ub2f5 \ub4f1)\uc744 \uce21\uc815\ud569\ub2c8\ub2e4. \ub530\ub77c\uc11c \uc774 \uadf8\ub9bc\uc740 CoCoMix \ubaa8\ub378\uc758 \uc804\ubc18\uc801\uc778 \uc131\ub2a5 \uc6b0\uc218\uc131\uc744 \ubcf4\uc5ec\uc8fc\ub294 \uc911\uc694\ud55c \uc9c0\ud45c\uc785\ub2c8\ub2e4.", "section": "3 Experiments"}, {"figure_path": "https://arxiv.org/html/2502.08524/x4.png", "caption": "(c) Average downstream task accuracy", "description": "\uadf8\ub9bc (c)\ub294 \ub2e4\uc591\ud55c \ub2e4\uc6b4\uc2a4\ud2b8\ub9bc \uc791\uc5c5(\ud558\uc704 \uacfc\uc81c)\uc5d0\uc11c CoCoMix \ubaa8\ub378\uc758 \uc815\ud655\ub3c4\ub97c \ubcf4\uc5ec\uc90d\ub2c8\ub2e4.  \ub2e4\uc6b4\uc2a4\ud2b8\ub9bc \uc791\uc5c5\uc774\ub780, \uc0ac\uc804 \ud6c8\ub828\ub41c \uc5b8\uc5b4 \ubaa8\ub378\uc744 \ud2b9\uc815 \uc791\uc5c5(\uc608: \uc9c8\ubb38 \uc751\ub2f5, \uac10\uc815 \ubd84\uc11d)\uc5d0 \uc801\uc6a9\ud558\ub294 \uac83\uc744 \uc758\ubbf8\ud569\ub2c8\ub2e4. \uc774 \uadf8\ub9bc\uc740 CoCoMix\uac00 \uc5ec\ub7ec \ub2e4\uc6b4\uc2a4\ud2b8\ub9bc \uc791\uc5c5\uc5d0\uc11c \uc77c\uad00\ub418\uac8c \ub192\uc740 \uc815\ud655\ub3c4\ub97c \ub2ec\uc131\ud568\uc744 \ubcf4\uc5ec\uc8fc\ub294 \ub2e4\uc591\ud55c \ud6c8\ub828 \ud1a0\ud070 \uc218\uc5d0 \ub300\ud55c \uacb0\uacfc\ub97c \ub098\ud0c0\ub0c5\ub2c8\ub2e4. \uc989, CoCoMix\ub294 \ub2e4\uc591\ud55c \ud558\uc704 \uacfc\uc81c\uc5d0\uc11c \ud6a8\uacfc\uc801\uc73c\ub85c \uc77c\ubc18\ud654\ub41c\ub2e4\ub294 \uac83\uc744 \uc758\ubbf8\ud569\ub2c8\ub2e4.  ", "section": "3 Experiments"}, {"figure_path": "https://arxiv.org/html/2502.08524/x5.png", "caption": "Figure 2: \nCoCoMix vs. NTP performance at different training checkpoints. Each model contains a total of 1.38B parameters. Each model is trained on the OpenWebText dataset. For CoCoMix, the concepts are extracted from a 124M-sized model (10\u00d7\\times\u00d7 smaller than the base model). The plots show improvements in: (a) validation perplexity, (b) average perplexity on LAMBADA, WikiText-103, and (c) average accuracy on HellaSwag, PIQA, SIQA, Arc-Easy, and WinoGrande.", "description": "\uadf8\ub9bc 2\ub294 13.8B \ud30c\ub77c\ubbf8\ud130\ub97c \uac00\uc9c4 \ubaa8\ub378\uc5d0 \ub300\ud55c CoCoMix\uc640 NTP(Next Token Prediction)\uc758 \uc131\ub2a5 \ube44\uad50 \uacb0\uacfc\ub97c \ubcf4\uc5ec\uc90d\ub2c8\ub2e4. \ub450 \ubaa8\ub378 \ubaa8\ub450 OpenWebText \ub370\uc774\ud130\uc14b\uc73c\ub85c \ud559\uc2b5\ub418\uc5c8\uc73c\uba70, CoCoMix\uc758 \uacbd\uc6b0 124M \ud30c\ub77c\ubbf8\ud130\uc758 \uc0ac\uc804 \ud559\uc2b5\ub41c \ubaa8\ub378(\uae30\ubcf8 \ubaa8\ub378\ubcf4\ub2e4 10\ubc30 \uc791\uc74c)\uc5d0\uc11c \ucd94\ucd9c\ud55c \uac1c\ub150\uc744 \uc0ac\uc6a9\ud569\ub2c8\ub2e4. \uadf8\ub9bc\uc740 (a) \uac80\uc99d \ud37c\ud50c\ub809\uc11c\ud2f0, (b) LAMBADA\uc640 WikiText-103\uc5d0 \ub300\ud55c \ud3c9\uade0 \ud37c\ud50c\ub809\uc11c\ud2f0, (c) HellaSwag, PIQA, SIQA, Arc-Easy, \uadf8\ub9ac\uace0 WinoGrande\uc5d0 \ub300\ud55c \ud3c9\uade0 \uc815\ud655\ub3c4 \uc138 \uac00\uc9c0 \uce21\uba74\uc5d0\uc11c CoCoMix\uac00 \uac1c\uc120\ub41c \uc131\ub2a5\uc744 \ubcf4\uc784\uc744 \ubcf4\uc5ec\uc90d\ub2c8\ub2e4.", "section": "3 Experiments"}, {"figure_path": "https://arxiv.org/html/2502.08524/x6.png", "caption": "(a) OpenWebText, PPL (\u2193\u2193\\downarrow\u2193)", "description": "\uadf8\ub9bc 2\ub294 CoCoMix\uc640 \uae30\ubcf8\uc801\uc778 \ub2e4\uc74c \ud1a0\ud070 \uc608\uce21(NTP) \ubc29\ubc95\uc758 \uc131\ub2a5\uc744 \ub2e4\uc591\ud55c \ud6c8\ub828 \ub2e8\uacc4\uc5d0\uc11c \ube44\uad50\ud55c \uac83\uc785\ub2c8\ub2e4. CoCoMix\ub294 OpenWebText \ub370\uc774\ud130\uc14b\uc73c\ub85c \ud6c8\ub828\ub418\uc5c8\uc73c\uba70, \uac1c\ub150\uc740 1\uc5b5 2\ucc9c 4\ubc31\ub9cc \ud30c\ub77c\ubbf8\ud130 \ubaa8\ub378(\uae30\ubcf8 \ubaa8\ub378\ubcf4\ub2e4 10\ubc30 \uc791\uc74c)\uc5d0\uc11c \ucd94\ucd9c\ub418\uc5c8\uc2b5\ub2c8\ub2e4. \uadf8\ub9bc\uc740 \uac80\uc99d \ud37c\ud50c\ub809\uc11c\ud2f0, LAMBADA, WikiText-103\uc758 \ud3c9\uade0 \ud37c\ud50c\ub809\uc11c\ud2f0, \uadf8\ub9ac\uace0 HellaSwag, PIQA, SIQA, Arc-Easy, WinoGrande\uc758 \ud3c9\uade0 \uc815\ud655\ub3c4\ub97c \ubcf4\uc5ec\uc90d\ub2c8\ub2e4. CoCoMix\ub294 \uc138 \uac00\uc9c0 \uc9c0\ud45c \ubaa8\ub450\uc5d0\uc11c \uc9c0\uc18d\uc801\uc778 \uac1c\uc120\uc744 \ubcf4\uc5ec\uc90d\ub2c8\ub2e4.", "section": "3 Experiments"}, {"figure_path": "https://arxiv.org/html/2502.08524/x7.png", "caption": "(b) LAMBADA, PPL (\u2193\u2193\\downarrow\u2193)", "description": "\uadf8\ub9bc (b)\ub294 LAMBADA \ub370\uc774\ud130\uc14b\uc5d0 \ub300\ud55c perplexity(PPL)\ub97c \ubcf4\uc5ec\uc90d\ub2c8\ub2e4.  Perplexity\ub294 \uc5b8\uc5b4 \ubaa8\ub378\uc774 \uc5bc\ub9c8\ub098 \uc798 \ud14d\uc2a4\ud2b8\ub97c \uc0dd\uc131\ud558\ub294\uc9c0 \uce21\uc815\ud558\ub294 \uc9c0\ud45c\ub85c, \ub0ae\uc744\uc218\ub85d \uc88b\uc2b5\ub2c8\ub2e4.  \uc774 \uadf8\ub798\ud504\ub294 \ud6c8\ub828 \ud1a0\ud070 \uc218\uac00 \uc99d\uac00\ud568\uc5d0 \ub530\ub77c CoCoMix\uc640 NTP(\ub2e4\uc74c \ud1a0\ud070 \uc608\uce21) \ubaa8\ub378\uc758 LAMBADA \ub370\uc774\ud130\uc14b\uc5d0 \ub300\ud55c perplexity \ubcc0\ud654\ub97c \ube44\uad50 \ubd84\uc11d\ud569\ub2c8\ub2e4.  \uc989, CoCoMix\uac00 \ud6c8\ub828 \ub370\uc774\ud130\uac00 \ub9ce\uc544\uc9d0\uc5d0 \ub530\ub77c NTP\ubcf4\ub2e4 \ub0ae\uc740 perplexity\ub97c \ub2ec\uc131\ud558\uc5ec LAMBADA \ub370\uc774\ud130\uc14b\uc5d0\uc11c \ub354 \ub098\uc740 \uc131\ub2a5\uc744 \ubcf4\uc784\uc744 \uc2dc\uac01\uc801\uc73c\ub85c \ub098\ud0c0\ub0c5\ub2c8\ub2e4.", "section": "3 Experiments"}, {"figure_path": "https://arxiv.org/html/2502.08524/x8.png", "caption": "(c) WikiText-103, PPL (\u2193\u2193\\downarrow\u2193)", "description": "\uadf8\ub9bc (c)\ub294 WikiText-103 \ub370\uc774\ud130\uc14b\uc5d0 \ub300\ud55c perplexity(PPL) \ubcc0\ud654\ub97c \ubcf4\uc5ec\uc90d\ub2c8\ub2e4.  \ub0ae\uc740 perplexity \uac12\uc740 \ubaa8\ub378\uc758 \uc131\ub2a5\uc774 \uc88b\ub2e4\ub294 \uac83\uc744 \uc758\ubbf8\ud569\ub2c8\ub2e4.  x\ucd95\uc740 \ud559\uc2b5\uc5d0 \uc0ac\uc6a9\ub41c \ud1a0\ud070 \uc218(\ub2e8\uc704: B, \uc989 1B\ub294 10\uc5b5)\uc774\uace0, y\ucd95\uc740 perplexity \uac12\uc785\ub2c8\ub2e4.  \ub2e4\uc591\ud55c \ud559\uc2b5 \ub2e8\uacc4\uc5d0\uc11c NTP(Next Token Prediction)\uc640 CoCoMix(Continuous Concept Mixing) \ubaa8\ub378\uc758 perplexity\ub97c \ube44\uad50\ud558\uc5ec CoCoMix \ubaa8\ub378\uc774 NTP \ubaa8\ub378\ubcf4\ub2e4 \ud6e8\uc52c \ub0ae\uc740 perplexity\ub97c \ub2ec\uc131\ud568\uc744 \ubcf4\uc5ec\uc90d\ub2c8\ub2e4. \uc774\ub294 CoCoMix\uac00 WikiText-103 \ub370\uc774\ud130\uc14b\uc5d0 \ub300\ud574 \ub354 \uc6b0\uc218\ud55c \uc131\ub2a5\uc744 \uac00\uc9d0\uc744 \uc2dc\uc0ac\ud569\ub2c8\ub2e4.", "section": "3 Experiments"}, {"figure_path": "https://arxiv.org/html/2502.08524/x9.png", "caption": "(d) HellaSwag, Acc-n (\u2191\u2191\\uparrow\u2191)", "description": "\uadf8\ub9bc (d)\ub294 HellaSwag \ub370\uc774\ud130\uc14b\uc5d0 \ub300\ud55c \uc815\ud655\ub3c4(Acc-n)\ub97c \ubcf4\uc5ec\uc90d\ub2c8\ub2e4.  Acc-n\uc740 \uc815\ub2f5\uc744 \ub9de\ucd98 \ube44\uc728\uc744 \uc758\ubbf8\ud558\uba70,  \u2191 \uae30\ud638\ub294 CoCoMix \ubaa8\ub378\uc774 \uae30\uc900 \ubaa8\ub378(NTP)\ubcf4\ub2e4 \uc131\ub2a5\uc774 \ud5a5\uc0c1\ub418\uc5c8\uc74c\uc744 \ub098\ud0c0\ub0c5\ub2c8\ub2e4.  \ub450 \uac1c\uc758 \u2191 \uae30\ud638\ub294 \uc131\ub2a5 \ud5a5\uc0c1\uc774 \uc0c1\ub2f9\ud788 \ud06c\ub2e4\ub294 \uac83\uc744 \uac15\uc870\ud569\ub2c8\ub2e4. \uc774 \uadf8\ub9bc\uc740 CoCoMix \ubaa8\ub378\uc774 \ub2e4\uc591\ud55c \uc5b8\uc5b4 \ubaa8\ub378\ub9c1 \uc791\uc5c5\uc5d0\uc11c \uc6b0\uc218\ud55c \uc131\ub2a5\uc744 \ubcf4\uc5ec\uc90c\uc744 \uc2dc\uac01\uc801\uc73c\ub85c \ubcf4\uc5ec\uc8fc\ub294 \uc5ec\ub7ec \uadf8\ub9bc \uc911 \ud558\ub098\uc785\ub2c8\ub2e4.", "section": "3 Experiments"}, {"figure_path": "https://arxiv.org/html/2502.08524/x10.png", "caption": "(e) PIQA, Acc (\u2191\u2191\\uparrow\u2191)", "description": "\uadf8\ub9bc (e)\ub294 PIQA \ub370\uc774\ud130\uc14b\uc5d0 \ub300\ud55c CoCoMix \ubaa8\ub378\uc758 \uc815\ud655\ub3c4\ub97c \ubcf4\uc5ec\uc90d\ub2c8\ub2e4.  PIQA\ub294 \ubb3c\uc74c\uacfc \ub2f5\ubcc0\uc758 \uc30d\uc73c\ub85c \uad6c\uc131\ub41c \ub370\uc774\ud130\uc14b\uc774\uba70, \ubaa8\ub378\uc758 \ucd94\ub860 \ub2a5\ub825\uc744 \ud3c9\uac00\ud558\ub294 \ub370 \uc0ac\uc6a9\ub429\ub2c8\ub2e4.  'Acc (\u2191\u2191)'\ub294  CoCoMix \ubaa8\ub378\uc774 PIQA \ub370\uc774\ud130\uc14b\uc5d0\uc11c \uc0c1\ub2f9\ud55c \uc815\ud655\ub3c4 \ud5a5\uc0c1\uc744 \ubcf4\uc600\ub2e4\ub294 \uac83\uc744 \uc758\ubbf8\ud569\ub2c8\ub2e4.  \ub450 \uac1c\uc758 \ud654\uc0b4\ud45c\ub294 \uc815\ud655\ub3c4 \ud5a5\uc0c1\uc758 \uc815\ub3c4\ub97c \uac15\uc870\ud569\ub2c8\ub2e4. \uc774 \uadf8\ub9bc\uc740 CoCoMix \ubaa8\ub378\uc774 \ub2e4\ub978 \ubaa8\ub378\ub4e4\uc5d0 \ube44\ud574 PIQA\uc640 \uac19\uc740 \ucd94\ub860 \uae30\ubc18 \uacfc\uc81c\uc5d0\uc11c \ub354 \ub098\uc740 \uc131\ub2a5\uc744 \ubcf4\uc784\uc744 \uc2dc\uac01\uc801\uc73c\ub85c \ubcf4\uc5ec\uc8fc\ub294 \uc5ed\ud560\uc744 \ud569\ub2c8\ub2e4.", "section": "3 Experiments"}, {"figure_path": "https://arxiv.org/html/2502.08524/x11.png", "caption": "(f) SIQA, Acc (\u2191\u2191\\uparrow\u2191)", "description": "\uadf8\ub9bc (f)\ub294 SIQA(Social Interaction QA) \ub370\uc774\ud130\uc14b\uc5d0\uc11c CoCoMix \ubaa8\ub378\uc758 \uc815\ud655\ub3c4\ub97c \ubcf4\uc5ec\uc90d\ub2c8\ub2e4.  'Acc (\u2191\u2191)'\ub294 \uc815\ud655\ub3c4\uac00 \uc0c1\ub2f9\ud788 \ud5a5\uc0c1\ub418\uc5c8\uc74c\uc744 \uc758\ubbf8\ud569\ub2c8\ub2e4. \uc774\ub294 CoCoMix\uac00 \uc0ac\ud68c\uc801 \uc0c1\ud638\uc791\uc6a9\uc5d0 \ub300\ud55c \uc774\ud574\ub97c \uc694\uad6c\ud558\ub294 \uc9c8\ubb38\uc5d0 \ub300\ud574\uc11c\ub3c4 \uc6b0\uc218\ud55c \uc131\ub2a5\uc744 \ubcf4\uc784\uc744 \uc2dc\uc0ac\ud569\ub2c8\ub2e4.  \uc989,  \ub2e8\uc21c\ud55c \uc5b8\uc5b4 \ubaa8\ub378\ub9c1\ubfd0 \uc544\ub2c8\ub77c, \ubcf4\ub2e4 \ubcf5\uc7a1\ud558\uace0 \uc0c1\ud669\uc5d0 \ub9de\ub294 \uc774\ud574\ub97c \ud544\uc694\ub85c \ud558\ub294 \uc791\uc5c5\uc5d0\uc11c\ub3c4 \ud6a8\uacfc\uc801\uc784\uc744 \ub098\ud0c0\ub0c5\ub2c8\ub2e4.", "section": "3 Experiments"}, {"figure_path": "https://arxiv.org/html/2502.08524/x12.png", "caption": "(g) Arc-Easy, Acc (\u2191\u2191\\uparrow\u2191)", "description": "\uadf8\ub9bc (g)\ub294 Arc-Easy \ub370\uc774\ud130\uc14b\uc5d0 \ub300\ud55c CoCoMix \ubaa8\ub378\uc758 \uc815\ud655\ub3c4(Accuracy)\ub97c \ubcf4\uc5ec\uc90d\ub2c8\ub2e4.  'Acc (\u2191\u2191)'\ub294  CoCoMix \ubaa8\ub378\uc774 \uae30\uc874\uc758 Next Token Prediction (NTP) \ubaa8\ub378\uc5d0 \ube44\ud574 Arc-Easy \uc791\uc5c5\uc5d0\uc11c \uc0c1\ub2f9\ud788 \ub192\uc740 \uc815\ud655\ub3c4 \ud5a5\uc0c1\uc744 \ubcf4\uc600\ub2e4\ub294 \uac83\uc744 \uc758\ubbf8\ud569\ub2c8\ub2e4.  \ub450 \uac1c\uc758 \ud654\uc0b4\ud45c\ub294 \uc815\ud655\ub3c4 \ud5a5\uc0c1\uc758 \uc815\ub3c4\uac00 \ub9e4\uc6b0 \ud06c\ub2e4\ub294 \uac83\uc744 \uac15\uc870\ud569\ub2c8\ub2e4. \uc774 \uadf8\ub9bc\uc740 CoCoMix\uac00 \ub2e4\uc591\ud55c downstream task\uc5d0\uc11c \uc77c\uad00\ub418\uac8c \uc131\ub2a5 \ud5a5\uc0c1\uc744 \ub2ec\uc131\ud588\uc74c\uc744 \ubcf4\uc5ec\uc8fc\ub294 \uc5ec\ub7ec \uadf8\ub9bc \uc911 \ud558\ub098\uc785\ub2c8\ub2e4.", "section": "3 Experiments"}, {"figure_path": "https://arxiv.org/html/2502.08524/x13.png", "caption": "(h) WinoGrande, Acc (\u2191\u2191\\uparrow\u2191)", "description": "\uadf8\ub9bc (h)\ub294 WinoGrande \ub370\uc774\ud130\uc14b\uc5d0 \ub300\ud55c \uc815\ud655\ub3c4(Accuracy)\ub97c \ubcf4\uc5ec\uc90d\ub2c8\ub2e4.  WinoGrande\ub294 \uc0c1\uc2dd\uc801 \ucd94\ub860 \ub2a5\ub825\uc744 \ud3c9\uac00\ud558\ub294 \ubca4\uce58\ub9c8\ud06c \ub370\uc774\ud130\uc14b\uc774\uba70, \uc774 \uadf8\ub798\ud504\ub294 CoCoMix \ubaa8\ub378\uacfc \uae30\uc874\uc758 \ub2e4\uc74c \ud1a0\ud070 \uc608\uce21(NTP) \ubaa8\ub378\uc758 \uc131\ub2a5\uc744 \ud6c8\ub828 \ud1a0\ud070 \uc218\uc5d0 \ub530\ub77c \ube44\uad50\ud569\ub2c8\ub2e4.  \ud654\uc0b4\ud45c(\u2191\u2191)\ub294 CoCoMix \ubaa8\ub378\uc774 NTP \ubaa8\ub378\ubcf4\ub2e4 WinoGrande \ub370\uc774\ud130\uc14b\uc5d0\uc11c \uc720\uc758\ubbf8\ud558\uac8c \ub354 \ub192\uc740 \uc815\ud655\ub3c4\ub97c \ub2ec\uc131\ud588\uc74c\uc744 \uc2dc\uac01\uc801\uc73c\ub85c \ubcf4\uc5ec\uc90d\ub2c8\ub2e4.", "section": "3 Experiments"}, {"figure_path": "https://arxiv.org/html/2502.08524/x14.png", "caption": "Figure 3: \nCoCoMix vs. NTP performance at different model sizes. We consider various model sizes, including 69M, 386M, and 1.38B parameters and train on 200B OpenWebText tokens. We evaluate the models on OpenWebText validation perplexity and downstream datasets LAMBADA, WikiText-103, HellaSwag, PIQA, SIQA, Arc-Easy, and WinoGrande.", "description": "\uadf8\ub9bc 3\uc740 \ub2e4\uc591\ud55c \ud06c\uae30(69M, 386M, 13.8B \ud30c\ub77c\ubbf8\ud130)\uc758 \uc5b8\uc5b4 \ubaa8\ub378\uc5d0 \ub300\ud574 CoCoMix\uc640 NTP\uc758 \uc131\ub2a5\uc744 \ube44\uad50\ud55c \uacb0\uacfc\ub97c \ubcf4\uc5ec\uc90d\ub2c8\ub2e4.  200B\uac1c\uc758 OpenWebText \ud1a0\ud070\uc73c\ub85c \ubaa8\ub378\ub4e4\uc744 \ud559\uc2b5\uc2dc\ucf30\uace0, OpenWebText \uac80\uc99d \ud37c\ud50c\ub809\uc11c\ud2f0\uc640 LAMBADA, WikiText-103, HellaSwag, PIQA, SIQA, Arc-Easy, WinoGrande \ub4f1\uc758 \ub2e4\uc6b4\uc2a4\ud2b8\ub9bc \ub370\uc774\ud130\uc14b\uc744 \uc0ac\uc6a9\ud558\uc5ec \ubaa8\ub378\ub4e4\uc744 \ud3c9\uac00\ud588\uc2b5\ub2c8\ub2e4.  \uac01 \uadf8\ub798\ud504\ub294 \ud2b9\uc815 \uc9c0\ud45c(\ud37c\ud50c\ub809\uc11c\ud2f0 \ub610\ub294 \uc815\ud655\ub3c4)\uc5d0 \ub300\ud55c CoCoMix\uc640 NTP\uc758 \uc131\ub2a5 \ucc28\uc774\ub97c \ubcf4\uc5ec\uc90d\ub2c8\ub2e4. \uc774\ub97c \ud1b5\ud574 \ub2e4\uc591\ud55c \ubaa8\ub378 \ud06c\uae30\uc5d0 \ub530\ub978 CoCoMix\uc758 \uc131\ub2a5\uacfc \ud6a8\uc728\uc131\uc744 \ud30c\uc545\ud560 \uc218 \uc788\uc2b5\ub2c8\ub2e4.", "section": "3 Experiments"}, {"figure_path": "https://arxiv.org/html/2502.08524/x15.png", "caption": "(a) Weak-to-strong: Avg. Perplexity", "description": "\uadf8\ub9bc 4(a)\ub294 \uc57d\uc138-\uac15\uc138 \ud559\uc2b5 \uc124\uc815\uc5d0\uc11c \ud3c9\uade0 perplexity\ub97c \ubcf4\uc5ec\uc90d\ub2c8\ub2e4.  \uc57d\uc138-\uac15\uc138 \ud559\uc2b5\uc774\ub780 \uc791\uc740 \ubaa8\ub378(124M \ub9e4\uac1c\ubcc0\uc218)\uc5d0\uc11c \ucd94\ucd9c\ub41c \uac1c\ub150\uc744 \uc0ac\uc6a9\ud558\uc5ec \ub354 \ud070 \ubaa8\ub378(386M \ub9e4\uac1c\ubcc0\uc218)\uc744 \ud559\uc2b5\uc2dc\ud0a4\ub294 \uac83\uc744 \uc758\ubbf8\ud569\ub2c8\ub2e4.  \uc774 \uadf8\ub9bc\uc740 OpenWebText, LAMBADA, WikiText \ub370\uc774\ud130\uc14b\uc5d0 \ub300\ud55c \ud3c9\uade0 perplexity\ub97c \ub098\ud0c0\ub0b4\uba70, CoCoMix\uac00 KD(\uc9c0\uc2dd \uc99d\ub958) \ubc0f NTP(\ub2e4\uc74c \ud1a0\ud070 \uc608\uce21)\ubcf4\ub2e4 \uc131\ub2a5\uc774 \uc6b0\uc218\ud568\uc744 \ubcf4\uc5ec\uc90d\ub2c8\ub2e4.", "section": "3 Experiments"}, {"figure_path": "https://arxiv.org/html/2502.08524/x16.png", "caption": "(b) Weak-to-strong: Avg. Accuracy", "description": "\uadf8\ub9bc (b)\ub294 \uc57d\ud55c-\uac15\ud55c \uc9c0\ub3c4 \ud559\uc2b5 \uc124\uc815\uc5d0\uc11c \ud3c9\uade0 \uc815\ud655\ub3c4\ub97c \ubcf4\uc5ec\uc90d\ub2c8\ub2e4.  \uc5ec\uae30\uc11c 124M \ud06c\uae30\uc758 \ubaa8\ub378\uc774 386M \ud06c\uae30\uc758 \ubaa8\ub378\uc744 \uc704\ud55c \uad50\uc0ac \ubaa8\ub378 \uc5ed\ud560\uc744 \ud569\ub2c8\ub2e4.  OpenWebText, LAMBADA, WikiText \ub370\uc774\ud130\uc14b\uc744 \uc0ac\uc6a9\ud55c \ud3c9\uade0 perplexity\uc640 HellaSwag, PIQA, SIQA, Arc-Easy, WinoGrande \ub370\uc774\ud130\uc14b\uc744 \uc0ac\uc6a9\ud55c \ud3c9\uade0 \uc815\ud655\ub3c4\ub97c \ube44\uad50\ud558\uc5ec CoCoMix\uc758 \uc131\ub2a5\uc744 \ubcf4\uc5ec\uc90d\ub2c8\ub2e4.  CoCoMix\ub294 \uae30\uc874\uc758 \uc9c0\uc2dd \uc99d\ub958(KD) \ubc29\ubc95\ubcf4\ub2e4 \uc57d\ud55c-\uac15\ud55c \uc9c0\ub3c4 \ud559\uc2b5 \uc124\uc815\uc5d0\uc11c \uc0c1\ub2f9\ud55c \uc131\ub2a5 \ud5a5\uc0c1\uc744 \ubcf4\uc5ec\uc90d\ub2c8\ub2e4.", "section": "3 Experiments"}, {"figure_path": "https://arxiv.org/html/2502.08524/x17.png", "caption": "(c) Distribution shift (OpenWebMath)", "description": "\uadf8\ub9bc 4(c)\ub294 CoCoMix, \uc9c0\uc2dd \uc99d\ub958(KD), \uadf8\ub9ac\uace0 \uc21c\uc218 \ub2e4\uc74c \ud1a0\ud070 \uc608\uce21(NTP) \uc138 \uac00\uc9c0 \ubc29\ubc95\uc758 \uc131\ub2a5\uc744 OpenWebMath \ub370\uc774\ud130\uc14b\uc5d0\uc11c \ube44\uad50 \ubd84\uc11d\ud55c \uacb0\uacfc\ub97c \ubcf4\uc5ec\uc90d\ub2c8\ub2e4.  OpenWebMath\ub294 \uc218\ud559 \uad00\ub828 \uc9c0\uc2dd\uc5d0 \ucd08\uc810\uc744 \ub9de\ucd98 \ub370\uc774\ud130\uc14b\uc774\uae30 \ub54c\ubb38\uc5d0, \uc774 \uadf8\ub9bc\uc740 \ubaa8\ub378\ub4e4\uc774 OpenWebMath\uc640 \uac19\uc740 \uc0c8\ub85c\uc6b4 \ub370\uc774\ud130 \ubd84\ud3ec\uc5d0 \uc801\uc751\ud558\ub294 \ub2a5\ub825, \uc989 \uc77c\ubc18\ud654 \ub2a5\ub825\uc744 \ud3c9\uac00\ud558\uae30 \uc704\ud55c \uac83\uc785\ub2c8\ub2e4.  \uc774 \uadf8\ub9bc\uc744 \ud1b5\ud574  CoCoMix\uac00 \uae30\uc874 \ubc29\ubc95\ub4e4\ubcf4\ub2e4 \uc0c8\ub85c\uc6b4 \ub370\uc774\ud130\uc14b\uc5d0 \ub300\ud574 \ub354 \ub098\uc740 \uc131\ub2a5\uc744 \ubcf4\uc774\ub294\uc9c0 \ud655\uc778\ud560 \uc218 \uc788\uc2b5\ub2c8\ub2e4.", "section": "3 \uc2e4\ud5d8"}, {"figure_path": "https://arxiv.org/html/2502.08524/x18.png", "caption": "Figure 4: \nCoCoMix vs. Knowledge Distillation (KD).\nFor our weak-to-strong supervision setup, we train a 386M model where the teacher of KD (or concept extraction for CoCoMix) is a 124M-sized model: we report (a) average perplexity over OpenWebText, LAMABADA, and WikiText and (b) average accuracy over HellaSwag, PIQA, SIQA, Arc-Easy, and WiniGrande dataset. For (c) a distribution shift setup, we train all methods on OpenWebMath, a math specific pretraining corpus.", "description": "\uadf8\ub9bc 4\ub294 386M \ud06c\uae30\uc758 \ubaa8\ub378\uc744 \uc0ac\uc6a9\ud558\uc5ec CoCoMix\uc640 \uc9c0\uc2dd \uc99d\ub958(KD)\uc758 \uc131\ub2a5\uc744 \ube44\uad50\ud55c \uacb0\uacfc\ub97c \ubcf4\uc5ec\uc90d\ub2c8\ub2e4. \uc57d-\uac15 \uc9c0\ub3c4 \ud559\uc2b5 \uc124\uc815\uc5d0\uc11c, KD\uc758 \uad50\uc0ac \ubaa8\ub378(\ub610\ub294 CoCoMix\uc758 \uac1c\ub150 \ucd94\ucd9c \ubaa8\ub378)\uc740 124M \ud06c\uae30\uc758 \ubaa8\ub378\ub85c \uc124\uc815\ub418\uc5c8\uc2b5\ub2c8\ub2e4. \uadf8\ub9bc\uc5d0\uc11c\ub294 (a) OpenWebText, LAMBADA \ubc0f WikiText\uc5d0 \ub300\ud55c \ud3c9\uade0 perplexity\uc640 (b) HellaSwag, PIQA, SIQA, Arc-Easy \ubc0f WinoGrande \ub370\uc774\ud130\uc14b\uc5d0 \ub300\ud55c \ud3c9\uade0 \uc815\ud655\ub3c4\ub97c \ube44\uad50 \ubd84\uc11d\ud558\uc600\uc2b5\ub2c8\ub2e4. (c)\uc5d0\uc11c\ub294 \ub370\uc774\ud130 \ubd84\ud3ec \ubcc0\ud654 \uc124\uc815\uc744 \uc704\ud574 \ubaa8\ub4e0 \ubc29\ubc95\ub860\uc744 \uc218\ud559 \uc804\uc6a9 \uc0ac\uc804 \ud6c8\ub828 \ucf54\ud37c\uc2a4\uc778 OpenWebMath\ub85c \ud6c8\ub828\uc2dc\ud0a8 \uacb0\uacfc\ub97c \ubcf4\uc5ec\uc90d\ub2c8\ub2e4.  \uc989, \uadf8\ub9bc 4\ub294 \uc11c\ub85c \ub2e4\ub978 \ud06c\uae30\uc758 \ubaa8\ub378\uacfc \uc11c\ub85c \ub2e4\ub978 \ub370\uc774\ud130\uc14b\uc744 \uc0ac\uc6a9\ud558\uc5ec CoCoMix\uc640 KD \uae30\ubc95\uc744 \ube44\uad50 \ubd84\uc11d\ud558\uace0, \uadf8 \uacb0\uacfc\ub97c perplexity\uc640 \uc815\ud655\ub3c4 \uc9c0\ud45c\ub85c \uc81c\uc2dc\ud569\ub2c8\ub2e4.", "section": "3 Experiments"}, {"figure_path": "https://arxiv.org/html/2502.08524/x19.png", "caption": "Figure 5: Qualitative demonstration of the concept steering effect. CoCoMix and GPT2 models are 350M and 124M parameter transformers, respectively, trained on the OpenWebText dataset. For CoCoMix, we manipulate the predicted concept logit \ud835\udc33\ud835\udc33{\\mathbf{z}}bold_z, while for GPT2, we adjust the SAE concept space \ud835\udc1c\ud835\udc1c{\\mathbf{c}}bold_c by increasing the activation of a specific concept index. This illustrates the impact of targeted concept steering on the respective model outputs.", "description": "\uadf8\ub9bc 5\ub294 \uac1c\ub150 \uc870\ud5a5 \ud6a8\uacfc\ub97c \uc815\uc131\uc801\uc73c\ub85c \ubcf4\uc5ec\uc90d\ub2c8\ub2e4. OpenWebText \ub370\uc774\ud130\uc14b\uc73c\ub85c \ud559\uc2b5\ub41c CoCoMix\uc640 GPT-2 \ubaa8\ub378\uc740 \uac01\uac01 3\uc5b5 5\ucc9c\ub9cc\uac1c\uc640 1\uc5b5 2\ucc9c 4\ubc31\ub9cc\uac1c\uc758 \ud30c\ub77c\ubbf8\ud130\ub97c \uac00\uc9c4 \ubcc0\ud658\uae30 \ubaa8\ub378\uc785\ub2c8\ub2e4. CoCoMix\uc758 \uacbd\uc6b0 \uc608\uce21\ub41c \uac1c\ub150 \ub85c\uc9d3 \ud835\udc33 \ub97c \uc870\uc791\ud558\uc5ec, GPT-2\uc758 \uacbd\uc6b0 \ud2b9\uc815 \uac1c\ub150 \uc778\ub371\uc2a4\uc758 \ud65c\uc131\ud654\ub97c \uc99d\uac00\uc2dc\ucf1c SAE \uac1c\ub150 \uacf5\uac04 \ud835\udc1c \ub97c \uc870\uc815\ud569\ub2c8\ub2e4. \uc774 \uadf8\ub9bc\uc740 \ubaa9\ud45c \uac1c\ub150 \uc870\ud5a5\uc774 \uac01 \ubaa8\ub378\uc758 \ucd9c\ub825\uc5d0 \ubbf8\uce58\ub294 \uc601\ud5a5\uc744 \ubcf4\uc5ec\uc90d\ub2c8\ub2e4.", "section": "3.2 CoCoMix\uc758 \ud574\uc11d \uac00\ub2a5\uc131 \ubc0f \uc870\ud5a5"}, {"figure_path": "https://arxiv.org/html/2502.08524/x20.png", "caption": "(a) Effectiveness of the attribution score", "description": "\uadf8\ub9bc 6(a)\ub294 \ubaa8\ub378\uc758 \ucd9c\ub825\uc5d0 \ub300\ud55c \uac01 \uac1c\ub150\uc758 \uc601\ud5a5\uc744 \uc815\ub7c9\ud654\ud558\ub294 \uc9c0\ud45c\uc778 \uadc0\uc778 \uc810\uc218(attribution score)\uc758 \ud6a8\uacfc\ub97c \ubcf4\uc5ec\uc90d\ub2c8\ub2e4. \uadc0\uc778 \uc810\uc218\ub97c \uc0ac\uc6a9\ud558\uc5ec \uc911\uc694\ud55c \uac1c\ub150\uc744 \uc120\ud0dd\ud558\ub294 \uac83\uc774 \ud65c\uc131\ud654 \uac12(activation value)\ub9cc \uc0ac\uc6a9\ud558\ub294 \uac83\ubcf4\ub2e4 \uc0d8\ud50c \ud6a8\uc728\uc131\uc744 17.5% \ud5a5\uc0c1\uc2dc\ud0a4\ub294 \uac83\uc744 \ubcf4\uc5ec\uc90d\ub2c8\ub2e4. \uc774\ub294 \uadc0\uc778 \uc810\uc218\uac00 \uac1c\ub150\uc758 \uc911\uc694\uc131\uc744 \ub354 \uc798 \ubc18\uc601\ud558\uace0, \ubd88\ud544\uc694\ud55c \uac1c\ub150\uc744 \uc81c\uac70\ud558\uc5ec \ubaa8\ub378 \uc131\ub2a5\uc744 \ud5a5\uc0c1\uc2dc\ud0a4\ub294 \ub370 \ub3c4\uc6c0\uc774 \ub428\uc744 \uc2dc\uc0ac\ud569\ub2c8\ub2e4.", "section": "3.3 CoCoMix\uc758 \ud6a8\uacfc \ubd84\uc11d"}, {"figure_path": "https://arxiv.org/html/2502.08524/x21.png", "caption": "(b) Concept vs. direct hidden state", "description": "\uadf8\ub9bc (b)\ub294 CoCoMix \ubaa8\ub378\uc758 \uc131\ub2a5\uc744 \ud3c9\uac00\ud558\uae30 \uc704\ud574 \uac1c\ub150 \uc608\uce21\uacfc \uc740\ub2c9 \uc0c1\ud0dc \uc9c1\uc811 \uc608\uce21\uc744 \ube44\uad50\ud55c \uacb0\uacfc\ub97c \ubcf4\uc5ec\uc90d\ub2c8\ub2e4. CoCoMix\ub294 \uc0ac\uc804 \ud6c8\ub828\ub41c SAE(Sparse Autoencoder)\ub97c \uc0ac\uc6a9\ud558\uc5ec \uc740\ub2c9 \uc0c1\ud0dc\uc5d0\uc11c \uac1c\ub150\uc744 \ucd94\ucd9c\ud558\uace0, \uc774\ub97c \uc0ac\uc6a9\ud558\uc5ec \ub2e4\uc74c \ud1a0\ud070\uc744 \uc608\uce21\ud569\ub2c8\ub2e4. \ubc18\uba74\uc5d0 \uc740\ub2c9 \uc0c1\ud0dc \uc9c1\uc811 \uc608\uce21\uc740 SAE\ub97c \uc0ac\uc6a9\ud558\uc9c0 \uc54a\uace0 \uc740\ub2c9 \uc0c1\ud0dc\ub97c \uc9c1\uc811 \uc608\uce21\ud558\uc5ec \ub2e4\uc74c \ud1a0\ud070\uc744 \uc608\uce21\ud569\ub2c8\ub2e4. \uc774 \uadf8\ub9bc\uc740 \uc740\ub2c9 \uc0c1\ud0dc \uc9c1\uc811 \uc608\uce21 \ubc29\uc2dd\uc774 CoCoMix\ubcf4\ub2e4 \uc131\ub2a5\uc774 \ub5a8\uc5b4\uc9c4\ub2e4\ub294 \uac83\uc744 \ubcf4\uc5ec\uc8fc\uba70, SAE\ub97c \uc0ac\uc6a9\ud558\uc5ec \uac1c\ub150\uc744 \ucd94\ucd9c\ud558\ub294 \uac83\uc774 \ubaa8\ub378 \uc131\ub2a5 \ud5a5\uc0c1\uc5d0 \uc911\uc694\ud568\uc744 \uc2dc\uc0ac\ud569\ub2c8\ub2e4.", "section": "3.3 CoCoMix\uc758 \ud6a8\uacfc \ubd84\uc11d"}, {"figure_path": "https://arxiv.org/html/2502.08524/x22.png", "caption": "(c) Compression layer\u2019s weight analysis", "description": "\uadf8\ub9bc 6(c)\ub294 CoCoMix \ubaa8\ub378\uc758 \uc555\ucd95 \uacc4\uce35(compression layer) \uac00\uc911\uce58 \ubd84\uc11d \uacb0\uacfc\ub97c \ubcf4\uc5ec\uc90d\ub2c8\ub2e4. CoCoMix\ub294 \uc5ec\ub7ec \uac1c\uc758 \uc608\uce21\ub41c \uac1c\ub150\ub4e4\uc744 \uc555\ucd95\ub41c \uc5f0\uc18d\uc801\uc778 \uac1c\ub150 \ubca1\ud130\ub85c \ubcc0\ud658\ud558\ub294\ub370, \uc774\ub54c \uc0ac\uc6a9\ub418\ub294 \uc555\ucd95 \uacc4\uce35\uc758 \uac00\uc911\uce58\ub97c \ubd84\uc11d\ud558\uc5ec \uac01 \uac1c\ub150\uc758 \uc911\uc694\ub3c4\ub97c \uc2dc\uac01\ud654\ud55c \uac83\uc785\ub2c8\ub2e4. \uac00\uc911\uce58\uc758 \ud06c\uae30\uac00 \ud074\uc218\ub85d \ud574\ub2f9 \uac1c\ub150\uc774 \ucd5c\uc885\uc801\uc778 \ub2e4\uc74c \ud1a0\ud070 \uc608\uce21\uc5d0 \ub354 \ud070 \uc601\ud5a5\uc744 \ubbf8\uce58\ub294 \uac83\uc744 \uc758\ubbf8\ud569\ub2c8\ub2e4. \uadf8\ub9bc\uc5d0\uc11c\ub294 \uac1c\ub150 \uac00\uc911\uce58\uc758 \ud06c\uae30\ub97c 12-norm\uc73c\ub85c \uacc4\uc0b0\ud558\uc5ec \ud45c\uc2dc\ud558\uace0 \uc788\uc73c\uba70, \uc77c\ubd80 \uac1c\ub150\ub4e4\uc758 \uac00\uc911\uce58\uac00 \uac70\uc758 0\uc5d0 \uac00\uae4c\uc6b4 \uac83\uc744 \ud655\uc778\ud560 \uc218 \uc788\uc2b5\ub2c8\ub2e4. \uc774\ub294 CoCoMix\uac00 \ucd5c\uc885 \uc608\uce21\uc5d0 \ubd88\ud544\uc694\ud55c \uac1c\ub150\ub4e4\uc744 \ud6a8\uacfc\uc801\uc73c\ub85c \ubb34\uc2dc\ud558\uace0 \uc911\uc694\ud55c \uac1c\ub150\ub4e4\ub9cc\uc744 \uc120\ud0dd\uc801\uc73c\ub85c \uc0ac\uc6a9\ud55c\ub2e4\ub294 \uac83\uc744 \uc2dc\uc0ac\ud569\ub2c8\ub2e4. \ud2b9\ud788, \uc791\uc740 \ubaa8\ub378\uc5d0\uc11c \ucd94\ucd9c\ud55c \uac1c\ub150\uc744 \ud070 \ubaa8\ub378\uc5d0 \uc801\uc6a9\ud558\ub294 \uc57d-\uac15(weak-to-strong) \uc9c0\ub3c4 \ud559\uc2b5 \uc2dc\ub098\ub9ac\uc624\uc5d0\uc11c \uc774\ub7ec\ud55c \ud2b9\uc9d5\uc774 \ud6a8\uacfc\uc801\uc73c\ub85c \uc791\ub3d9\ud558\uc5ec \uc131\ub2a5 \ud5a5\uc0c1\uc5d0 \uae30\uc5ec\ud560 \uc218 \uc788\ub2e4\uace0 \ub17c\ubb38\uc5d0\uc11c\ub294 \uc8fc\uc7a5\ud569\ub2c8\ub2e4.", "section": "3.3 CoCoMix\uc758 \ud6a8\uacfc \ubd84\uc11d"}, {"figure_path": "https://arxiv.org/html/2502.08524/x23.png", "caption": "(d) Component analysis", "description": "\uadf8\ub9bc (d)\ub294 CoCoMix\uc758 \ud6a8\uacfc\ub97c \ubd84\uc11d\ud558\uae30 \uc704\ud574 \uac1c\ubcc4 \uad6c\uc131 \uc694\uc18c(\uad6c\uc131 \uc694\uc18c \ubd84\uc11d)\uc758 \uae30\uc5ec\ub3c4\ub97c \ubcf4\uc5ec\uc90d\ub2c8\ub2e4.  \uad6c\uccb4\uc801\uc73c\ub85c, \uac1c\ub150 \uc608\uce21(Equation 2)\uacfc \uac1c\ub150 \uc0bd\uc785(Equation 4)\uc758 \ub450 \uac00\uc9c0 \uc8fc\uc694 \uad6c\uc131 \uc694\uc18c\uac00 \uc131\ub2a5 \ud5a5\uc0c1\uc5d0 \uc5bc\ub9c8\ub098 \uc911\uc694\ud55c\uc9c0 \ubcf4\uc5ec\uc90d\ub2c8\ub2e4.  \uac1c\ub150 \uc608\uce21 \uc190\uc2e4\ub9cc \uc801\uc6a9\ud558\uba74 \uc131\ub2a5\uc774 \ub2e4\uc18c \ud5a5\uc0c1\ub418\uc9c0\ub9cc, \uac1c\ub150 \uc0bd\uc785\uc744 \ud568\uaed8 \uc801\uc6a9\ud558\uba74 \uc131\ub2a5\uc774 \ub354 \ud06c\uac8c \ud5a5\uc0c1\ub418\ub294 \uac83\uc744 \ud655\uc778\ud560 \uc218 \uc788\uc2b5\ub2c8\ub2e4.  \uc774\ub97c \ud1b5\ud574 \uac1c\ub150 \uc608\uce21\uacfc \uac1c\ub150 \uc0bd\uc785\uc774 \ubaa8\ub450 CoCoMix\uc758 \uc131\ub2a5 \ud5a5\uc0c1\uc5d0 \uc911\uc694\ud55c \uc5ed\ud560\uc744 \ud55c\ub2e4\ub294 \uac83\uc744 \uc54c \uc218 \uc788\uc2b5\ub2c8\ub2e4.", "section": "3.3 CoCoMix\uc758 \ud6a8\uacfc \ubd84\uc11d"}, {"figure_path": "https://arxiv.org/html/2502.08524/x24.png", "caption": "(e) Design choice for concept condition", "description": "\uadf8\ub9bc (e)\ub294 CoCoMix \ubaa8\ub378\uc758 \ud575\uc2ec \uad6c\uc131 \uc694\uc18c \uc911 \ud558\ub098\uc778 \uc9c0\uc18d\uc801\uc778 \uac1c\ub150(continuous concept)\uc744 \ubaa8\ub378\uc758 \uc740\ub2c9 \uc0c1\ud0dc(hidden state)\uc5d0 \ud1b5\ud569\ud558\ub294 \ubc29\ubc95\uc5d0 \ub300\ud55c \ub514\uc790\uc778 \uc120\ud0dd\uc9c0\ub97c \ubcf4\uc5ec\uc90d\ub2c8\ub2e4.  \ub450 \uac00\uc9c0 \ubc29\ubc95, \uc989 \uac1c\ub150 \ubca1\ud130\ub97c \uae30\uc874 \ud1a0\ud070 \uc784\ubca0\ub529\uc5d0 \ucd94\uac00\ud558\ub294 '\ucd94\uac00(Adding)' \ubc29\uc2dd\uacfc \ud1a0\ud070 \uc784\ubca0\ub529\uacfc \uac1c\ub150 \ubca1\ud130\ub97c \ubc88\uac08\uc544 \ubc30\uce58\ud558\ub294 '\ud63c\ud569(Mixing/Interleaving)' \ubc29\uc2dd\uc744 \ube44\uad50 \ubd84\uc11d\ud569\ub2c8\ub2e4.  \uadf8\ub9bc\uc740 \uac01 \ubc29\ubc95\uc744 \uc0ac\uc6a9\ud588\uc744 \ub54c\uc758 \uac80\uc99d \ud37c\ud50c\ub809\uc11c\ud2f0(validation perplexity) \ubcc0\ud654\ub97c \ubcf4\uc5ec\uc8fc\uc5b4, \uc5b4\ub5a4 \ubc29\uc2dd\uc774 \ubaa8\ub378 \uc131\ub2a5 \ud5a5\uc0c1\uc5d0 \ub354 \ud6a8\uacfc\uc801\uc778\uc9c0\ub97c \uc2dc\uac01\uc801\uc73c\ub85c \uc81c\uc2dc\ud569\ub2c8\ub2e4.  \uacb0\uacfc\uc801\uc73c\ub85c \ud63c\ud569 \ubc29\uc2dd\uc774 \ucd94\uac00 \ubc29\uc2dd\ubcf4\ub2e4 \uc131\ub2a5\uc774 \uc6b0\uc218\ud568\uc744 \ud655\uc778\ud560 \uc218 \uc788\uc2b5\ub2c8\ub2e4.", "section": "2.2 Continuous Concept Mixing"}, {"figure_path": "https://arxiv.org/html/2502.08524/x25.png", "caption": "(f) Comparison with Pause Token", "description": "\uadf8\ub9bc (f)\ub294 pause token\uc744 \uc0ac\uc6a9\ud55c \ubc29\ubc95\uacfc CoCoMix\uc758 \uc131\ub2a5\uc744 \ube44\uad50\ud55c \uacb0\uacfc\ub97c \ubcf4\uc5ec\uc90d\ub2c8\ub2e4. pause token\uc740 \ubaa8\ub378\uc774 \ub2e4\uc74c \ud1a0\ud070\uc744 \uc608\uce21\ud558\uae30 \uc804\uc5d0 \uc77c\uc2dc \uc815\uc9c0\ud558\uc5ec \uc0dd\uac01\ud560 \uc218 \uc788\ub3c4\ub85d \ud558\ub294 \ucd94\uac00\uc801\uc778 \ud559\uc2b5 \uac00\ub2a5\ud55c \ud1a0\ud070\uc785\ub2c8\ub2e4. \uc774 \uadf8\ub9bc\uc740 pause token\uc744 \uc0ac\uc6a9\ud55c \ubc29\ubc95\uacfc pause token\uc5d0 \uc9c0\uc2dd \uc99d\ub958(KD)\ub97c \uc801\uc6a9\ud55c \ubc29\ubc95, \uadf8\ub9ac\uace0 CoCoMix\uc758 \uac80\uc99d perplexity\ub97c \ube44\uad50\ud558\uc5ec CoCoMix\uac00 \ub2e4\ub978 \ubc29\ubc95\ub4e4\ubcf4\ub2e4 \uc6b0\uc218\ud55c \uc131\ub2a5\uc744 \ubcf4\uc784\uc744 \uc2dc\uac01\uc801\uc73c\ub85c \ubcf4\uc5ec\uc90d\ub2c8\ub2e4.", "section": "3.3 CoCoMix\uc758 \ud6a8\uacfc \ubd84\uc11d"}, {"figure_path": "https://arxiv.org/html/2502.08524/x26.png", "caption": "Figure 6: \nAnalysis of CoCoMix: (a) Effectiveness of the attribution score for selecting concepts. (b) Comparison between concept prediction and direct hidden state prediction (i.e., predicting the hidden state with continuous loss rather than discretizing the hidden state with SAE). (c) The sparsity in the compression weight. (d) Component analysis by analyzing the contribution of concept prediction and mixing. (e) Design choices for concept conditioning by comparing adding the concept vector to the original hidden state and mixing (interleaving the concept vector with token hidden representation). (f) Comparison between CoCoMix and the Pause token (i.e., adding learnable tokens). We use a 69M transformer and train on 20B tokens from the OpenWebText dataset.", "description": "\uadf8\ub9bc 6\uc740 CoCoMix\uc758 \ud6a8\uacfc\ub97c \ubd84\uc11d\ud55c \uadf8\ub9bc\uc785\ub2c8\ub2e4. (a)\uc5d0\uc11c\ub294 \uac1c\ub150 \uc120\ud0dd\uc5d0 \ub300\ud55c \uae30\uc5ec\ub3c4 \uc810\uc218\uc758 \ud6a8\uacfc\ub97c \ubcf4\uc5ec\uc90d\ub2c8\ub2e4. (b)\uc5d0\uc11c\ub294 \uac1c\ub150 \uc608\uce21\uacfc \uc9c1\uc811\uc801\uc778 \uc740\ub2c9 \uc0c1\ud0dc \uc608\uce21(SAE\ub97c \uc0ac\uc6a9\ud558\uc5ec \uc740\ub2c9 \uc0c1\ud0dc\ub97c \uc774\uc0b0\ud654\ud558\ub294 \ub300\uc2e0 \uc5f0\uc18d \uc190\uc2e4\uc744 \uc0ac\uc6a9\ud558\uc5ec \uc740\ub2c9 \uc0c1\ud0dc\ub97c \uc608\uce21) \uac04\uc758 \ube44\uad50\ub97c \ubcf4\uc5ec\uc90d\ub2c8\ub2e4. (c)\ub294 \uc555\ucd95 \uac00\uc911\uce58\uc758 \uc2a4\ud30c\uc2a4\uc131\uc744 \ubcf4\uc5ec\uc90d\ub2c8\ub2e4. (d)\ub294 \uac1c\ub150 \uc608\uce21\uacfc \ud63c\ud569\uc758 \uae30\uc5ec\ub3c4\ub97c \ubd84\uc11d\ud558\uc5ec \uad6c\uc131 \uc694\uc18c \ubd84\uc11d\uc744 \uc218\ud589\ud569\ub2c8\ub2e4. (e)\ub294 \uc6d0\ub798 \uc740\ub2c9 \uc0c1\ud0dc\uc5d0 \uac1c\ub150 \ubca1\ud130\ub97c \ucd94\uac00\ud558\ub294 \uac83\uacfc \ud1a0\ud070 \uc740\ub2c9 \ud45c\ud604\uacfc \uac1c\ub150 \ubca1\ud130\ub97c \uc11e\ub294 \uac83(\ud1a0\ud070 \uc740\ub2c9 \ud45c\ud604\uacfc \uac1c\ub150 \ubca1\ud130\ub97c \uc11e\uc74c)\uc744 \ube44\uad50\ud558\uc5ec \uac1c\ub150 \uc870\uac74\ud654\uc5d0 \ub300\ud55c \uc124\uacc4 \uc120\ud0dd\uc744 \ubcf4\uc5ec\uc90d\ub2c8\ub2e4. (f)\ub294 CoCoMix\uc640 Pause \ud1a0\ud070(\uc989, \ud559\uc2b5 \uac00\ub2a5\ud55c \ud1a0\ud070 \ucd94\uac00) \uac04\uc758 \ube44\uad50\ub97c \ubcf4\uc5ec\uc90d\ub2c8\ub2e4. 69M \ubcc0\ud658\uae30\uc640 OpenWebText \ub370\uc774\ud130\uc14b\uc758 20B \ud1a0\ud070\uc744 \uc0ac\uc6a9\ud588\uc2b5\ub2c8\ub2e4.", "section": "3 Experiments"}, {"figure_path": "https://arxiv.org/html/2502.08524/x27.png", "caption": "(a) OpenWebText, PPL (\u2193\u2193\\downarrow\u2193)", "description": "\uadf8\ub9bc 2\ub294 CoCoMix\uc640 \uae30\uc874\uc758 \ub2e4\uc74c \ud1a0\ud070 \uc608\uce21(NTP) \ubc29\ubc95\uc758 \uc131\ub2a5\uc744 \ub2e4\uc591\ud55c \ud6c8\ub828 \ub2e8\uacc4\uc5d0\uc11c \ube44\uad50\ud55c \uac83\uc785\ub2c8\ub2e4. (a)\ub294 OpenWebText \ub370\uc774\ud130\uc14b\uc744 \uc0ac\uc6a9\ud55c \uac80\uc99d \ud37c\ud50c\ub809\uc11c\ud2f0\ub97c \ubcf4\uc5ec\uc90d\ub2c8\ub2e4. CoCoMix\ub294 NTP\ubcf4\ub2e4 \ub0ae\uc740 \ud37c\ud50c\ub809\uc11c\ud2f0\ub97c \ubcf4\uc774\uba70, \ud6c8\ub828 \ud1a0\ud070 \uc218\uac00 \uc99d\uac00\ud568\uc5d0 \ub530\ub77c \uc131\ub2a5 \ud5a5\uc0c1\uc774 \ub354\uc6b1 \ub450\ub4dc\ub7ec\uc9d1\ub2c8\ub2e4.  \uc774\ub294 CoCoMix\uac00 \ub354 \uc801\uc740 \uc0d8\ud50c\ub85c\ub3c4 \ub192\uc740 \uc131\ub2a5\uc744 \ub2ec\uc131\ud560 \uc218 \uc788\uc74c\uc744 \uc2dc\uc0ac\ud569\ub2c8\ub2e4.", "section": "3 Experiments"}, {"figure_path": "https://arxiv.org/html/2502.08524/x28.png", "caption": "(b) LAMBADA, PPL (\u2193\u2193\\downarrow\u2193)", "description": "\uadf8\ub9bc (b)\ub294 LAMBADA \ub370\uc774\ud130\uc14b\uc5d0 \ub300\ud55c \ud37c\ud50c\ub809\uc11c\ud2f0(perplexity)\ub97c \ubcf4\uc5ec\uc90d\ub2c8\ub2e4.  \ud37c\ud50c\ub809\uc11c\ud2f0\ub294 \uc5b8\uc5b4 \ubaa8\ub378\uc774 \ud14d\uc2a4\ud2b8\ub97c \uc5bc\ub9c8\ub098 \uc798 \uc0dd\uc131\ud558\ub294\uc9c0 \uce21\uc815\ud558\ub294 \uc9c0\ud45c\ub85c, \uac12\uc774 \ub0ae\uc744\uc218\ub85d \uc131\ub2a5\uc774 \uc88b\uc74c\uc744 \uc758\ubbf8\ud569\ub2c8\ub2e4.  \uc774 \uadf8\ub9bc\uc740 \ub2e4\uc591\ud55c \ud6c8\ub828 \ud1a0\ud070 \uc218\uc5d0 \ub530\ub978 CoCoMix(ours)\uc640 NTP \ubaa8\ub378\uc758 \ud37c\ud50c\ub809\uc11c\ud2f0\ub97c \ube44\uad50\ud558\uc5ec CoCoMix\uac00 \ub354 \ub098\uc740 \uc131\ub2a5\uc744 \ubcf4\uc784\uc744 \uc2dc\uac01\uc801\uc73c\ub85c \ub098\ud0c0\ub0c5\ub2c8\ub2e4.  \uc138\ub85c\ucd95\uc740 \ud37c\ud50c\ub809\uc11c\ud2f0 \uac12\uc774\uace0, \uac00\ub85c\ucd95\uc740 \ud6c8\ub828\uc5d0 \uc0ac\uc6a9\ub41c \ud1a0\ud070 \uc218 (\ub2e8\uc704: B, 1B = 10\uc5b5) \uc785\ub2c8\ub2e4.", "section": "3 Experiments"}, {"figure_path": "https://arxiv.org/html/2502.08524/x29.png", "caption": "(c) WikiText-103, PPL (\u2193\u2193\\downarrow\u2193)", "description": "\uadf8\ub9bc (c)\ub294 WikiText-103 \ub370\uc774\ud130\uc14b\uc5d0 \ub300\ud55c perplexity(PPL) \ubcc0\ud654\ub97c \ubcf4\uc5ec\uc90d\ub2c8\ub2e4.  Perplexity\ub294 \uc5b8\uc5b4 \ubaa8\ub378\uc758 \uc131\ub2a5\uc744 \ud3c9\uac00\ud558\ub294 \uc9c0\ud45c\ub85c, \uac12\uc774 \ub0ae\uc744\uc218\ub85d \ubaa8\ub378\uc758 \uc131\ub2a5\uc774 \uc88b\uc74c\uc744 \uc758\ubbf8\ud569\ub2c8\ub2e4.  \uc774 \uadf8\ub9bc\uc740 \uc5ec\ub7ec\uac00\uc9c0 \ub2e4\ub978 \ud559\uc2b5 \ubc29\ubc95 (\uc608: NTP, CoCoMix \ub4f1)\uc744 \uc0ac\uc6a9\ud588\uc744 \ub54c, WikiText-103 \ub370\uc774\ud130\uc14b\uc5d0 \ub300\ud55c perplexity\uac00 \ud559\uc2b5 \ud1a0\ud070 \uc218\uc5d0 \ub530\ub77c \uc5b4\ub5bb\uac8c \ubcc0\ud654\ud558\ub294\uc9c0\ub97c \ub098\ud0c0\ub0c5\ub2c8\ub2e4.  \uc989,  \ub2e4\uc591\ud55c \ud559\uc2b5 \ubc29\ubc95\uc744 \uc801\uc6a9\ud588\uc744 \ub54c WikiText-103 \ub370\uc774\ud130\uc14b\uc5d0\uc11c\uc758 \uc5b8\uc5b4 \ubaa8\ub378 \uc131\ub2a5 \ubcc0\ud654\ub97c perplexity\ub97c \ud1b5\ud574 \uc2dc\uac01\uc801\uc73c\ub85c \ubcf4\uc5ec\uc8fc\ub294 \uadf8\ub798\ud504\uc785\ub2c8\ub2e4.", "section": "3 Experiments"}, {"figure_path": "https://arxiv.org/html/2502.08524/x30.png", "caption": "(d) HellaSwag, Acc-n (\u2191\u2191\\uparrow\u2191)", "description": "\uadf8\ub9bc (d)\ub294 HellaSwag \ub370\uc774\ud130\uc14b\uc5d0 \ub300\ud55c \uc815\ud655\ub3c4(Acc-n)\ub97c \ubcf4\uc5ec\uc90d\ub2c8\ub2e4.  HellaSwag\ub294 \uc0c1\uc2dd\uc801 \ucd94\ub860 \ub2a5\ub825\uc744 \ud3c9\uac00\ud558\ub294 \ubca4\uce58\ub9c8\ud06c \ub370\uc774\ud130\uc14b\uc774\uba70, Acc-n\uc740 \uc815\ub2f5\ub960\uc744 \ub098\ud0c0\ub0c5\ub2c8\ub2e4.  \uc774 \uadf8\ub9bc\uc740 CoCoMix \ubaa8\ub378\uc774 \uae30\uc874\uc758 \ub2e4\uc74c \ud1a0\ud070 \uc608\uce21(NTP) \ubc29\ubc95\uc5d0 \ube44\ud574 HellaSwag \ub370\uc774\ud130\uc14b\uc5d0\uc11c \uc5bc\ub9c8\ub098 \uc131\ub2a5\uc774 \ud5a5\uc0c1\ub418\uc5c8\ub294\uc9c0 \ubcf4\uc5ec\uc8fc\ub294 \uacb0\uacfc\uc785\ub2c8\ub2e4.  \ud654\uc0b4\ud45c\ub294 CoCoMix \ubaa8\ub378\uc758 \uc131\ub2a5 \ud5a5\uc0c1\uc744 \uc2dc\uac01\uc801\uc73c\ub85c \uac15\uc870\ud569\ub2c8\ub2e4.  \uc989,  CoCoMix\ub97c \uc0ac\uc6a9\ud558\uba74 \uc0c1\uc2dd \ucd94\ub860 \uc791\uc5c5\uc5d0\uc11c \uc131\ub2a5\uc774 \ud06c\uac8c \ud5a5\uc0c1\ub428\uc744 \ubcf4\uc5ec\uc90d\ub2c8\ub2e4.", "section": "3 Experiments"}, {"figure_path": "https://arxiv.org/html/2502.08524/x31.png", "caption": "(e) PIQA, Acc (\u2191\u2191\\uparrow\u2191)", "description": "\uadf8\ub9bc (e)\ub294 PIQA(Physical Interaction QA) \ub370\uc774\ud130\uc14b\uc5d0 \ub300\ud55c CoCoMix \ubaa8\ub378\uc758 \uc815\ud655\ub3c4(Accuracy)\ub97c \ubcf4\uc5ec\uc90d\ub2c8\ub2e4.  PIQA\ub294 \ubb3c\ub9ac\uc801 \uc0c1\uc2dd \ucd94\ub860 \ub2a5\ub825\uc744 \ud3c9\uac00\ud558\ub294 \uc9c8\ubb38\uc751\ub2f5 \ub370\uc774\ud130\uc14b\uc774\uba70,  \uc774 \uadf8\ub9bc\uc740 CoCoMix \ubaa8\ub378\uc774 PIQA\uc5d0\uc11c \uc5bc\ub9c8\ub098 \uc88b\uc740 \uc131\ub2a5\uc744 \ubcf4\uc774\ub294\uc9c0, \ud2b9\ud788 \ub2e4\ub978 \ubaa8\ub378\ub4e4\uacfc \ube44\uad50\ud588\uc744 \ub54c \uc5bc\ub9c8\ub098 \ud5a5\uc0c1\ub41c \uc131\ub2a5\uc744 \ubcf4\uc774\ub294\uc9c0\ub97c \ub098\ud0c0\ub0c5\ub2c8\ub2e4.  'Acc (\u2191\u2191)'\uc740 \uc815\ud655\ub3c4\uac00 \uc0c1\ub2f9\ud788 \ud5a5\uc0c1\ub418\uc5c8\uc74c\uc744 \uc758\ubbf8\ud569\ub2c8\ub2e4.  \uc815\ud655\ub3c4 \uc218\uce58 \uc790\uccb4\ub294 \ud45c\ub098 \ubcf8\ubb38\uc5d0 \uc81c\uc2dc\ub418\uc5b4 \uc788\uc744 \uac83\uc73c\ub85c \uc608\uc0c1\ub429\ub2c8\ub2e4.", "section": "3 Experiments"}, {"figure_path": "https://arxiv.org/html/2502.08524/x32.png", "caption": "(f) SIQA, Acc (\u2191\u2191\\uparrow\u2191)", "description": "\uadf8\ub9bc (f)\ub294 SIQA(Social Interaction QA) \ub370\uc774\ud130\uc14b\uc5d0 \ub300\ud55c CoCoMix \ubaa8\ub378\uc758 \uc815\ud655\ub3c4\ub97c \ubcf4\uc5ec\uc90d\ub2c8\ub2e4.  'Acc (\u2191\u2191)'\ub294 \uc815\ud655\ub3c4\uac00 \uc0c1\ub2f9\ud788 \ud5a5\uc0c1\ub418\uc5c8\uc74c\uc744 \uc758\ubbf8\ud569\ub2c8\ub2e4. \uc774\ub294 CoCoMix \ubaa8\ub378\uc774 \uc0ac\ud68c\uc801 \uc0c1\ud638\uc791\uc6a9\uc5d0 \ub300\ud55c \uc774\ud574\ub97c \ub192\uc774\ub294 \ub370 \ud6a8\uacfc\uc801\uc784\uc744 \uc2dc\uc0ac\ud569\ub2c8\ub2e4. \uadf8\ub9bc\uc740 CoCoMix\uac00 \ub2e4\uc591\ud55c \ubca4\uce58\ub9c8\ud06c \ub370\uc774\ud130\uc14b\uc5d0\uc11c \uc77c\uad00\ub418\uac8c \uc131\ub2a5 \ud5a5\uc0c1\uc744 \ubcf4\uc784\uc744 \ubcf4\uc5ec\uc8fc\ub294 \uc2e4\ud5d8 \uacb0\uacfc \uc911 \ud558\ub098\uc758 \uc608\uc2dc\uc785\ub2c8\ub2e4.", "section": "3 Experiments"}, {"figure_path": "https://arxiv.org/html/2502.08524/x33.png", "caption": "(g) Arc-Easy, Acc (\u2191\u2191\\uparrow\u2191)", "description": "\uadf8\ub9bc (g)\ub294 Arc-Easy \ub370\uc774\ud130\uc14b\uc5d0 \ub300\ud55c CoCoMix \ubaa8\ub378\uc758 \uc815\ud655\ub3c4(Accuracy)\ub97c \ubcf4\uc5ec\uc90d\ub2c8\ub2e4.  'Acc (\u2191\u2191)'\ub294 \uc815\ud655\ub3c4\uac00 \uc0c1\ub2f9\ud788 \ud5a5\uc0c1\ub418\uc5c8\uc74c\uc744 \uc758\ubbf8\ud569\ub2c8\ub2e4. \uc774 \uadf8\ub9bc\uc740 \ub2e4\uc591\ud55c \ubaa8\ub378 \ud06c\uae30(69M, 386M, 1.38B \ud30c\ub77c\ubbf8\ud130)\uc5d0 \uac78\uccd0 CoCoMix\uac00 \uae30\ubcf8\uc801\uc778 \ub2e4\uc74c \ud1a0\ud070 \uc608\uce21(NTP) \ubc29\ubc95\ubcf4\ub2e4 \uc131\ub2a5\uc774 \uc6b0\uc218\ud568\uc744 \ubcf4\uc5ec\uc8fc\ub294 \uc2e4\ud5d8 \uacb0\uacfc \uc911 \ud558\ub098\uc785\ub2c8\ub2e4.  \ud2b9\ud788 Arc-Easy\ub294 \ucd94\ub860 \ub2a5\ub825\uc744 \ud3c9\uac00\ud558\ub294 \ub370\uc774\ud130\uc14b\uc774\uae30 \ub54c\ubb38\uc5d0, CoCoMix\uc758 \ud5a5\uc0c1\ub41c \uc131\ub2a5\uc740 \uac1c\uc120\ub41c \ucd94\ub860 \ub2a5\ub825\uc744 \uc2dc\uc0ac\ud569\ub2c8\ub2e4.", "section": "3 Experiments"}, {"figure_path": "https://arxiv.org/html/2502.08524/x34.png", "caption": "(h) WinoGrande, Acc (\u2191\u2191\\uparrow\u2191)", "description": "\uadf8\ub9bc 2\ub294 \ub2e4\uc591\ud55c \ud06c\uae30\uc758 \uc0ac\uc804 \ud559\uc2b5\ub41c \uc5b8\uc5b4 \ubaa8\ub378(69M, 386M, 1.38B \ub9e4\uac1c\ubcc0\uc218)\uc5d0 \ub300\ud574 CoCoMix\uc640 NTP\uc758 \uc131\ub2a5\uc744 \ube44\uad50\ud55c \uac83\uc785\ub2c8\ub2e4.  OpenWebText \uac80\uc99d \uc9d1\ud569\uc758 \ud37c\ud50c\ub809\uc11c\ud2f0\uc640 LAMBADA, WikiText-103, HellaSwag, PIQA, SIQA, Arc-Easy \ubc0f WinoGrande\uc640 \uac19\uc740 \ub2e4\uc6b4\uc2a4\ud2b8\ub9bc \uc791\uc5c5\uc758 \ud3c9\uade0 \ud37c\ud50c\ub809\uc11c\ud2f0 \ubc0f \uc815\ud655\ub3c4\ub97c \ud3c9\uac00\ud588\uc2b5\ub2c8\ub2e4.  (h)\ub294 WinoGrande \ub370\uc774\ud130\uc14b\uc5d0\uc11c\uc758 \uc815\ud655\ub3c4\ub97c \ub098\ud0c0\ub0b4\uba70, CoCoMix\uac00 NTP\ubcf4\ub2e4 \uc131\ub2a5\uc774 \ud6e8\uc52c \ub6f0\uc5b4\ub0a8\uc744 \ubcf4\uc5ec\uc90d\ub2c8\ub2e4.  \uc774 \uadf8\ub9bc\uc740 CoCoMix\uac00 \ub2e4\uc591\ud55c \ubaa8\ub378 \ud06c\uae30\uc5d0\uc11c \uc77c\uad00\ub418\uac8c \uc6b0\uc218\ud55c \uc131\ub2a5\uc744 \ubc1c\ud718\ud558\uba70, \ud2b9\ud788 WinoGrande\uc640 \uac19\uc740 \uc5b4\ub824\uc6b4 \ucd94\ub860 \uc791\uc5c5\uc5d0\uc11c \uadf8 \ud6a8\uacfc\uac00 \ub450\ub4dc\ub7ec\uc9d0\uc744 \uc2dc\uac01\uc801\uc73c\ub85c \ubcf4\uc5ec\uc90d\ub2c8\ub2e4.", "section": "3 Experiments"}, {"figure_path": "https://arxiv.org/html/2502.08524/x35.png", "caption": "Figure 7: \nCoCoMix vs. NTP performance at different training checkpoints on 69M parameter model. Each model is trained on the 200B tokens sampled from the OpenWebText dataset. The plot shows the result of (a) OpenWebText, (b) LAMBADA, (c) WikiText-103, (d) HellaSwag, (e) PIQA, (f) SIQA, (g) Arc-Easy, and (h) WinoGrande datasets. We use the concepts extracted from a 124M-sized model for training CoCoMix.", "description": "\uadf8\ub9bc 7\uc740 69M \ud30c\ub77c\ubbf8\ud130 \ubaa8\ub378\uc5d0 \ub300\ud55c CoCoMix\uc640 NTP\uc758 \uc131\ub2a5\uc744 \ub2e4\uc591\ud55c \ud6c8\ub828 \uc2dc\uc810\uc5d0\uc11c \ube44\uad50\ud55c \uac83\uc785\ub2c8\ub2e4. \uac01 \ubaa8\ub378\uc740 OpenWebText \ub370\uc774\ud130\uc14b\uc5d0\uc11c \uc0d8\ud50c\ub9c1\ub41c 200B \ud1a0\ud070\uc73c\ub85c \ud6c8\ub828\ub418\uc5c8\uc2b5\ub2c8\ub2e4. \uadf8\ub798\ud504\ub294 (a) OpenWebText, (b) LAMBADA, (c) WikiText-103, (d) HellaSwag, (e) PIQA, (f) SIQA, (g) Arc-Easy, (h) WinoGrande \ub370\uc774\ud130\uc14b\uc5d0 \ub300\ud55c \uacb0\uacfc\ub97c \ubcf4\uc5ec\uc90d\ub2c8\ub2e4. CoCoMix \ud6c8\ub828\uc5d0\ub294 124M \ud06c\uae30\uc758 \ubaa8\ub378\uc5d0\uc11c \ucd94\ucd9c\ud55c \uac1c\ub150\uc774 \uc0ac\uc6a9\ub418\uc5c8\uc2b5\ub2c8\ub2e4.  \uc774 \uadf8\ub9bc\uc740 \ub2e4\uc591\ud55c \uc5b8\uc5b4 \ubaa8\ub378\ub9c1 \ubca4\uce58\ub9c8\ud06c\uc5d0\uc11c CoCoMix\uac00  \ub2e4\ub978 \ubc29\ubc95\ub860\ub4e4\uc5d0 \ube44\ud574 \uc131\ub2a5\uc774 \uc5bc\ub9c8\ub098 \ub6f0\uc5b4\ub09c\uc9c0 \ubcf4\uc5ec\uc8fc\ub294 \uc99d\uac70\ub85c \uc81c\uc2dc\ub429\ub2c8\ub2e4. \ud2b9\ud788,  \ub2e4\ub978 \ubaa8\ub378 \ud06c\uae30 (69M, 386M, 1.38B)\uc5d0\uc11c\ub3c4 \uc77c\uad00\ub41c \uc131\ub2a5 \ud5a5\uc0c1\uc744 \ubcf4\uc5ec\uc90d\ub2c8\ub2e4.", "section": "3 Experiments"}, {"figure_path": "https://arxiv.org/html/2502.08524/x36.png", "caption": "(a) OpenWebText, PPL (\u2193\u2193\\downarrow\u2193)", "description": "\uadf8\ub9bc 2(a)\ub294 OpenWebText \ub370\uc774\ud130\uc14b\uc744 \uc0ac\uc6a9\ud558\uc5ec \uc0ac\uc804 \ud6c8\ub828\ub41c 1.38B \ub9e4\uac1c\ubcc0\uc218 \ubaa8\ub378\uc758 \uac80\uc99d \ud37c\ud50c\ub809\uc11c\ud2f0(PPL)\ub97c \ubcf4\uc5ec\uc90d\ub2c8\ub2e4.  CoCoMix(\ud30c\ub780\uc0c9 \uc120)\ub294 \ud45c\uc900 \ub2e4\uc74c \ud1a0\ud070 \uc608\uce21(NTP, \uc8fc\ud669\uc0c9 \uc120)\uacfc \ube44\uad50\ud558\uc5ec \ud6c8\ub828 \ud1a0\ud070 \uc218\uac00 \uc99d\uac00\ud568\uc5d0 \ub530\ub77c \ud37c\ud50c\ub809\uc11c\ud2f0\uac00 \ub354 \ub0ae\uac8c \uc720\uc9c0\ub428\uc744 \ubcf4\uc5ec\uc90d\ub2c8\ub2e4.  \ud2b9\ud788, CoCoMix\ub294 \ud6c8\ub828 \ud1a0\ud070\uc774 21.5% \uc801\uac8c \uc0ac\uc6a9\ub418\uc5c8\uc74c\uc5d0\ub3c4 \ubd88\uad6c\ud558\uace0 NTP\uc640 \uc720\uc0ac\ud55c \uc131\ub2a5\uc744 \ubcf4\uc5ec\uc8fc\uc5b4 \uc0d8\ud50c \ud6a8\uc728\uc131\uc774 \ub192\uc74c\uc744 \uc2dc\uc0ac\ud569\ub2c8\ub2e4.", "section": "3 \uc2e4\ud5d8"}, {"figure_path": "https://arxiv.org/html/2502.08524/x37.png", "caption": "(b) LAMBADA, PPL (\u2193\u2193\\downarrow\u2193)", "description": "\uadf8\ub9bc (b)\ub294 LAMBADA \ubca4\uce58\ub9c8\ud06c\uc5d0 \ub300\ud55c \uacb0\uacfc\ub97c \ubcf4\uc5ec\uc90d\ub2c8\ub2e4. LAMBADA\ub294 \uc5b4\ub824\uc6b4 \uc5b8\uc5b4 \ucd94\ub860 \ub2a5\ub825\uc744 \uc694\uad6c\ud558\ub294 \uc9c8\ubb38\uc751\ub2f5 \ub370\uc774\ud130\uc14b\uc785\ub2c8\ub2e4.  PPL (Perplexity)\uc740 \ubaa8\ub378\uc774 \ud14d\uc2a4\ud2b8\ub97c \uc5bc\ub9c8\ub098 \uc798 \uc608\uce21\ud558\ub294\uc9c0\ub97c \ub098\ud0c0\ub0b4\ub294 \uc9c0\ud45c\ub85c, \uac12\uc774 \ub0ae\uc744\uc218\ub85d \uc131\ub2a5\uc774 \uc88b\uc74c\uc744 \uc758\ubbf8\ud569\ub2c8\ub2e4.  \uc774 \uadf8\ub9bc\uc5d0\uc11c\ub294 CoCoMix \ubaa8\ub378\uc774 \uae30\uc900 \ubaa8\ub378(NTP)\ubcf4\ub2e4 \ub0ae\uc740 PPL \uac12\uc744 \uae30\ub85d\ud558\uc5ec, LAMBADA \ub370\uc774\ud130\uc14b\uc5d0\uc11c \ub354 \ub098\uc740 \uc131\ub2a5\uc744 \ubcf4\uc600\uc74c\uc744 \uc2dc\uac01\uc801\uc73c\ub85c \ubcf4\uc5ec\uc90d\ub2c8\ub2e4.  \uc989, CoCoMix \ubaa8\ub378\uc774 \ubcf5\uc7a1\ud55c \uc5b8\uc5b4 \ucd94\ub860 \ubb38\uc81c\uc5d0 \ub300\ud574\uc11c \ub354 \uc815\ud655\ud558\uac8c \ub2f5\ubcc0\uc744 \uc608\uce21\ud560 \uc218 \uc788\uc74c\uc744 \uc758\ubbf8\ud569\ub2c8\ub2e4.", "section": "3 Experiments"}, {"figure_path": "https://arxiv.org/html/2502.08524/x38.png", "caption": "(c) WikiText-103, PPL (\u2193\u2193\\downarrow\u2193)", "description": "\uadf8\ub9bc (c)\ub294 3\uac00\uc9c0 \ud06c\uae30\uc758 \uc5b8\uc5b4 \ubaa8\ub378(69M, 386M, 1.38B \ud30c\ub77c\ubbf8\ud130)\uc744 WikiText-103 \ub370\uc774\ud130\uc14b\uc73c\ub85c \uc0ac\uc804 \ud6c8\ub828 \uc2dc\ud0a8 \uacb0\uacfc\ub97c \ubcf4\uc5ec\uc90d\ub2c8\ub2e4.  \uc138\ub85c\ucd95\uc740 \ud3c9\uade0 perplexity(\ub0ae\uc744\uc218\ub85d \uc88b\uc74c)\uc774\uace0, \uac00\ub85c\ucd95\uc740 \uc0ac\uc6a9\ub41c \ud6c8\ub828 \ud1a0\ud070 \uc218(\ub2e8\uc704: 10\uc5b5)\uc785\ub2c8\ub2e4. CoCoMix(\ud30c\ub780\uc0c9 \uc120)\uacfc \uae30\ubcf8\uc801\uc778 \ub2e4\uc74c \ud1a0\ud070 \uc608\uce21(NTP, \uc8fc\ud669\uc0c9 \uc120) \ubc29\ubc95\uc744 \ube44\uad50\ud558\uc5ec, CoCoMix\uac00 \ub2e4\uc591\ud55c \ubaa8\ub378 \ud06c\uae30\uc5d0\uc11c \uafb8\uc900\ud788 \ub354 \ub0ae\uc740 perplexity\ub97c \ub2ec\uc131\ud568\uc744 \ubcf4\uc5ec\uc90d\ub2c8\ub2e4. \uc774\ub294 CoCoMix\uac00 \ub354 \uc801\uc740 \ud6c8\ub828 \ub370\uc774\ud130\ub85c\ub3c4 \ub192\uc740 \uc131\ub2a5\uc744 \ub2ec\uc131\ud560 \uc218 \uc788\uc74c\uc744 \uc2dc\uc0ac\ud569\ub2c8\ub2e4.", "section": "3 Experiments"}, {"figure_path": "https://arxiv.org/html/2502.08524/x39.png", "caption": "(d) HellaSwag, Acc-n (\u2191\u2191\\uparrow\u2191)", "description": "\uadf8\ub9bc (d)\ub294 HellaSwag \ub370\uc774\ud130\uc14b\uc5d0\uc11c\uc758 \uc815\ud655\ub3c4(Acc-n)\ub97c \ubcf4\uc5ec\uc90d\ub2c8\ub2e4.  HellaSwag\ub294 \uc0c1\uc2dd \ucd94\ub860 \ub2a5\ub825\uc744 \ud3c9\uac00\ud558\ub294 \ubca4\uce58\ub9c8\ud06c \ub370\uc774\ud130\uc14b\uc774\uba70, Acc-n\uc740 \uc815\ub2f5\ub960\uc744 \uc758\ubbf8\ud569\ub2c8\ub2e4.  \ub450 \uac1c\uc758 \ud654\uc0b4\ud45c\ub294 CoCoMix \ubaa8\ub378\uc774 \uae30\uc874\uc758 NTP(Next Token Prediction) \ubaa8\ub378\uc5d0 \ube44\ud574 \uc0c1\ub2f9\ud788 \ub192\uc740 \uc815\ud655\ub3c4\ub97c \ub2ec\uc131\ud588\uc74c\uc744 \uc2dc\uac01\uc801\uc73c\ub85c \uac15\uc870\ud569\ub2c8\ub2e4. \uc774\ub294 CoCoMix\uac00 \uc5b8\uc5b4 \ubaa8\ub378\uc758 \uc0c1\uc2dd \ucd94\ub860 \ub2a5\ub825 \ud5a5\uc0c1\uc5d0 \ud6a8\uacfc\uc801\uc784\uc744 \ubcf4\uc5ec\uc8fc\ub294 \uacb0\uacfc\uc785\ub2c8\ub2e4.", "section": "3 Experiments"}, {"figure_path": "https://arxiv.org/html/2502.08524/x40.png", "caption": "(e) PIQA, Acc (\u2191\u2191\\uparrow\u2191)", "description": "\uadf8\ub9bc (e)\ub294 PIQA(Physical Interaction QA) \ub370\uc774\ud130\uc14b\uc5d0 \ub300\ud55c CoCoMix \ubaa8\ub378\uc758 \uc815\ud655\ub3c4(Accuracy)\ub97c \ubcf4\uc5ec\uc90d\ub2c8\ub2e4.  PIQA\ub294 \ubb3c\ub9ac\uc801 \uc0c1\uc2dd\uc5d0 \ub300\ud55c \ucd94\ub860 \ub2a5\ub825\uc744 \ud3c9\uac00\ud558\ub294 \uc9c8\ubb38\uc751\ub2f5 \ub370\uc774\ud130\uc14b\uc774\uba70, \uc774 \uadf8\ub9bc\uc740 CoCoMix \ubaa8\ub378\uc774 PIQA \uc9c8\ubb38\uc5d0 \ub300\ud574 \uc5bc\ub9c8\ub098 \uc815\ud655\ud558\uac8c \ub2f5\ubcc0\ud558\ub294\uc9c0\ub97c \ub098\ud0c0\ub0c5\ub2c8\ub2e4.  \ud654\uc0b4\ud45c \ub450 \uac1c (\u2191\u2191)\ub294 CoCoMix \ubaa8\ub378\uc758 \uc131\ub2a5\uc774 \uae30\uc900 \ubaa8\ub378(NTP)\ubcf4\ub2e4 \uc0c1\ub2f9\ud788 \ud5a5\uc0c1\ub418\uc5c8\uc74c\uc744 \uc2dc\uac01\uc801\uc73c\ub85c \uac15\uc870\ud569\ub2c8\ub2e4.", "section": "3 Experiments"}, {"figure_path": "https://arxiv.org/html/2502.08524/x41.png", "caption": "(f) SIQA, Acc (\u2191\u2191\\uparrow\u2191)", "description": "\uadf8\ub9bc (f)\ub294 SIQA(Social Interaction QA) \ub370\uc774\ud130\uc14b\uc5d0 \ub300\ud55c CoCoMix \ubaa8\ub378\uc758 \uc815\ud655\ub3c4\ub97c \ubcf4\uc5ec\uc90d\ub2c8\ub2e4.  'Acc'\ub294 \uc815\ud655\ub3c4\ub97c \ub098\ud0c0\ub0b4\uace0, \ud654\uc0b4\ud45c \ub450 \uac1c\ub294 CoCoMix \ubaa8\ub378\uc758 \uc131\ub2a5\uc774 SIQA \uc791\uc5c5\uc5d0\uc11c \uc0c1\ub2f9\ud788 \ud5a5\uc0c1\ub418\uc5c8\uc74c\uc744 \uc758\ubbf8\ud569\ub2c8\ub2e4.  \uc774 \uadf8\ub9bc\uc740 CoCoMix\uac00 \ub2e4\uc591\ud55c \uc5b8\uc5b4 \ubaa8\ub378\ub9c1 \ubca4\uce58\ub9c8\ud06c\uc5d0\uc11c \uc77c\uad00\ub418\uac8c \uc6b0\uc218\ud55c \uc131\ub2a5\uc744 \ubcf4\uc784\uc744 \ubcf4\uc5ec\uc8fc\ub294 \uc5ec\ub7ec \uadf8\ub9bc \uc911 \ud558\ub098\uc785\ub2c8\ub2e4.", "section": "3 Experiments"}, {"figure_path": "https://arxiv.org/html/2502.08524/x42.png", "caption": "(g) Arc-Easy, Acc (\u2191\u2191\\uparrow\u2191)", "description": "\uadf8\ub9bc (g)\ub294 Arc-Easy \ub370\uc774\ud130\uc14b\uc5d0 \ub300\ud55c CoCoMix \ubaa8\ub378\uc758 \uc815\ud655\ub3c4\ub97c \ubcf4\uc5ec\uc90d\ub2c8\ub2e4.  'Acc (\u2191\u2191)'\ub294 \uc815\ud655\ub3c4\uac00 \uc0c1\ub2f9\ud788 \ud5a5\uc0c1\ub418\uc5c8\uc74c\uc744 \uc758\ubbf8\ud569\ub2c8\ub2e4. \uc774 \uadf8\ub9bc\uc740 CoCoMix \ubaa8\ub378\uc774 \ub2e4\uc591\ud55c \ubca4\uce58\ub9c8\ud06c\uc5d0\uc11c \uc77c\uad00\ub418\uac8c \uc131\ub2a5 \ud5a5\uc0c1\uc744 \ubcf4\uc5ec\uc8fc\ub294 \uc5ec\ub7ec \uc2e4\ud5d8 \uacb0\uacfc \uc911 \ud558\ub098\uc785\ub2c8\ub2e4.  \ud2b9\ud788, Arc-Easy\uc640 \uac19\uc740 \ucd94\ub860 \ub2a5\ub825\uc744 \uc694\uad6c\ud558\ub294 \uacfc\uc81c\uc5d0\uc11c CoCoMix\uc758 \ud6a8\uacfc\uac00 \ub450\ub4dc\ub7ec\uc9d0\uc744 \ubcf4\uc5ec\uc90d\ub2c8\ub2e4.", "section": "3 Experiments"}, {"figure_path": "https://arxiv.org/html/2502.08524/x43.png", "caption": "(h) WinoGrande, Acc (\u2191\u2191\\uparrow\u2191)", "description": "\uadf8\ub9bc (h)\ub294 WinoGrande \ub370\uc774\ud130\uc14b\uc5d0 \ub300\ud55c CoCoMix\uc640 NTP\uc758 \uc815\ud655\ub3c4 \ube44\uad50 \uacb0\uacfc\ub97c \ubcf4\uc5ec\uc90d\ub2c8\ub2e4.  WinoGrande\ub294 \uc0c1\uc2dd \ucd94\ub860 \ub2a5\ub825\uc744 \ud3c9\uac00\ud558\ub294 \ubca4\uce58\ub9c8\ud06c\uc774\uba70, \uc774 \uadf8\ub9bc\uc5d0\uc11c\ub294 CoCoMix \ubaa8\ub378\uc774 NTP \ubaa8\ub378\uc5d0 \ube44\ud574 \uc0c1\ub2f9\ud788 \ub192\uc740 \uc815\ud655\ub3c4\ub97c \ub2ec\uc131\ud568\uc744 \uc2dc\uac01\uc801\uc73c\ub85c \ub098\ud0c0\ub0c5\ub2c8\ub2e4.  \uc815\ud655\ub3c4 \ud5a5\uc0c1\uc758 \uc815\ub3c4\ub294 \uadf8\ub798\ud504\uc758 y\ucd95 \uac12\uc744 \ud1b5\ud574 \ud655\uc778\ud560 \uc218 \uc788\uc2b5\ub2c8\ub2e4.  \uc989, CoCoMix\uac00 WinoGrande\uc640 \uac19\uc740 \ucd94\ub860 \ub2a5\ub825\uc744 \uc694\uad6c\ud558\ub294 \uacfc\uc81c\uc5d0\uc11c \ub354 \ub098\uc740 \uc131\ub2a5\uc744 \ubcf4\uc778\ub2e4\ub294 \uac83\uc744 \ubcf4\uc5ec\uc90d\ub2c8\ub2e4.", "section": "3 Experiments"}, {"figure_path": "https://arxiv.org/html/2502.08524/x44.png", "caption": "Figure 8: \nCoCoMix vs. NTP performance at different training checkpoints on 368M parameter model. Each model is trained on the 200B tokens sampled from the OpenWebText dataset. The plot shows the result of (a) OpenWebText, (b) LAMBADA, (c) WikiText-103, (d) HellaSwag, (e) PIQA, (f) SIQA, (g) Arc-Easy, and (h) WinoGrande datasets. We use the concepts extracted from a 124M-sized model for training CoCoMix.", "description": "\uadf8\ub9bc 8\uc740 3\uc5b5 6\ucc9c 8\ubc31\ub9cc\uac1c\uc758 \ud30c\ub77c\ubbf8\ud130\ub97c \uac00\uc9c4 \ubaa8\ub378\uc5d0 \ub300\ud55c CoCoMix\uc640 NTP\uc758 \uc131\ub2a5\uc744 \ub2e4\uc591\ud55c \ud6c8\ub828 \uc9c0\uc810\uc5d0\uc11c \ube44\uad50\ud55c \uadf8\ub798\ud504\uc785\ub2c8\ub2e4. \uac01 \ubaa8\ub378\uc740 OpenWebText \ub370\uc774\ud130\uc14b\uc5d0\uc11c \uc0d8\ud50c\ub9c1\ub41c 2000\uc5b5\uac1c\uc758 \ud1a0\ud070\uc73c\ub85c \ud559\uc2b5\ub418\uc5c8\uc73c\uba70, CoCoMix \ud559\uc2b5\uc5d0\ub294 1\uc5b5 2\ucc9c 4\ubc31\ub9cc\uac1c \ud30c\ub77c\ubbf8\ud130\uc758 \ubaa8\ub378\uc5d0\uc11c \ucd94\ucd9c\ud55c \uac1c\ub150\uc774 \uc0ac\uc6a9\ub418\uc5c8\uc2b5\ub2c8\ub2e4. \uadf8\ub798\ud504\ub294 OpenWebText, LAMBADA, WikiText-103, HellaSwag, PIQA, SIQA, Arc-Easy \ubc0f WinoGrande \ub370\uc774\ud130\uc14b\uc5d0 \ub300\ud55c \uacb0\uacfc\ub97c \ubcf4\uc5ec\uc90d\ub2c8\ub2e4.", "section": "3 Experiments"}, {"figure_path": "https://arxiv.org/html/2502.08524/x45.png", "caption": "(a) OpenWebText, PPL (\u2193\u2193\\downarrow\u2193)", "description": "\uadf8\ub9bc 2\ub294 1.38B \ub9e4\uac1c\ubcc0\uc218 \ubaa8\ub378\uc5d0 \ub300\ud574 \ub2e4\uc591\ud55c \ud6c8\ub828 \uccb4\ud06c\ud3ec\uc778\ud2b8\uc5d0\uc11c CoCoMix\uc640 NTP\uc758 \uc131\ub2a5\uc744 \ube44\uad50\ud55c \uadf8\ub798\ud504\uc785\ub2c8\ub2e4. CoCoMix\ub294 \uac80\uc99d \ud37c\ud50c\ub809\uc11c\ud2f0, \ub78c\ub2e4\ub2e4, \uc704\ud0a4\ud14d\uc2a4\ud2b8-103\uc5d0\uc11c \ud3c9\uade0 \ud37c\ud50c\ub809\uc11c\ud2f0 \ubc0f \ud5ec\ub77c\uc2a4\uc6e8\uadf8, PIQA, SIQA, \uc544\ud06c-\uc774\uc9c0 \ubc0f \uc704\ub178\uadf8\ub780\ub370\uc5d0\uc11c \ud3c9\uade0 \uc815\ud655\ub3c4 \uce21\uba74\uc5d0\uc11c NTP\ubcf4\ub2e4 \uc6b0\uc218\ud55c \uc131\ub2a5\uc744 \ubcf4\uc785\ub2c8\ub2e4. \uc774\ub294 CoCoMix\uac00 \ub2e4\uc591\ud55c \uc5b8\uc5b4 \ubaa8\ub378\ub9c1 \ubca4\uce58\ub9c8\ud06c\uc5d0\uc11c \ub354\uc6b1 \ud6a8\uc728\uc801\uc774\uace0 \uc77c\uad00\ub418\uac8c \uc6b0\uc218\ud55c \uc131\ub2a5\uc744 \ubcf4\uc784\uc744 \uc2dc\uc0ac\ud569\ub2c8\ub2e4.", "section": "3 Experiments"}, {"figure_path": "https://arxiv.org/html/2502.08524/x46.png", "caption": "(b) LAMBADA, PPL (\u2193\u2193\\downarrow\u2193)", "description": "\uadf8\ub9bc (b)\ub294 LAMBADA \ub370\uc774\ud130\uc14b\uc5d0 \ub300\ud55c \ud37c\ud50c\ub809\uc11c\ud2f0(perplexity)\ub97c \ub098\ud0c0\ub0c5\ub2c8\ub2e4.  \ud37c\ud50c\ub809\uc11c\ud2f0\ub294 \uc5b8\uc5b4 \ubaa8\ub378\uc774 \ud14d\uc2a4\ud2b8\ub97c \uc5bc\ub9c8\ub098 \uc798 \uc608\uce21\ud558\ub294\uc9c0 \uce21\uc815\ud558\ub294 \uc9c0\ud45c\ub85c, \uac12\uc774 \ub0ae\uc744\uc218\ub85d \uc131\ub2a5\uc774 \uc88b\uc74c\uc744 \uc758\ubbf8\ud569\ub2c8\ub2e4. \uc774 \uadf8\ub798\ud504\ub294 \ub2e4\uc591\ud55c \ud6c8\ub828 \ud1a0\ud070 \uc218\uc5d0 \ub530\ub978 CoCoMix\uc640 NTP(Next Token Prediction) \ubaa8\ub378\uc758 \ud37c\ud50c\ub809\uc11c\ud2f0\ub97c \ube44\uad50\ud558\uc5ec CoCoMix \ubaa8\ub378\uc774 \ub354 \ub0ae\uc740 \ud37c\ud50c\ub809\uc11c\ud2f0 \uac12\uc744 \uac00\uc9c0\uba70, \ub530\ub77c\uc11c \ub354 \uc6b0\uc218\ud55c \uc131\ub2a5\uc744 \ubcf4\uc784\uc744 \uc2dc\uac01\uc801\uc73c\ub85c \ubcf4\uc5ec\uc90d\ub2c8\ub2e4.  \uc989,  CoCoMix\ub294 \ub354 \uc801\uc740 \ud6c8\ub828 \ub370\uc774\ud130\ub85c\ub3c4 \ub354 \ub098\uc740 \uacb0\uacfc\ub97c \ub2ec\uc131\ud569\ub2c8\ub2e4.", "section": "3 Experiments"}, {"figure_path": "https://arxiv.org/html/2502.08524/x47.png", "caption": "(c) WikiText-103, PPL (\u2193\u2193\\downarrow\u2193)", "description": "\uadf8\ub9bc (c)\ub294 WikiText-103 \ub370\uc774\ud130\uc14b\uc5d0 \ub300\ud55c perplexity(PPL) \ubcc0\ud654\ub97c \ubcf4\uc5ec\uc90d\ub2c8\ub2e4.  Perplexity\ub294 \uc5b8\uc5b4 \ubaa8\ub378\uc758 \uc131\ub2a5\uc744 \ud3c9\uac00\ud558\ub294 \uc9c0\ud45c\ub85c, \uac12\uc774 \ub0ae\uc744\uc218\ub85d \ubaa8\ub378\uc758 \uc131\ub2a5\uc774 \uc88b\ub2e4\ub294 \uac83\uc744 \uc758\ubbf8\ud569\ub2c8\ub2e4.  \uc774 \uadf8\ub798\ud504\ub294 \ud559\uc2b5 \ud1a0\ud070\uc758 \uc218\uac00 \uc99d\uac00\ud568\uc5d0 \ub530\ub77c CoCoMix\uc640 NTP \ubaa8\ub378\uc758 perplexity\uac00 \uc5b4\ub5bb\uac8c \ubcc0\ud654\ud558\ub294\uc9c0 \ube44\uad50 \ubd84\uc11d\ud569\ub2c8\ub2e4.  \ub0ae\uc740 perplexity \uac12\uc744 \uc720\uc9c0\ud558\ub294 \ubaa8\ub378\uc774 \ub354 \uc88b\uc740 \uc131\ub2a5\uc744 \ub098\ud0c0\ub0c5\ub2c8\ub2e4.", "section": "3 Experiments"}, {"figure_path": "https://arxiv.org/html/2502.08524/x48.png", "caption": "(d) HellaSwag, Acc-n (\u2191\u2191\\uparrow\u2191)", "description": "\uadf8\ub9bc (d)\ub294 HellaSwag \ub370\uc774\ud130\uc14b\uc5d0 \ub300\ud55c \uc815\ud655\ub3c4(Acc-n)\ub97c \ubcf4\uc5ec\uc90d\ub2c8\ub2e4.  HellaSwag\ub294 \uc0c1\uc2dd\uc801 \ucd94\ub860 \ub2a5\ub825\uc744 \ud3c9\uac00\ud558\ub294 \ubca4\uce58\ub9c8\ud06c \ub370\uc774\ud130\uc14b\uc774\uba70, Acc-n\uc740 \uc815\ub2f5\ub960\uc744 \ub098\ud0c0\ub0c5\ub2c8\ub2e4.  \uc774 \uadf8\ub9bc\uc740 CoCoMix \ubaa8\ub378\uc774 \uae30\uc874\uc758 \ub2e4\uc74c \ud1a0\ud070 \uc608\uce21(NTP) \ubaa8\ub378\ubcf4\ub2e4 HellaSwag \ub370\uc774\ud130\uc14b\uc5d0\uc11c \ub354 \ub192\uc740 \uc815\ud655\ub3c4\ub97c \ub2ec\uc131\ud588\uc74c\uc744 \uc2dc\uac01\uc801\uc73c\ub85c \ubcf4\uc5ec\uc90d\ub2c8\ub2e4.  \uc989, CoCoMix \ubaa8\ub378\uc774 \uc0c1\uc2dd\uc801 \ucd94\ub860 \uacfc\uc81c\uc5d0\uc11c \ub354 \ub098\uc740 \uc131\ub2a5\uc744 \ubcf4\uc600\ub2e4\ub294 \uac83\uc744 \uc758\ubbf8\ud569\ub2c8\ub2e4.  \ub450 \uac1c\uc758 \ud654\uc0b4\ud45c\ub294 \uc815\ud655\ub3c4 \ud5a5\uc0c1\uc758 \uc815\ub3c4\uac00 \ub9e4\uc6b0 \ud06c\ub2e4\ub294 \uac83\uc744 \uac15\uc870\ud569\ub2c8\ub2e4.", "section": "3 Experiments"}, {"figure_path": "https://arxiv.org/html/2502.08524/x49.png", "caption": "(e) PIQA, Acc (\u2191\u2191\\uparrow\u2191)", "description": "\uadf8\ub9bc (e)\ub294 PIQA \ub370\uc774\ud130\uc14b\uc5d0 \ub300\ud55c CoCoMix \ubaa8\ub378\uc758 \uc815\ud655\ub3c4\ub97c \ubcf4\uc5ec\uc90d\ub2c8\ub2e4.  'Acc (\u2191\u2191)'\ub294 \uc815\ud655\ub3c4\uac00 \uc0c1\ub2f9\ud788 \ud5a5\uc0c1\ub418\uc5c8\uc74c\uc744 \uc758\ubbf8\ud569\ub2c8\ub2e4.  PIQA\ub294 \ubb3c\uc74c\uacfc \ub2f5\ubcc0\uc758 \uc9dd\uc73c\ub85c \uad6c\uc131\ub41c \ub370\uc774\ud130\uc14b\uc73c\ub85c, \ubaa8\ub378\uc758 \ucd94\ub860 \ub2a5\ub825\uc744 \ud3c9\uac00\ud558\ub294 \ub370 \uc0ac\uc6a9\ub429\ub2c8\ub2e4. \uc774 \uadf8\ub9bc\uc740 CoCoMix \ubaa8\ub378\uc774 PIQA \ub370\uc774\ud130\uc14b\uc5d0\uc11c \uae30\uc874\uc758 \ub2e4\uc74c \ud1a0\ud070 \uc608\uce21 (NTP) \ubaa8\ub378\ubcf4\ub2e4 \ud6e8\uc52c \ub192\uc740 \uc815\ud655\ub3c4\ub97c \ub2ec\uc131\ud588\uc74c\uc744 \uc2dc\uac01\uc801\uc73c\ub85c \ubcf4\uc5ec\uc90d\ub2c8\ub2e4.", "section": "3 Experiments"}]